Workbook
Name CRF: #REF!
Name DiscountRate: #REF!
Name FacilityLifetime: #REF!
Name GeneralDataManufacturingLocations: #REF!
Name MaterialData316SSStandardDensity: #REF!
Name MaterialDataA36CSStandardDensity: #REF!
Name MaterialDataB4CNaturalTheoreticalDensity: #REF!
Name MaterialDataConcreteNominalSolidDensity: #REF!
Name MaterialDataGeneralInsulationStandardDensity: #REF!
Name MaterialDataGR22StandardDensity: #REF!
Name MaterialDataInconel718StandardDensity: #REF!
Name UC_m_in: #REF!

Sheet Cost Database
A1: Account | B1: Level | C1: Account Name | D1: Account Title | E1: Standard Cost Equation? | F1: Optional Variable | G1: Optional Value | H1: Sec Optional Variable | I1: Sec Optional Value | J1: Fixed Cost ($) | K1: Unit Cost | L1: Unit Cost (units) | M1: Scaling Variable | N1: Scaling Variable Ref Value | O1: Units | P1: Exponent | Q1: Dollar Year | R1: Type | S1: Source | T1: Ref | U1: Link | V1: Notes | W1: FOAK to NOAK Multiplier Type | X1: Fixed Cost Low End | Y1: Fixed Cost High End | Z1: Fixed Cost Distribution | AA1: Unit Cost Low End | AB1: Unit Cost High End | AC1: Unit Cost Distribution | AD1: Exponent std | AE1: Exponent Max | AF1: Exponent Min | AG1: Exponent Distribution
A2: 10 | B2: 0 | C2: Capitalized Pre-Construction Costs | D2: =REPT(" ", B2*2) & C2
A3: 11 | B3: 1 | C3: Land Cost | D3: =REPT(" ", B3*2) & C3 | E3: standard | K3: 3800 | L3: $/acres | M3: Land Area | O3: acres | Q3: 2022 | R3: General | S3: The average cost per acre for rural land in 2022 from the US Department of Agriculture | T3: Abou-Jaoude, A., Lohse, C. S., Larsen, L. M., Guaita, N., Trivedi, I., Joseck, F. C., ... & Stein, A. (2024). Meta-analysis of advanced nuclear reactor cost estimations (No. INL/RPT-24-77048-Rev001). Idaho National Laboratory (INL), Idaho Falls, ID (United States). | U3: https://inldigitallibrary.inl.gov/sites/sti/sti/Sort_107010.pdf | W3: No Learning | X3: =0.9*$J3 | Y3: =1.5*J3 | Z3: Lognormal | AA3: =0.9*K3 | AB3: =1.3*K3 | AC3: Lognormal | AD3: 0.1 | AE3: 1 | AF3: 0 | AG3: Truncated Normal
A4: 12 | B4: 1 | C4: Site Permits | D4: =REPT(" ", B4*2) & C4 | E4: standard | K4: =10.03*1000 | L4: $/MWe | M4: Power MWe | O4: MWe | Q4: 2022 | R4: Labor | S4: Data from SMR MHTGRs | W4: No Learning | X4: =0.9*$J4 | Y4: =1.5*J4 | Z4: Lognormal | AA4: =0.9*K4 | AB4: =1.3*K4 | AC4: Lognormal | AD4: 0.1 | AE4: 1 | AF4: 0 | AG4: Truncated Normal
A5: 13 | B5: 1 | C5: Plant Licensing | D5: =REPT(" ", B5*2) & C5 | E5: standard | J5: =0.5*(X5+Y5) | Q5: 2024 | R5: Labor | S5: NRC Website | T5: Using data from the NRC website that the cost is between 45 and 70M https://www.nrc.gov/about-nrc/regulatory/licensing/general-fee-questions.pdf Also, using recent change to the NRC fees by a factor of 0.47 https://ignition-news.com/the-nrc-passes-new-rules-for-advanced-reactor-companies/#:~:text=Under%20a%20rule%20published%20in,2024%2C%20which%20takes%20effect%20Oct. | U5: https://art.inl.gov/NGNP/INL%20Documents/Year%202012/Assessment%20of%20High%20Temperature%20Gas-Cooled%20Reactor%20-%20HTGR%20-%20Capital%20and%20Operating%20Costs.pdf | W5: Licensing Learning | X5: =0.47*45*1000000 | Y5: =0.47*70*1000000 | Z5: Uniform | AA5: =0.9*K5 | AB5: =1.3*K5 | AC5: Lognormal | AD5: 0.1 | AE5: 1 | AF5: 0 | AG5: Truncated Normal
A6: 14 | B6: 1 | C6: Plant Permits | D6: =REPT(" ", B6*2) & C6 | E6: standard | J6: 3000000 | Q6: 2009 | R6: Labor | S6: NGNP project | T6: Gandrik, A., B. Wallace, L. Demick, S. Melancon and M. Patterson (2011). "Assessment of high temperature gas-cooled reactor (HTGR) capital and operating costs." Idaho National Laboratory, TEV-1196, Idaho Falls, ID. | W6: No Learning | X6: =0.9*$J6 | Y6: =1.5*J6 | Z6: Lognormal | AA6: =0.9*K6 | AB6: =1.3*K6 | AC6: Lognormal | AD6: 0.1 | AE6: 1 | AF6: 0 | AG6: Truncated Normal
A7: 15 | B7: 1 | C7: Plant Studies | D7: =REPT(" ", B7*2) & C7 | E7: standard | J7: =MARVEL_Cost!C4 | Q7: 2024 | R7: Labor | S7: MARVEL Project (Labor-adjusted Cost) | T7: Hanna, B. N., Gonzaga de Oliveira, R. G., Mohammad Al Dawood, K. A., Patterson, M. D., Abou Jaoude, A., & Garcia, S. (2024). Technoeconomic Evaluation of Microreactor Using Detailed Bottom-up Estimate (No. INL/RPT-24-80433-Rev000). Idaho National Laboratory (INL), Idaho Falls, ID (United States). | U7: https://inldigitallibrary.inl.gov/sites/sti/sti/Sort_129862.pdf | V7: MARVEL's data were updated | W7: No Learning | X7: =0.9*$J7 | Y7: =1.5*J7 | Z7: Lognormal | AA7: =0.9*K7 | AB7: =1.3*K7 | AC7: Lognormal | AD7: 0.1 | AE7: 1 | AF7: 0 | AG7: Truncated Normal
A8: 20 | B8: 0 | C8: Capitalized Direct Costs | D8: =REPT(" ", B8*2) & C8
A9: 21 | B9: 1 | C9: Structures and Improvements | D9: =REPT(" ", B9*2) & C9
A10: 211 | B10: 2 | C10: Site Preparation/ Yard Work | D10: =REPT(" ", B10*2) & C10
A11: 211.1 | B11: 3 | C11: Cleaning and Grubbing | D11: =REPT(" ", B11*2) & C11 | E11: standard | K11: =4408.18*1.33 | L11: $/acres | M11: Land Area | O11: acres | Q11: 2024 | R11: Lab and Equip | S11: RSMeans software: a tool that primarily provides costs for non-nuclear work Nuclear Multiplier have been applied to adjust the costs for nuclear-site-related work | T11: GORDIAN. (2024). "RSMeans data. & Delene, J. G. and I. Hudson, C. R. (1993). Cost estimate guidelines for advanced nuclear power technologies. United States, Oak Ridge National Lab. (ORNL), Oak Ridge, TN (United States): Medium: ED; Size: 159 p. | U11: https://www.rsmeans.com/ & https://www.osti.gov/biblio/10176857 | W11: Onsite Learning | X11: =0.9*$J11 | Y11: =1.5*J11 | Z11: Lognormal | AA11: =0.9*K11 | AB11: =1.3*K11 | AC11: Lognormal | AD11: 0.1 | AE11: 1 | AF11: 0 | AG11: Truncated Normal
A12: 211.2 | B12: 3 | C12: Stripping Topsoil | D12: =REPT(" ", B12*2) & C12 | E12: standard | K12: =2565.2*1.33 | L12: $/acres | M12: Land Area | O12: acres | Q12: 2024 | R12: Lab and Equip | W12: Onsite Learning | X12: =0.9*$J12 | Y12: =1.5*J12 | Z12: Lognormal | AA12: =0.9*K12 | AB12: =1.3*K12 | AC12: Lognormal | AD12: 0.1 | AE12: 1 | AF12: 0 | AG12: Truncated Normal
A13: 211.3 | B13: 3 | C13: Excavation | D13: =REPT(" ", B13*2) & C13 | E13: standard | K13: =22.86*1.4 | L13: $/m^3 | M13: Excavation Volume | O13: m^3 | Q13: 2024 | R13: Lab and Equip | W13: Onsite Learning | X13: =0.9*$J13 | Y13: =1.5*J13 | Z13: Lognormal | AA13: =0.9*K13 | AB13: =1.3*K13 | AC13: Lognormal | AD13: 0.1 | AE13: 1 | AF13: 0 | AG13: Truncated Normal
A14: 212 | B14: =IF(ISNUMBER(A14), IF(AND(A14=INT(A14), MOD(A14, 10) = 0), 0, IF(AND(A14=INT(A14), LEN(A14)=2), 1, IF(AND(A14=INT(A14), LEN(A14)=3), 2, LEN(A14) - FIND(".", A14) + 2) ) ), "") | C14: Reactor Island Civil Structures | D14: =REPT(" ", B14*2) & C14
A15: 212.1 | B15: =IF(ISNUMBER(A15), IF(AND(A15=INT(A15), MOD(A15, 10) = 0), 0, IF(AND(A15=INT(A15), LEN(A15)=2), 1, IF(AND(A15=INT(A15), LEN(A15)=3), 2, LEN(A15) - FIND(".", A15) + 2) ) ), "") | C15: Reactor Building Slab Roof | D15: =REPT(" ", B15*2) & C15 | E15: standard | K15: =1200 *1.53 | L15: $/m^3 | M15: Reactor Building Slab Roof Volume | O15: m^3 | Q15: 2024 | R15: Lab and Mat and Equip | S15: RSMeans software: a tool that primarily provides costs for non-nuclear work Nuclear Multiplier have been applied to adjust the costs for nuclear-site-related work | T15: GORDIAN. (2024). "RSMeans data. & Delene, J. G. and I. Hudson, C. R. (1993). Cost estimate guidelines for advanced nuclear power technologies. United States, Oak Ridge National Lab. (ORNL), Oak Ridge, TN (United States): Medium: ED; Size: 159 p. | U15: https://www.rsmeans.com/ & https://www.osti.gov/biblio/10176857 | W15: Onsite Learning | X15: =0.9*$J15 | Y15: =1.5*J15 | Z15: Lognormal | AA15: =0.9*K15 | AB15: =1.3*K15 | AC15: Lognormal | AD15: 0.1 | AE15: 1 | AF15: 0 | AG15: Truncated Normal
A16: 212.2 | B16: =IF(ISNUMBER(A16), IF(AND(A16=INT(A16), MOD(A16, 10) = 0), 0, IF(AND(A16=INT(A16), LEN(A16)=2), 1, IF(AND(A16=INT(A16), LEN(A16)=3), 2, LEN(A16) - FIND(".", A16) + 2) ) ), "") | C16: Reactor Building Basement | D16: =REPT(" ", B16*2) & C16 | E16: standard | K16: =943.9*1.53 | L16: $/m^3 | M16: Reactor Building Basement Volume | O16: m^3 | Q16: 2024 | R16: Lab and Mat and Equip | W16: Onsite Learning | X16: =0.9*$J16 | Y16: =1.5*J16 | Z16: Lognormal | AA16: =0.9*K16 | AB16: =1.3*K16 | AC16: Lognormal | AD16: 0.1 | AE16: 1 | AF16: 0 | AG16: Truncated Normal
A17: 212.3 | B17: =IF(ISNUMBER(A17), IF(AND(A17=INT(A17), MOD(A17, 10) = 0), 0, IF(AND(A17=INT(A17), LEN(A17)=2), 1, IF(AND(A17=INT(A17), LEN(A17)=3), 2, LEN(A17) - FIND(".", A17) + 2) ) ), "") | C17: Reactor Building Walls | D17: =REPT(" ", B17*2) & C17 | E17: standard | K17: =721.21*1.53 | L17: $/m^3 | M17: Reactor Building Exterior Walls Volume | O17: m^3 | Q17: 2024 | R17: Lab and Mat and Equip | W17: Onsite Learning | X17: =0.9*$J17 | Y17: =1.5*J17 | Z17: Lognormal | AA17: =0.9*K17 | AB17: =1.3*K17 | AC17: Lognormal | AD17: 0.1 | AE17: 1 | AF17: 0 | AG17: Truncated Normal
A18: 212.4 | B18: =IF(ISNUMBER(A18), IF(AND(A18=INT(A18), MOD(A18, 10) = 0), 0, IF(AND(A18=INT(A18), LEN(A18)=2), 1, IF(AND(A18=INT(A18), LEN(A18)=3), 2, LEN(A18) - FIND(".", A18) + 2) ) ), "") | C18: Reactor Building Liner | D18: =REPT(" ", B18*2) & C18 | E18: standard | K18: =60848829/9373 | L18: $/m^2 | M18: Reactor Building Superstructure Area | N18: 9373 | O18: m^2 | P18: 1 | Q18: 2018 | R18: Lab and Mat and Equip | S18: Stewart W.R., Shirvan K., "Capital cost estimation for advanced nuclear power plants," Renewable and Sustainable Energy Reviews, Nov. 2021, 111880 | T18: Stewart W.R., Shirvan K., "Capital cost estimation for advanced nuclear power plants," Renewable and Sustainable Energy Reviews, Nov. 2021, 111880 | U18: https://doi.org/10.1016/j.rser.2021.111880 | W18: Onsite Learning | X18: =0.9*$J18 | Y18: =1.5*J18 | Z18: Lognormal | AA18: =0.9*K18 | AB18: =1.3*K18 | AC18: Lognormal | AD18: 0.1 | AE18: 1 | AF18: 0 | AG18: Truncated Normal
A19: 212.5 | B19: =IF(ISNUMBER(A19), IF(AND(A19=INT(A19), MOD(A19, 10) = 0), 0, IF(AND(A19=INT(A19), LEN(A19)=2), 1, IF(AND(A19=INT(A19), LEN(A19)=3), 2, LEN(A19) - FIND(".", A19) + 2) ) ), "") | C19: Reactor Building HVAC | D19: =REPT(" ", B19*2) & C19 | E19: standard | K19: =5917967/N19 | L19: $/MWt | M19: Power MWt | N19: 3417 | O19: MWt | P19: 0.8 | Q19: 2018 | R19: Lab and Mat and Equip | S19: Stewart W.R., Shirvan K., "Capital cost estimation for advanced nuclear power plants," Renewable and Sustainable Energy Reviews, Nov. 2021, 111880 | T19: Stewart W.R., Shirvan K., "Capital cost estimation for advanced nuclear power plants," Renewable and Sustainable Energy Reviews, Nov. 2021, 111880 | U19: https://doi.org/10.1016/j.rser.2021.111880 | W19: Onsite Learning | X19: =0.9*$J19 | Y19: =1.5*J19 | Z19: Lognormal | AA19: =0.9*K19 | AB19: =1.3*K19 | AC19: Lognormal | AD19: 0.1 | AE19: 1 | AF19: 0 | AG19: Truncated Normal
A20: 213 | B20: =IF(ISNUMBER(A20), IF(AND(A20=INT(A20), MOD(A20, 10) = 0), 0, IF(AND(A20=INT(A20), LEN(A20)=2), 1, IF(AND(A20=INT(A20), LEN(A20)=3), 2, LEN(A20) - FIND(".", A20) + 2) ) ), "") | C20: Main Function Buildings | D20: =REPT(" ", B20*2) & C20
A21: 213.1 | B21: =IF(ISNUMBER(A21), IF(AND(A21=INT(A21), MOD(A21, 10) = 0), 0, IF(AND(A21=INT(A21), LEN(A21)=2), 1, IF(AND(A21=INT(A21), LEN(A21)=3), 2, LEN(A21) - FIND(".", A21) + 2) ) ), "") | C21: Energy conversion Building | D21: =REPT(" ", B21*2) & C21
A22: 213.11 | B22: =IF(ISNUMBER(A22), IF(AND(A22=INT(A22), MOD(A22, 10) = 0), 0, IF(AND(A22=INT(A22), LEN(A22)=2), 1, IF(AND(A22=INT(A22), LEN(A22)=3), 2, LEN(A22) - FIND(".", A22) + 2) ) ), "") | C22: Energy Conversion Building Slab Roof | D22: =REPT(" ", B22*2) & C22 | E22: standard | K22: =1200 | L22: $/m^3 | M22: Turbine Building Slab Roof Volume | O22: m^3 | Q22: 2024 | R22: Lab and Mat and Equip | S22: RSMeans software: a tool that primarily provides costs for non-nuclear work | T22: GORDIAN. (2024). "RSMeans data. & Delene, J. G. and I. Hudson, C. R. (1993). Cost estimate guidelines for advanced nuclear power technologies. United States, Oak Ridge National Lab. (ORNL), Oak Ridge, TN (United States): Medium: ED; Size: 159 p. | U22: https://www.rsmeans.com/ & https://www.osti.gov/biblio/10176857 | W22: Onsite Learning | X22: =0.9*$J22 | Y22: =1.5*J22 | Z22: Lognormal | AA22: =0.9*K22 | AB22: =1.3*K22 | AC22: Lognormal | AD22: 0.1 | AE22: 1 | AF22: 0 | AG22: Truncated Normal
A23: 213.12 | B23: =IF(ISNUMBER(A23), IF(AND(A23=INT(A23), MOD(A23, 10) = 0), 0, IF(AND(A23=INT(A23), LEN(A23)=2), 1, IF(AND(A23=INT(A23), LEN(A23)=3), 2, LEN(A23) - FIND(".", A23) + 2) ) ), "") | C23: Energy Conversion Building Basement | D23: =REPT(" ", B23*2) & C23 | E23: standard | K23: =943.9 | L23: $/m^3 | M23: Turbine Building Basement Volume | O23: m^3 | Q23: 2024 | R23: Lab and Mat and Equip | W23: Onsite Learning | X23: =0.9*$J23 | Y23: =1.5*J23 | Z23: Lognormal | AA23: =0.9*K23 | AB23: =1.3*K23 | AC23: Lognormal | AD23: 0.1 | AE23: 1 | AF23: 0 | AG23: Truncated Normal
A24: 213.13 | B24: =IF(ISNUMBER(A24), IF(AND(A24=INT(A24), MOD(A24, 10) = 0), 0, IF(AND(A24=INT(A24), LEN(A24)=2), 1, IF(AND(A24=INT(A24), LEN(A24)=3), 2, LEN(A24) - FIND(".", A24) + 2) ) ), "") | C24: Energy Conversion Building Walls | D24: =REPT(" ", B24*2) & C24 | E24: standard | K24: =721.21 | L24: $/m^3 | M24: Turbine Building Exterior Walls Volume | O24: m^3 | Q24: 2024 | R24: Lab and Mat and Equip | W24: Onsite Learning | X24: =0.9*$J24 | Y24: =1.5*J24 | Z24: Lognormal | AA24: =0.9*K24 | AB24: =1.3*K24 | AC24: Lognormal | AD24: 0.1 | AE24: 1 | AF24: 0 | AG24: Truncated Normal
A25: 213.2 | B25: =IF(ISNUMBER(A25), IF(AND(A25=INT(A25), MOD(A25, 10) = 0), 0, IF(AND(A25=INT(A25), LEN(A25)=2), 1, IF(AND(A25=INT(A25), LEN(A25)=3), 2, LEN(A25) - FIND(".", A25) + 2) ) ), "") | C25: Control building | D25: =REPT(" ", B25*2) & C25
A26: 213.21 | B26: =IF(ISNUMBER(A26), IF(AND(A26=INT(A26), MOD(A26, 10) = 0), 0, IF(AND(A26=INT(A26), LEN(A26)=2), 1, IF(AND(A26=INT(A26), LEN(A26)=3), 2, LEN(A26) - FIND(".", A26) + 2) ) ), "") | C26: Control Building Slab Roof | D26: =REPT(" ", B26*2) & C26 | E26: standard | K26: =1200 | L26: $/m^3 | M26: Control Building Slab Roof Volume | O26: m^3 | Q26: 2024 | R26: Lab and Mat and Equip | S26: RSMeans software: a tool that primarily provides costs for non-nuclear work | T26: GORDIAN. (2024). "RSMeans data. & Delene, J. G. and I. Hudson, C. R. (1993). Cost estimate guidelines for advanced nuclear power technologies. United States, Oak Ridge National Lab. (ORNL), Oak Ridge, TN (United States): Medium: ED; Size: 159 p. | U26: https://www.rsmeans.com/ & https://www.osti.gov/biblio/10176857 | W26: Onsite Learning | X26: =0.9*$J26 | Y26: =1.5*J26 | Z26: Lognormal | AA26: =0.9*K26 | AB26: =1.3*K26 | AC26: Lognormal | AD26: 0.1 | AE26: 1 | AF26: 0 | AG26: Truncated Normal
A27: 213.22 | B27: =IF(ISNUMBER(A27), IF(AND(A27=INT(A27), MOD(A27, 10) = 0), 0, IF(AND(A27=INT(A27), LEN(A27)=2), 1, IF(AND(A27=INT(A27), LEN(A27)=3), 2, LEN(A27) - FIND(".", A27) + 2) ) ), "") | C27: Control Building Basement | D27: =REPT(" ", B27*2) & C27 | E27: standard | K27: =943.9 | L27: $/m^3 | M27: Control Building Basement Volume | O27: m^3 | Q27: 2024 | R27: Lab and Mat and Equip | W27: Onsite Learning | X27: =0.9*$J27 | Y27: =1.5*J27 | Z27: Lognormal | AA27: =0.9*K27 | AB27: =1.3*K27 | AC27: Lognormal | AD27: 0.1 | AE27: 1 | AF27: 0 | AG27: Truncated Normal
A28: 213.23 | B28: =IF(ISNUMBER(A28), IF(AND(A28=INT(A28), MOD(A28, 10) = 0), 0, IF(AND(A28=INT(A28), LEN(A28)=2), 1, IF(AND(A28=INT(A28), LEN(A28)=3), 2, LEN(A28) - FIND(".", A28) + 2) ) ), "") | C28: Control Building Walls | D28: =REPT(" ", B28*2) & C28 | E28: standard | K28: =721.21 | L28: $/m^3 | M28: Control Building Exterior Walls Volume | O28: m^3 | Q28: 2024 | R28: Lab and Mat and Equip | W28: Onsite Learning | X28: =0.9*$J28 | Y28: =1.5*J28 | Z28: Lognormal | AA28: =0.9*K28 | AB28: =1.3*K28 | AC28: Lognormal | AD28: 0.1 | AE28: 1 | AF28: 0 | AG28: Truncated Normal
A29: 213.3 | B29: =IF(ISNUMBER(A29), IF(AND(A29=INT(A29), MOD(A29, 10) = 0), 0, IF(AND(A29=INT(A29), LEN(A29)=2), 1, IF(AND(A29=INT(A29), LEN(A29)=3), 2, LEN(A29) - FIND(".", A29) + 2) ) ), "") | C29: Integrated Heat Exchanger Building | D29: =REPT(" ", B29*2) & C29 | F29: reactor type | G29: GCMR
A30: 213.31 | B30: =IF(ISNUMBER(A30), IF(AND(A30=INT(A30), MOD(A30, 10) = 0), 0, IF(AND(A30=INT(A30), LEN(A30)=2), 1, IF(AND(A30=INT(A30), LEN(A30)=3), 2, LEN(A30) - FIND(".", A30) + 2) ) ), "") | C30: Integrated Heat Exchanger Building Slab Roof | D30: =REPT(" ", B30*2) & C30 | E30: standard | F30: reactor type | G30: GCMR | K30: =1200 | L30: $/m^3 | M30: Integrated Heat Exchanger Building Slab Roof Volume | O30: m^3 | Q30: 2024 | R30: Lab and Mat and Equip | S30: RSMeans software: a tool that primarily provides costs for non-nuclear work | T30: GORDIAN. (2024). "RSMeans data. & Delene, J. G. and I. Hudson, C. R. (1993). Cost estimate guidelines for advanced nuclear power technologies. United States, Oak Ridge National Lab. (ORNL), Oak Ridge, TN (United States): Medium: ED; Size: 159 p. | U30: https://www.rsmeans.com/ & https://www.osti.gov/biblio/10176857 | W30: Onsite Learning | X30: =0.9*$J30 | Y30: =1.5*J30 | Z30: Lognormal | AA30: =0.9*K30 | AB30: =1.3*K30 | AC30: Lognormal | AD30: 0.1 | AE30: 1 | AF30: 0 | AG30: Truncated Normal
A31: 213.32 | B31: =IF(ISNUMBER(A31), IF(AND(A31=INT(A31), MOD(A31, 10) = 0), 0, IF(AND(A31=INT(A31), LEN(A31)=2), 1, IF(AND(A31=INT(A31), LEN(A31)=3), 2, LEN(A31) - FIND(".", A31) + 2) ) ), "") | C31: Integrated Heat Exchanger Building Basement | D31: =REPT(" ", B31*2) & C31 | E31: standard | F31: reactor type | G31: GCMR | K31: =943.9 | L31: $/m^3 | M31: Integrated Heat Exchanger Building Basement Volume | O31: m^3 | Q31: 2024 | R31: Lab and Mat and Equip | W31: Onsite Learning | X31: =0.9*$J31 | Y31: =1.5*J31 | Z31: Lognormal | AA31: =0.9*K31 | AB31: =1.3*K31 | AC31: Lognormal | AD31: 0.1 | AE31: 1 | AF31: 0 | AG31: Truncated Normal
A32: 213.33 | B32: =IF(ISNUMBER(A32), IF(AND(A32=INT(A32), MOD(A32, 10) = 0), 0, IF(AND(A32=INT(A32), LEN(A32)=2), 1, IF(AND(A32=INT(A32), LEN(A32)=3), 2, LEN(A32) - FIND(".", A32) + 2) ) ), "") | C32: Integrated Heat Exchanger Building Walls | D32: =REPT(" ", B32*2) & C32 | E32: standard | F32: reactor type | G32: GCMR | K32: =721.21 | L32: $/m^3 | M32: Integrated Heat Exchanger Building Exterior Walls Volume | O32: m^3 | Q32: 2024 | R32: Lab and Mat and Equip | W32: Onsite Learning | X32: =0.9*$J32 | Y32: =1.5*J32 | Z32: Lognormal | AA32: =0.9*K32 | AB32: =1.3*K32 | AC32: Lognormal | AD32: 0.1 | AE32: 1 | AF32: 0 | AG32: Truncated Normal
A33: 213.34 | B33: =IF(ISNUMBER(A33), IF(AND(A33=INT(A33), MOD(A33, 10) = 0), 0, IF(AND(A33=INT(A33), LEN(A33)=2), 1, IF(AND(A33=INT(A33), LEN(A33)=3), 2, LEN(A33) - FIND(".", A33) + 2) ) ), "") | C33: Integrated Heat Exchanger Building Liner | D33: =REPT(" ", B33*2) & C33 | E33: standard | F33: reactor type | G33: GCMR | K33: =60848829/9373 | L33: $/m^2 | M33: Integrated Heat Exchanger Building Superstructure Area | N33: 9373 | O33: m^2 | P33: 1 | Q33: 2018 | R33: Lab and Mat and Equip | S33: Stewart W.R., Shirvan K., "Capital cost estimation for advanced nuclear power plants," Renewable and Sustainable Energy Reviews, Nov. 2021, 111880 | T33: Stewart W.R., Shirvan K., "Capital cost estimation for advanced nuclear power plants," Renewable and Sustainable Energy Reviews, Nov. 2021, 111880 | U33: https://doi.org/10.1016/j.rser.2021.111880 | W33: Onsite Learning | X33: =0.9*$J33 | Y33: =1.5*J33 | Z33: Lognormal | AA33: =0.9*K33 | AB33: =1.3*K33 | AC33: Lognormal | AD33: 0.1 | AE33: 1 | AF33: 0 | AG33: Truncated Normal
A34: 214 | B34: =IF(ISNUMBER(A34), IF(AND(A34=INT(A34), MOD(A34, 10) = 0), 0, IF(AND(A34=INT(A34), LEN(A34)=2), 1, IF(AND(A34=INT(A34), LEN(A34)=3), 2, LEN(A34) - FIND(".", A34) + 2) ) ), "") | C34: Buildings to Support Main Function | D34: =REPT(" ", B34*2) & C34
A35: 214.1 | B35: =IF(ISNUMBER(A35), IF(AND(A35=INT(A35), MOD(A35, 10) = 0), 0, IF(AND(A35=INT(A35), LEN(A35)=2), 1, IF(AND(A35=INT(A35), LEN(A35)=3), 2, LEN(A35) - FIND(".", A35) + 2) ) ), "") | C35: Fuel Management Buildings | D35: =REPT(" ", B35*2) & C35
A36: 214.11 | B36: =IF(ISNUMBER(A36), IF(AND(A36=INT(A36), MOD(A36, 10) = 0), 0, IF(AND(A36=INT(A36), LEN(A36)=2), 1, IF(AND(A36=INT(A36), LEN(A36)=3), 2, LEN(A36) - FIND(".", A36) + 2) ) ), "") | C36: Refueling Building | D36: =REPT(" ", B36*2) & C36
A37: 214.111 | B37: =IF(ISNUMBER(A37), IF(AND(A37=INT(A37), MOD(A37, 10) = 0), 0, IF(AND(A37=INT(A37), LEN(A37)=2), 1, IF(AND(A37=INT(A37), LEN(A37)=3), 2, LEN(A37) - FIND(".", A37) + 2) ) ), "") | C37: Refueling Building Slab Roof | D37: =REPT(" ", B37*2) & C37 | E37: standard | K37: =1200 *1.53 | L37: $/m^3 | M37: Refueling Building Slab Roof Volume | O37: m^3 | Q37: 2024 | R37: Lab and Mat and Equip | S37: RSMeans software: a tool that primarily provides costs for non-nuclear work Nuclear Multiplier have been applied to adjust the costs for nuclear-site-related work | T37: GORDIAN. (2024). "RSMeans data. & Delene, J. G. and I. Hudson, C. R. (1993). Cost estimate guidelines for advanced nuclear power technologies. United States, Oak Ridge National Lab. (ORNL), Oak Ridge, TN (United States): Medium: ED; Size: 159 p. | U37: https://www.rsmeans.com/ & https://www.osti.gov/biblio/10176857 | W37: Onsite Learning | X37: =0.9*$J37 | Y37: =1.5*J37 | AA37: =0.9*K37 | AB37: =1.3*K37 | AC37: Lognormal | AD37: 0.1 | AE37: 1 | AF37: 0 | AG37: Truncated Normal
A38: 214.112 | B38: =IF(ISNUMBER(A38), IF(AND(A38=INT(A38), MOD(A38, 10) = 0), 0, IF(AND(A38=INT(A38), LEN(A38)=2), 1, IF(AND(A38=INT(A38), LEN(A38)=3), 2, LEN(A38) - FIND(".", A38) + 2) ) ), "") | C38: Refueling Building Basement | D38: =REPT(" ", B38*2) & C38 | E38: standard | K38: =943.9*1.53 | L38: $/m^3 | M38: Refueling Building Basement Volume | O38: m^3 | Q38: 2024 | R38: Lab and Mat and Equip | W38: Onsite Learning | X38: =0.9*$J38 | Y38: =1.5*J38 | Z38: Lognormal | AA38: =0.9*K38 | AB38: =1.3*K38 | AC38: Lognormal | AD38: 0.1 | AE38: 1 | AF38: 0 | AG38: Truncated Normal
A39: 214.113 | B39: =IF(ISNUMBER(A39), IF(AND(A39=INT(A39), MOD(A39, 10) = 0), 0, IF(AND(A39=INT(A39), LEN(A39)=2), 1, IF(AND(A39=INT(A39), LEN(A39)=3), 2, LEN(A39) - FIND(".", A39) + 2) ) ), "") | C39: Refueling Building Walls | D39: =REPT(" ", B39*2) & C39 | E39: standard | K39: =721.21*1.53 | L39: $/m^3 | M39: Refueling Building Exterior Walls Volume | O39: m^3 | Q39: 2024 | R39: Lab and Mat and Equip | W39: Onsite Learning | X39: =0.9*$J39 | Y39: =1.5*J39 | Z39: Lognormal | AA39: =0.9*K39 | AB39: =1.3*K39 | AC39: Lognormal | AD39: 0.1 | AE39: 1 | AF39: 0 | AG39: Truncated Normal
A40: 214.12 | B40: =IF(ISNUMBER(A40), IF(AND(A40=INT(A40), MOD(A40, 10) = 0), 0, IF(AND(A40=INT(A40), LEN(A40)=2), 1, IF(AND(A40=INT(A40), LEN(A40)=3), 2, LEN(A40) - FIND(".", A40) + 2) ) ), "") | C40: Spent Fuel Building | D40: =REPT(" ", B40*2) & C40
A41: 214.121 | B41: =IF(ISNUMBER(A41), IF(AND(A41=INT(A41), MOD(A41, 10) = 0), 0, IF(AND(A41=INT(A41), LEN(A41)=2), 1, IF(AND(A41=INT(A41), LEN(A41)=3), 2, LEN(A41) - FIND(".", A41) + 2) ) ), "") | C41: Spent Fuel Building Slab Roof | D41: =REPT(" ", B41*2) & C41 | E41: standard | K41: =1200 *1.53 | L41: $/m^3 | M41: Spent Fuel Building Slab Roof Volume | O41: m^3 | Q41: 2024 | R41: Lab and Mat and Equip | S41: RSMeans software: a tool that primarily provides costs for non-nuclear work Nuclear Multiplier have been applied to adjust the costs for nuclear-site-related work | T41: GORDIAN. (2024). "RSMeans data. & Delene, J. G. and I. Hudson, C. R. (1993). Cost estimate guidelines for advanced nuclear power technologies. United States, Oak Ridge National Lab. (ORNL), Oak Ridge, TN (United States): Medium: ED; Size: 159 p. | U41: https://www.rsmeans.com/ & https://www.osti.gov/biblio/10176857 | W41: Onsite Learning | X41: =0.9*$J41 | Y41: =1.5*J41 | Z41: Lognormal | AA41: =0.9*K41 | AB41: =1.3*K41 | AC41: Lognormal | AD41: 0.1 | AE41: 1 | AF41: 0 | AG41: Truncated Normal
A42: 214.122 | B42: =IF(ISNUMBER(A42), IF(AND(A42=INT(A42), MOD(A42, 10) = 0), 0, IF(AND(A42=INT(A42), LEN(A42)=2), 1, IF(AND(A42=INT(A42), LEN(A42)=3), 2, LEN(A42) - FIND(".", A42) + 2) ) ), "") | C42: Spent Fuel Building Basement | D42: =REPT(" ", B42*2) & C42 | E42: standard | K42: =943.9*1.53 | L42: $/m^3 | M42: Spent Fuel Building Basement Volume | O42: m^3 | Q42: 2024 | R42: Lab and Mat and Equip | W42: Onsite Learning | X42: =0.9*$J42 | Y42: =1.5*J42 | Z42: Lognormal | AA42: =0.9*K42 | AB42: =1.3*K42 | AC42: Lognormal | AD42: 0.1 | AE42: 1 | AF42: 0 | AG42: Truncated Normal
A43: 214.123 | B43: =IF(ISNUMBER(A43), IF(AND(A43=INT(A43), MOD(A43, 10) = 0), 0, IF(AND(A43=INT(A43), LEN(A43)=2), 1, IF(AND(A43=INT(A43), LEN(A43)=3), 2, LEN(A43) - FIND(".", A43) + 2) ) ), "") | C43: Spent Fuel Building Walls | D43: =REPT(" ", B43*2) & C43 | E43: standard | K43: =721.21*1.53 | L43: $/m^3 | M43: Spent Fuel Building Exterior Walls Volume | O43: m^3 | Q43: 2024 | R43: Lab and Mat and Equip | W43: Onsite Learning | X43: =0.9*$J43 | Y43: =1.5*J43 | Z43: Lognormal | AA43: =0.9*K43 | AB43: =1.3*K43 | AC43: Lognormal | AD43: 0.1 | AE43: 1 | AF43: 0 | AG43: Truncated Normal
A44: 214.7 | B44: =IF(ISNUMBER(A44), IF(AND(A44=INT(A44), MOD(A44, 10) = 0), 0, IF(AND(A44=INT(A44), LEN(A44)=2), 1, IF(AND(A44=INT(A44), LEN(A44)=3), 2, LEN(A44) - FIND(".", A44) + 2) ) ), "") | C44: Emergency and Start-up Power Systems Building | D44: =REPT(" ", B44*2) & C44
A45: 214.71 | B45: 4 | C45: Emergency Building | D45: =REPT(" ", B45*2) & C45
A46: 214.711 | B46: =IF(ISNUMBER(A46), IF(AND(A46=INT(A46), MOD(A46, 10) = 0), 0, IF(AND(A46=INT(A46), LEN(A46)=2), 1, IF(AND(A46=INT(A46), LEN(A46)=3), 2, LEN(A46) - FIND(".", A46) + 2) ) ), "") | C46: Emergency Building Slab Roof | D46: =REPT(" ", B46*2) & C46 | E46: standard | K46: =1200 | L46: $/m^3 | M46: Emergency Building Slab Roof Volume | O46: m^3 | Q46: 2024 | R46: Lab and Mat and Equip | S46: RSMeans software: a tool that primarily provides costs for non-nuclear work | T46: GORDIAN. (2024). "RSMeans data. & Delene, J. G. and I. Hudson, C. R. (1993). Cost estimate guidelines for advanced nuclear power technologies. United States, Oak Ridge National Lab. (ORNL), Oak Ridge, TN (United States): Medium: ED; Size: 159 p. | U46: https://www.rsmeans.com/ & https://www.osti.gov/biblio/10176857 | W46: Onsite Learning | X46: =0.9*$J46 | Y46: =1.5*J46 | Z46: Lognormal | AA46: =0.9*K46 | AB46: =1.3*K46 | AC46: Lognormal | AD46: 0.1 | AE46: 1 | AF46: 0 | AG46: Truncated Normal
A47: 214.712 | B47: =IF(ISNUMBER(A47), IF(AND(A47=INT(A47), MOD(A47, 10) = 0), 0, IF(AND(A47=INT(A47), LEN(A47)=2), 1, IF(AND(A47=INT(A47), LEN(A47)=3), 2, LEN(A47) - FIND(".", A47) + 2) ) ), "") | C47: Emergency Building Basement | D47: =REPT(" ", B47*2) & C47 | E47: standard | K47: =943.9 | L47: $/m^3 | M47: Emergency Building Basement Volume | O47: m^3 | Q47: 2024 | R47: Lab and Mat and Equip | W47: Onsite Learning | X47: =0.9*$J47 | Y47: =1.5*J47 | Z47: Lognormal | AA47: =0.9*K47 | AB47: =1.3*K47 | AC47: Lognormal | AD47: 0.1 | AE47: 1 | AF47: 0 | AG47: Truncated Normal
A48: 214.713 | B48: =IF(ISNUMBER(A48), IF(AND(A48=INT(A48), MOD(A48, 10) = 0), 0, IF(AND(A48=INT(A48), LEN(A48)=2), 1, IF(AND(A48=INT(A48), LEN(A48)=3), 2, LEN(A48) - FIND(".", A48) + 2) ) ), "") | C48: Emergency Building Walls | D48: =REPT(" ", B48*2) & C48 | E48: standard | K48: =721.21 | L48: $/m^3 | M48: Emergency Building Exterior Walls Volume | O48: m^3 | Q48: 2024 | R48: Lab and Mat and Equip | W48: Onsite Learning | X48: =0.9*$J48 | Y48: =1.5*J48 | Z48: Lognormal | AA48: =0.9*K48 | AB48: =1.3*K48 | AC48: Lognormal | AD48: 0.1 | AE48: 1 | AF48: 0 | AG48: Truncated Normal
A49: 214.72 | B49: =IF(ISNUMBER(A49), IF(AND(A49=INT(A49), MOD(A49, 10) = 0), 0, IF(AND(A49=INT(A49), LEN(A49)=2), 1, IF(AND(A49=INT(A49), LEN(A49)=3), 2, LEN(A49) - FIND(".", A49) + 2) ) ), "") | C49: Diesel Generator | D49: =REPT(" ", B49*2) & C49 | E49: standard | K49: =MARVEL_Cost!C11/N49 | L49: $/MWt | M49: Power MWt | N49: ='Design Variables'!B3/1000 | O49: MWt | P49: 0.7 | Q49: 2024 | R49: Equipment | S49: MARVEL (for the cost of the diesel generator) The exponent is based on the work by Koruoush considering cost scaling from nuclear ad non nuclear power plants. When using the power as scaling variable, the exponent ranges between 0..6 and 0.8 so 0.7 is used here | T49: Hanna, B. N., Gonzaga de Oliveira, R. G., Mohammad Al Dawood, K. A., Patterson, M. D., Abou Jaoude, A., & Garcia, S. (2024). Technoeconomic Evaluation of Microreactor Using Detailed Bottom-up Estimate (No. INL/RPT-24-80433-Rev000). Idaho National Laboratory (INL), Idaho Falls, ID (United States). Stewart, W. R., & Shirvan, K. (2022). Capital cost estimation for advanced nuclear power plants. Renewable and Sustainable Energy Reviews, 155, 111880. | U49: https://inldigitallibrary.inl.gov/sites/sti/sti/Sort_129862.pdf https://www.sciencedirect.com/science/article/pii/S1364032121011473 | W49: Factory Other | X49: =0.9*$J49 | Y49: =1.5*J49 | Z49: Lognormal | AA49: =0.9*K49 | AB49: =1.3*K49 | AC49: Lognormal | AD49: 0.1 | AE49: 1 | AF49: 0 | AG49: Truncated Normal
A50: 214.8 | B50: =IF(ISNUMBER(A50), IF(AND(A50=INT(A50), MOD(A50, 10) = 0), 0, IF(AND(A50=INT(A50), LEN(A50)=2), 1, IF(AND(A50=INT(A50), LEN(A50)=3), 2, LEN(A50) - FIND(".", A50) + 2) ) ), "") | C50: Auxilliary Building | D50: =REPT(" ", B50*2) & C50
A51: 214.81 | B51: =IF(ISNUMBER(A51), IF(AND(A51=INT(A51), MOD(A51, 10) = 0), 0, IF(AND(A51=INT(A51), LEN(A51)=2), 1, IF(AND(A51=INT(A51), LEN(A51)=3), 2, LEN(A51) - FIND(".", A51) + 2) ) ), "") | C51: Maniplator Building | D51: =REPT(" ", B51*2) & C51
A52: 214.811 | B52: =IF(ISNUMBER(A52), IF(AND(A52=INT(A52), MOD(A52, 10) = 0), 0, IF(AND(A52=INT(A52), LEN(A52)=2), 1, IF(AND(A52=INT(A52), LEN(A52)=3), 2, LEN(A52) - FIND(".", A52) + 2) ) ), "") | C52: Manipulator Building Slab Roof | D52: =REPT(" ", B52*2) & C52 | E52: standard | K52: =1200 | L52: $/m^3 | M52: Manipulator Building Slab Roof Volume | O52: m^3 | Q52: 2024 | R52: Lab and Mat and Equip | S52: RSMeans software: a tool that primarily provides costs for non-nuclear work | T52: GORDIAN. (2024). "RSMeans data. & Delene, J. G. and I. Hudson, C. R. (1993). Cost estimate guidelines for advanced nuclear power technologies. United States, Oak Ridge National Lab. (ORNL), Oak Ridge, TN (United States): Medium: ED; Size: 159 p. | U52: https://www.rsmeans.com/ & https://www.osti.gov/biblio/10176857 | V52: Added a custom building for GCMR based on CAD drawing | W52: Onsite Learning | X52: =0.9*$J52 | Y52: =1.5*J52 | Z52: Lognormal | AA52: =0.9*K52 | AB52: =1.3*K52 | AC52: Lognormal | AD52: 0.1 | AE52: 1 | AF52: 0 | AG52: Truncated Normal
A53: 214.812 | B53: =IF(ISNUMBER(A53), IF(AND(A53=INT(A53), MOD(A53, 10) = 0), 0, IF(AND(A53=INT(A53), LEN(A53)=2), 1, IF(AND(A53=INT(A53), LEN(A53)=3), 2, LEN(A53) - FIND(".", A53) + 2) ) ), "") | C53: ManipulatorBuilding Basement | D53: =REPT(" ", B53*2) & C53 | E53: standard | K53: =943.9 | L53: $/m^3 | M53: Manipulator Building Basement Volume | O53: m^3 | Q53: 2024 | R53: Lab and Mat and Equip | W53: Onsite Learning | X53: =0.9*$J53 | Y53: =1.5*J53 | Z53: Lognormal | AA53: =0.9*K53 | AB53: =1.3*K53 | AC53: Lognormal | AD53: 0.1 | AE53: 1 | AF53: 0 | AG53: Truncated Normal
A54: 214.813 | B54: =IF(ISNUMBER(A54), IF(AND(A54=INT(A54), MOD(A54, 10) = 0), 0, IF(AND(A54=INT(A54), LEN(A54)=2), 1, IF(AND(A54=INT(A54), LEN(A54)=3), 2, LEN(A54) - FIND(".", A54) + 2) ) ), "") | C54: Manipulator Building Exterior Walls | D54: =REPT(" ", B54*2) & C54 | E54: standard | K54: =721.21 | L54: $/m^3 | M54: Manipulator Building Exterior Walls Volume | O54: m^3 | Q54: 2024 | R54: Lab and Mat and Equip | W54: Onsite Learning | X54: =0.9*$J54 | Y54: =1.5*J54 | Z54: Lognormal | AA54: =0.9*K54 | AB54: =1.3*K54 | AC54: Lognormal | AD54: 0.1 | AE54: 1 | AF54: 0 | AG54: Truncated Normal
A55: 215 | B55: =IF(ISNUMBER(A55), IF(AND(A55=INT(A55), MOD(A55, 10) = 0), 0, IF(AND(A55=INT(A55), LEN(A55)=2), 1, IF(AND(A55=INT(A55), LEN(A55)=3), 2, LEN(A55) - FIND(".", A55) + 2) ) ), "") | C55: Supply Chain Buildings | D55: =REPT(" ", B55*2) & C55
A56: 215.1 | B56: =IF(ISNUMBER(A56), IF(AND(A56=INT(A56), MOD(A56, 10) = 0), 0, IF(AND(A56=INT(A56), LEN(A56)=2), 1, IF(AND(A56=INT(A56), LEN(A56)=3), 2, LEN(A56) - FIND(".", A56) + 2) ) ), "") | C56: Storage Building | D56: =REPT(" ", B56*2) & C56
A57: 215.11 | B57: =IF(ISNUMBER(A57), IF(AND(A57=INT(A57), MOD(A57, 10) = 0), 0, IF(AND(A57=INT(A57), LEN(A57)=2), 1, IF(AND(A57=INT(A57), LEN(A57)=3), 2, LEN(A57) - FIND(".", A57) + 2) ) ), "") | C57: Storage Building Slab Roof | D57: =REPT(" ", B57*2) & C57 | E57: standard | K57: =1200 | L57: $/m^3 | M57: Storage Building Slab Roof Volume | O57: m^3 | Q57: 2024 | R57: Lab and Mat and Equip | S57: RSMeans software: a tool that primarily provides costs for non-nuclear work | T57: GORDIAN. (2024). "RSMeans data. & Delene, J. G. and I. Hudson, C. R. (1993). Cost estimate guidelines for advanced nuclear power technologies. United States, Oak Ridge National Lab. (ORNL), Oak Ridge, TN (United States): Medium: ED; Size: 159 p. | U57: https://www.rsmeans.com/ & https://www.osti.gov/biblio/10176857 | W57: Onsite Learning | X57: =0.9*$J57 | Y57: =1.5*J57 | Z57: Lognormal | AA57: =0.9*K57 | AB57: =1.3*K57 | AC57: Lognormal | AD57: 0.1 | AE57: 1 | AF57: 0 | AG57: Truncated Normal
A58: 215.12 | B58: =IF(ISNUMBER(A58), IF(AND(A58=INT(A58), MOD(A58, 10) = 0), 0, IF(AND(A58=INT(A58), LEN(A58)=2), 1, IF(AND(A58=INT(A58), LEN(A58)=3), 2, LEN(A58) - FIND(".", A58) + 2) ) ), "") | C58: Storage Building Basement | D58: =REPT(" ", B58*2) & C58 | E58: standard | K58: =943.9 | L58: $/m^3 | M58: Storage Building Basement Volume | O58: m^3 | Q58: 2024 | R58: Lab and Mat and Equip | W58: Onsite Learning | X58: =0.9*$J58 | Y58: =1.5*J58 | Z58: Lognormal | AA58: =0.9*K58 | AB58: =1.3*K58 | AC58: Lognormal | AD58: 0.1 | AE58: 1 | AF58: 0 | AG58: Truncated Normal
A59: 215.13 | B59: =IF(ISNUMBER(A59), IF(AND(A59=INT(A59), MOD(A59, 10) = 0), 0, IF(AND(A59=INT(A59), LEN(A59)=2), 1, IF(AND(A59=INT(A59), LEN(A59)=3), 2, LEN(A59) - FIND(".", A59) + 2) ) ), "") | C59: Storage Building Walls | D59: =REPT(" ", B59*2) & C59 | E59: standard | K59: =721.21 | L59: $/m^3 | M59: Storage Building Exterior Walls Volume | O59: m^3 | Q59: 2024 | R59: Lab and Mat and Equip | W59: Onsite Learning | X59: =0.9*$J59 | Y59: =1.5*J59 | Z59: Lognormal | AA59: =0.9*K59 | AB59: =1.3*K59 | AC59: Lognormal | AD59: 0.1 | AE59: 1 | AF59: 0 | AG59: Truncated Normal
A60: 215.4 | B60: =IF(ISNUMBER(A60), IF(AND(A60=INT(A60), MOD(A60, 10) = 0), 0, IF(AND(A60=INT(A60), LEN(A60)=2), 1, IF(AND(A60=INT(A60), LEN(A60)=3), 2, LEN(A60) - FIND(".", A60) + 2) ) ), "") | C60: Radwaste Building | D60: =REPT(" ", B60*2) & C60
A61: 215.41 | B61: =IF(ISNUMBER(A61), IF(AND(A61=INT(A61), MOD(A61, 10) = 0), 0, IF(AND(A61=INT(A61), LEN(A61)=2), 1, IF(AND(A61=INT(A61), LEN(A61)=3), 2, LEN(A61) - FIND(".", A61) + 2) ) ), "") | C61: Radwaste Building Slab Roof | D61: =REPT(" ", B61*2) & C61 | E61: standard | K61: =1200 *1.53 | L61: $/m^3 | M61: Radwaste Building Slab Roof Volume | O61: m^3 | Q61: 2024 | R61: Lab and Mat and Equip | S61: RSMeans software: a tool that primarily provides costs for non-nuclear work Nuclear Multiplier have been applied to adjust the costs for nuclear-site-related work | T61: GORDIAN. (2024). "RSMeans data. & Delene, J. G. and I. Hudson, C. R. (1993). Cost estimate guidelines for advanced nuclear power technologies. United States, Oak Ridge National Lab. (ORNL), Oak Ridge, TN (United States): Medium: ED; Size: 159 p. | U61: https://www.rsmeans.com/ & https://www.osti.gov/biblio/10176857 | W61: Onsite Learning | X61: =0.9*$J61 | Y61: =1.5*J61 | Z61: Lognormal | AA61: =0.9*K61 | AB61: =1.3*K61 | AC61: Lognormal | AD61: 0.1 | AE61: 1 | AF61: 0 | AG61: Truncated Normal
A62: 215.42 | B62: =IF(ISNUMBER(A62), IF(AND(A62=INT(A62), MOD(A62, 10) = 0), 0, IF(AND(A62=INT(A62), LEN(A62)=2), 1, IF(AND(A62=INT(A62), LEN(A62)=3), 2, LEN(A62) - FIND(".", A62) + 2) ) ), "") | C62: Radwaste Building Basement | D62: =REPT(" ", B62*2) & C62 | E62: standard | K62: =943.9*1.53 | L62: $/m^3 | M62: Radwaste Building Basement Volume | O62: m^3 | Q62: 2024 | R62: Lab and Mat and Equip | W62: Onsite Learning | X62: =0.9*$J62 | Y62: =1.5*J62 | Z62: Lognormal | AA62: =0.9*K62 | AB62: =1.3*K62 | AC62: Lognormal | AD62: 0.1 | AE62: 1 | AF62: 0 | AG62: Truncated Normal
A63: 215.43 | B63: =IF(ISNUMBER(A63), IF(AND(A63=INT(A63), MOD(A63, 10) = 0), 0, IF(AND(A63=INT(A63), LEN(A63)=2), 1, IF(AND(A63=INT(A63), LEN(A63)=3), 2, LEN(A63) - FIND(".", A63) + 2) ) ), "") | C63: Radwaste Building Walls | D63: =REPT(" ", B63*2) & C63 | E63: standard | K63: =721.21*1.53 | L63: $/m^3 | M63: Radwaste Building Exterior Walls Volume | O63: m^3 | Q63: 2024 | R63: Lab and Mat and Equip | W63: Onsite Learning | X63: =0.9*$J63 | Y63: =1.5*J63 | Z63: Lognormal | AA63: =0.9*K63 | AB63: =1.3*K63 | AC63: Lognormal | AD63: 0.1 | AE63: 1 | AF63: 0 | AG63: Truncated Normal
A64: 22 | B64: =IF(ISNUMBER(A64), IF(AND(A64=INT(A64), MOD(A64, 10) = 0), 0, IF(AND(A64=INT(A64), LEN(A64)=2), 1, IF(AND(A64=INT(A64), LEN(A64)=3), 2, LEN(A64) - FIND(".", A64) + 2) ) ), "") | C64: Reactor System | D64: =REPT(" ", B64*2) & C64
A65: 221 | B65: =IF(ISNUMBER(A65), IF(AND(A65=INT(A65), MOD(A65, 10) = 0), 0, IF(AND(A65=INT(A65), LEN(A65)=2), 1, IF(AND(A65=INT(A65), LEN(A65)=3), 2, LEN(A65) - FIND(".", A65) + 2) ) ), "") | C65: Reactor Components | D65: =REPT(" ", B65*2) & C65
A66: 221.1 | B66: =IF(ISNUMBER(A66), IF(AND(A66=INT(A66), MOD(A66, 10) = 0), 0, IF(AND(A66=INT(A66), LEN(A66)=2), 1, IF(AND(A66=INT(A66), LEN(A66)=3), 2, LEN(A66) - FIND(".", A66) + 2) ) ), "") | C66: Reactor Vessel and Accessories | D66: =REPT(" ", B66*2) & C66
A67: 221.11 | B67: =IF(ISNUMBER(A67), IF(AND(A67=INT(A67), MOD(A67, 10) = 0), 0, IF(AND(A67=INT(A67), LEN(A67)=2), 1, IF(AND(A67=INT(A67), LEN(A67)=3), 2, LEN(A67) - FIND(".", A67) + 2) ) ), "") | C67: Reactor Support | D67: =REPT(" ", B67*2) & C67 | E67: standard | K67: =MARVEL_Cost!C16/N67 | L67: $/Kg | M67: Total Vessels Mass | N67: =1000*('Design Variables'!B52+'Design Variables'!B49) | O67: Kg | P67: 0.85 | Q67: 2018 | R67: Lab and Mat and Equip | S67: PWR12-ME | V67: Unit cost is the cost of support structure divided by the cost of guard vessel plus PCS | W67: Factory Primary Structure | X67: =0.9*$J67 | Y67: =1.5*J67 | Z67: Lognormal | AA67: =0.9*K67 | AB67: =1.3*K67 | AC67: Lognormal | AD67: 0.1 | AE67: 1 | AF67: 0 | AG67: Truncated Normal
A68: 221.12 | B68: =IF(ISNUMBER(A68), IF(AND(A68=INT(A68), MOD(A68, 10) = 0), 0, IF(AND(A68=INT(A68), LEN(A68)=2), 1, IF(AND(A68=INT(A68), LEN(A68)=3), 2, LEN(A68) - FIND(".", A68) + 2) ) ), "") | C68: Outer Vessel Structure | D68: =REPT(" ", B68*2) & C68 | E68: standard | F68: Guard Vessel Material | G68: stainless_steel | K68: =MARVEL_Cost!C17/N68 | L68: $/Kg | M68: Guard Vessel Mass | N68: ='Design Variables'!B52*1000 | O68: Kg | Q68: 2017 | R68: Lab and Mat and Equip | S68: Ganda et al., 2018 | T68: Ganda, F., Hoffman, E., Taiwo, T. A., Kim, T. K., & Hansen, J. (2019). Report on the ACCERT cost algorithms tool (No. ANL/NSE-19/10). Argonne National Lab.(ANL), Argonne, IL (United States). | W68: Factory Primary Structure | X68: =0.9*$J68 | Y68: =1.5*J68 | Z68: Lognormal | AA68: =0.9*K68 | AB68: =1.3*K68 | AC68: Lognormal | AD68: 0.1 | AE68: 1 | AF68: 0 | AG68: Truncated Normal
A69: 221.12 | B69: =IF(ISNUMBER(A69), IF(AND(A69=INT(A69), MOD(A69, 10) = 0), 0, IF(AND(A69=INT(A69), LEN(A69)=2), 1, IF(AND(A69=INT(A69), LEN(A69)=3), 2, LEN(A69) - FIND(".", A69) + 2) ) ), "") | C69: Outer Vessel Structure | D69: =REPT(" ", B69*2) & C69 | E69: standard | F69: Guard Vessel Material | G69: low_alloy_steel | K69: 154.08 | L69: $/Kg | M69: Guard Vessel Mass | Q69: 2017 | R69: Lab and Mat and Equip | S69: Ganda et al., 2018 | W69: Factory Primary Structure | X69: =0.9*$J69 | Y69: =1.5*J69 | Z69: Lognormal | AA69: =0.9*K69 | AB69: =1.3*K69 | AC69: Lognormal | AD69: 0.1 | AE69: 1 | AF69: 0 | AG69: Truncated Normal
A70: 221.12 | B70: 4 | C70: Outer Vessel Structure | D70: =REPT(" ", B70*2) & C70 | E70: standard | F70: Guard Vessel Material | G70: incoloy | K70: 444.08 | L70: $/Kg | M70: Guard Vessel Mass | Q70: 2017 | R70: Lab and Mat and Equip | S70: Ganda et al., 2018 | W70: Factory Primary Structure | X70: =0.9*$J70 | Y70: =1.5*J70 | Z70: Lognormal | AA70: =0.9*K70 | AB70: =1.3*K70 | AC70: Lognormal | AD70: 0.1 | AE70: 1 | AF70: 0 | AG70: Truncated Normal
A71: 221.13 | B71: 4 | C71: Inner Vessel Structure | D71: =REPT(" ", B71*2) & C71 | E71: standard | F71: Vessel Material | G71: stainless_steel | J71: =MARVEL_Cost!C37+MARVEL_Cost!C36 | K71: =(MARVEL_Cost!C35)/N71 | L71: $/Kg | M71: Vessel Mass | N71: =1000*'Design Variables'!B49 | Q71: 2017 | R71: Lab and Mat and Equip | S71: Ganda et al., 2018 | V71: Unit cost if the PCS cost (in MARVEL) divided by the PCS mass in MARVEL | W71: Factory Primary Structure | X71: =0.9*$J71 | Y71: =1.5*J71 | Z71: Lognormal | AA71: =0.9*K71 | AB71: =1.3*K71 | AC71: Lognormal | AD71: 0.1 | AE71: 1 | AF71: 0 | AG71: Truncated Normal
A72: 221.13 | B72: 4 | C72: Inner Vessel Structure | D72: =REPT(" ", B72*2) & C72 | E72: standard | F72: Vessel Material | G72: low_alloy_steel | K72: 154.08 | L72: $/Kg | M72: Vessel Mass | Q72: 2017 | R72: Lab and Mat and Equip | S72: Ganda et al., 2018 | W72: Factory Primary Structure | X72: =0.9*$J72 | Y72: =1.5*J72 | Z72: Lognormal | AA72: =0.9*K72 | AB72: =1.3*K72 | AC72: Lognormal | AD72: 0.1 | AE72: 1 | AF72: 0 | AG72: Truncated Normal
A73: 221.13 | B73: 4 | C73: Inner Vessel Structure | D73: =REPT(" ", B73*2) & C73 | E73: standard | F73: Vessel Material | G73: incoloy | K73: 444.08 | L73: $/Kg | M73: Vessel Mass | Q73: 2017 | R73: Lab and Mat and Equip | S73: Ganda et al., 2018 | W73: Factory Primary Structure | X73: =0.9*$J73 | Y73: =1.5*J73 | Z73: Lognormal | AA73: =0.9*K73 | AB73: =1.3*K73 | AC73: Lognormal | AD73: 0.1 | AE73: 1 | AF73: 0 | AG73: Truncated Normal
A74: 221.2 | B74: 3 | C74: Reactor Control Devices | D74: =REPT(" ", B74*2) & C74
A75: 221.21 | B75: 4 | C75: Reactivity Control System | D75: =REPT(" ", B75*2) & C75
A76: 221.211 | B76: 5 | C76: Reactivity Control System Fabrication | D76: =REPT(" ", B76*2) & C76 | E76: standard | K76: =MARVEL_Cost!C21/'Design Variables'!B21 | L76: $/Drum | M76: Drum Count | Q76: 2024 | R76: Lab and Mat and Equip | S76: MARVEL Project | T76: Updated MARVEL Cost Estimate + Communication with MARVEL Team | U76: Gerstner, D., & Arafat, Y. (2023). MARVEL 90% Final Design Report (No. INL/RPT-23-74280-Rev000). Idaho National Laboratory (INL), Idaho Falls, ID (United States). Hanna, B. N., Gonzaga de Oliveira, R. G., Mohammad Al Dawood, K. A., Patterson, M. D., Abou Jaoude, A., & Garcia, S. (2024). Technoeconomic Evaluation of Microreactor Using Detailed Bottom-up Estimate (No. INL/RPT-24-80433-Rev000). Idaho National Laboratory (INL), Idaho Falls, ID (United States). | V76: The scaling variable here is the total mass of all the control drums | W76: Factory Drums | X76: =0.9*$J76 | Y76: =1.5*J76 | Z76: Lognormal | AA76: =0.9*K76 | AB76: =1.3*K76 | AC76: Lognormal | AD76: 0.1 | AE76: 1 | AF76: 0 | AG76: Truncated Normal
A77: 221.212 | B77: 5 | C77: Installation | D77: =REPT(" ", B77*2) & C77 | E77: standard | K77: =MARVEL_Cost!C22/'Design Variables'!B21 | L77: $/Drum | M77: Drum Count | Q77: 2024 | R77: Lab and Equip | S77: MARVEL Project | W77: Factory Drums | X77: =0.9*$J77 | Y77: =1.5*J77 | Z77: Lognormal | AA77: =0.9*K77 | AB77: =1.3*K77 | AC77: Lognormal | AD77: 0.1 | AE77: 1 | AF77: 0 | AG77: Truncated Normal
A78: 221.213 | B78: 5 | C78: Control Drums Materials (Absorber) | D78: =REPT(" ", B78*2) & C78 | E78: standard | F78: Control Drum Absorber | G78: B4C_natural | K78: =400000/N78 | L78: $/Kg | M78: Control Drum Absorber Mass | N78: ='Design Variables'!B28+'Design Variables'!B29 | O78: Kg | P78: 1 | Q78: 2024 | R78: Material | S78: MARVEL Project | W78: Factory Other | X78: =0.9*$J78 | Y78: =1.5*J78 | Z78: Lognormal | AA78: =0.9*K78 | AB78: =1.3*K78 | AC78: Lognormal | AD78: 0.1 | AE78: 1 | AF78: 0 | AG78: Truncated Normal
A79: 221.213 | B79: 5 | C79: Control Drums Materials (Absorber) | D79: =REPT(" ", B79*2) & C79 | E79: standard | F79: Control Drum Absorber | G79: B4C_enriched | K79: 10064 | L79: $/Kg | M79: Control Drum Absorber Mass | Q79: 2023 | R79: Material | S79: Prosser et al., 2023 | W79: Factory Other | X79: =0.9*$J79 | Y79: =1.5*J79 | Z79: Lognormal | AA79: =0.9*K79 | AB79: =1.3*K79 | AC79: Lognormal | AD79: 0.1 | AE79: 1 | AF79: 0 | AG79: Truncated Normal
A80: 221.214 | B80: 5 | C80: Control Drums Materials (Reflector) | D80: =REPT(" ", B80*2) & C80 | E80: standard | F80: Control Drum Reflector | G80: BeO | K80: =MARVEL_Cost!C27/N80 | L80: $/Kg | M80: Control Drum Reflector Mass | N80: ='Design Variables'!B17 | O80: Kg | P80: 1 | Q80: 2024 | R80: Material | S80: MARVEL Project | W80: Factory BeO | X80: =0.9*$J80 | Y80: =1.5*J80 | Z80: Lognormal | AA80: =0.9*K80 | AB80: =1.3*K80 | AC80: Lognormal | AD80: 0.1 | AE80: 1 | AF80: 0 | AG80: Truncated Normal
A81: 221.214 | B81: 5 | C81: Control Drums Materials (Reflector) | D81: =REPT(" ", B81*2) & C81 | E81: standard | F81: Control Drum Reflector | G81: Be | K81: =MARVEL_Cost!C28/N81 | L81: $/Kg | M81: Control Drum Reflector Mass | N81: =1000*'Design Variables'!B19 | O81: Kg | P81: 1 | Q81: 2024 | R81: Material | S81: MARVEL Project | W81: Factory Be | X81: =0.9*$J81 | Y81: =1.5*J81 | Z81: Lognormal | AA81: =0.9*K81 | AB81: =1.3*K81 | AC81: Lognormal | AD81: 0.1 | AE81: 1 | AF81: 0 | AG81: Truncated Normal
A82: 221.214 | B82: 5 | C82: Control Drums Materials (Reflector) | D82: =REPT(" ", B82*2) & C82 | E82: standard | F82: Control Drum Reflector | G82: Graphite | K82: 80 | L82: $/Kg | M82: Control Drum Reflector Mass | Q82: 2022 | R82: Material | S82: Naranjo de Candido and Shirvan, 2022 | T82: Naranjo De Candido and Shirvan. (2022). Graphite Life-Cycle Cost Model for HTGRs, International High-Level Radioactive Waste Management Conference | W82: Factory Other | X82: =0.9*$J82 | Y82: =1.5*J82 | Z82: Lognormal | AA82: =0.9*K82 | AB82: =1.3*K82 | AC82: Lognormal | AD82: 0.1 | AE82: 1 | AF82: 0 | AG82: Truncated Normal
A83: 221.215 | B83: 5 | C83: Control System Drive Mechanism | D83: =REPT(" ", B83*2) & C83 | E83: standard | K83: 74759 | L83: $/Drum | M83: Drum Count | Q83: 2023 | R83: Lab and Mat and Equip | S83: Prosser et al., 2023 | T83: First-Principles Cost Estimation of a Sodium Fast Reactor Nuclear Plant. INL/RPT-23-74316 Table 38, 39 | V83: Bottom-up Estimation of components with nuclear escalation + contingency | W83: Factory Drums | X83: =0.9*$J83 | Y83: =1.5*J83 | Z83: Lognormal | AA83: =0.9*K83 | AB83: =1.3*K83 | AC83: Lognormal | AD83: 0.1 | AE83: 1 | AF83: 0 | AG83: Truncated Normal
A84: 221.3 | B84: 3 | C84: Non-Fuel Core Internals | D84: =REPT(" ", B84*2) & C84 | E84: standard
A85: 221.31 | B85: 4 | C85: Reflector | D85: =REPT(" ", B85*2) & C85
A86: 221.311 | B86: 5 | C86: Radial Reflector | D86: =REPT(" ", B86*2) & C86 | E86: standard | F86: Radial Reflector | G86: BeO | J86: =MARVEL_Cost!C29 | K86: =MARVEL_Cost!C27/N86 | L86: $/Kg | M86: Radial Reflector Mass | N86: ='Design Variables'!B17 | O86: Kg | P86: 1 | Q86: 2024 | R86: Material | S86: MARVEL Project | T86: Updated MARVEL Cost Estimate + Communication with MARVEL Team | U86: Gerstner, D., & Arafat, Y. (2023). MARVEL 90% Final Design Report (No. INL/RPT-23-74280-Rev000). Idaho National Laboratory (INL), Idaho Falls, ID (United States). Hanna, B. N., Gonzaga de Oliveira, R. G., Mohammad Al Dawood, K. A., Patterson, M. D., Abou Jaoude, A., & Garcia, S. (2024). Technoeconomic Evaluation of Microreactor Using Detailed Bottom-up Estimate (No. INL/RPT-24-80433-Rev000). Idaho National Laboratory (INL), Idaho Falls, ID (United States). | W86: Factory BeO | X86: =0.9*$J86 | Y86: =1.5*J86 | Z86: Lognormal | AA86: =0.9*K86 | AB86: =1.3*K86 | AC86: Lognormal | AD86: 0.1 | AE86: 1 | AF86: 0 | AG86: Truncated Normal
A87: 221.312 | B87: 5 | C87: Axial Reflector | D87: =REPT(" ", B87*2) & C87 | E87: standard | F87: Axial Reflector | G87: BeO | J87: 120231 | K87: 10062.893 | L87: $/Kg | M87: Axial Reflector Mass | N87: 318 | O87: Kg | P87: 1 | Q87: 2024 | R87: Material | S87: MARVEL Project | T87: Updated MARVEL Cost Estimate + Communication with MARVEL Team | W87: Factory BeO | X87: =0.9*$J87 | Y87: =1.5*J87 | Z87: Lognormal | AA87: =0.9*K87 | AB87: =1.3*K87 | AC87: Lognormal | AD87: 0.1 | AE87: 1 | AF87: 0 | AG87: Truncated Normal
A88: 221.311 | B88: 5 | C88: Radial Reflector | D88: =REPT(" ", B88*2) & C88 | E88: standard | F88: Radial Reflector | G88: Be | K88: =MARVEL_Cost!C28/N81 | L88: $/Kg | M88: Radial Reflector Mass | N88: =1000*'Design Variables'!B19 | O88: Kg | P88: 1 | Q88: 2024 | R88: Material | S88: MARVEL Project | T88: Updated MARVEL Cost Estimate + Communication with MARVEL Team | W88: Factory Be | X88: =0.9*$J88 | Y88: =1.5*J88 | Z88: Lognormal | AA88: =0.9*K88 | AB88: =1.3*K88 | AC88: Lognormal | AD88: 0.1 | AE88: 1 | AF88: 0 | AG88: Truncated Normal
A89: 221.312 | B89: =IF(ISNUMBER(A89), IF(AND(A89=INT(A89), MOD(A89, 10) = 0), 0, IF(AND(A89=INT(A89), LEN(A89)=2), 1, IF(AND(A89=INT(A89), LEN(A89)=3), 2, LEN(A89) - FIND(".", A89) + 2) ) ), "") | C89: Axial Reflector | D89: =REPT(" ", B89*2) & C89 | E89: standard | F89: Axial Reflector | G89: Be | K89: 44736.842 | L89: $/Kg | M89: Axial Reflector Mass | N89: 19 | O89: Kg | P89: 1 | Q89: 2024 | R89: Material | S89: MARVEL Project | T89: Updated MARVEL Cost Estimate + Communication with MARVEL Team | W89: Factory Be | X89: =0.9*$J89 | Y89: =1.5*J89 | Z89: Lognormal | AA89: =0.9*K89 | AB89: =1.3*K89 | AC89: Lognormal | AD89: 0.1 | AE89: 1 | AF89: 0 | AG89: Truncated Normal
A90: 221.311 | B90: =IF(ISNUMBER(A90), IF(AND(A90=INT(A90), MOD(A90, 10) = 0), 0, IF(AND(A90=INT(A90), LEN(A90)=2), 1, IF(AND(A90=INT(A90), LEN(A90)=3), 2, LEN(A90) - FIND(".", A90) + 2) ) ), "") | C90: Radial Reflector | D90: =REPT(" ", B90*2) & C90 | E90: standard | F90: Radial Reflector | G90: Graphite | K90: 80 | L90: $/Kg | M90: Radial Reflector Mass | Q90: 2022 | R90: Material | S90: Naranjo de Candido and Shirvan, 2022 | T90: Naranjo De Candido and Shirvan. (2022). Graphite Life-Cycle Cost Model for HTGRs, International High-Level Radioactive Waste Management Conference | W90: Factory Other | X90: =0.9*$J90 | Y90: =1.5*J90 | Z90: Lognormal | AA90: =0.9*K90 | AB90: =1.3*K90 | AC90: Lognormal | AD90: 0.1 | AE90: 1 | AF90: 0 | AG90: Truncated Normal
A91: 221.312 | B91: =IF(ISNUMBER(A91), IF(AND(A91=INT(A91), MOD(A91, 10) = 0), 0, IF(AND(A91=INT(A91), LEN(A91)=2), 1, IF(AND(A91=INT(A91), LEN(A91)=3), 2, LEN(A91) - FIND(".", A91) + 2) ) ), "") | C91: Axial Reflector | D91: =REPT(" ", B91*2) & C91 | E91: standard | F91: Axial Reflector | G91: Graphite | K91: 80 | L91: $/Kg | M91: Axial Reflector Mass | Q91: 2022 | R91: Material | S91: Naranjo de Candido and Shirvan, 2022 | T91: Naranjo De Candido and Shirvan. (2022). Graphite Life-Cycle Cost Model for HTGRs, International High-Level Radioactive Waste Management Conference | W91: Factory Other | X91: =0.9*$J91 | Y91: =1.5*J91 | Z91: Lognormal | AA91: =0.9*K91 | AB91: =1.3*K91 | AC91: Lognormal | AD91: 0.1 | AE91: 1 | AF91: 0 | AG91: Truncated Normal
A92: 221.311 | B92: =IF(ISNUMBER(A92), IF(AND(A92=INT(A92), MOD(A92, 10) = 0), 0, IF(AND(A92=INT(A92), LEN(A92)=2), 1, IF(AND(A92=INT(A92), LEN(A92)=3), 2, LEN(A92) - FIND(".", A92) + 2) ) ), "") | C92: Radial Reflector | D92: =REPT(" ", B92*2) & C92 | E92: standard | F92: Radial Reflector | G92: Al2O3 | K92: 134.1 | L92: $/Kg | M92: Radial Reflector Mass | Q92: 2017 | R92: Material | S92: NTRD-FCO-2018-000439 | W92: Factory Other | X92: =0.9*$J92 | Y92: =1.5*J92 | Z92: Lognormal | AA92: =0.9*K92 | AB92: =1.3*K92 | AC92: Lognormal | AD92: 0.1 | AE92: 1 | AF92: 0 | AG92: Truncated Normal
A93: 221.312 | B93: =IF(ISNUMBER(A93), IF(AND(A93=INT(A93), MOD(A93, 10) = 0), 0, IF(AND(A93=INT(A93), LEN(A93)=2), 1, IF(AND(A93=INT(A93), LEN(A93)=3), 2, LEN(A93) - FIND(".", A93) + 2) ) ), "") | C93: Axial Reflector | D93: =REPT(" ", B93*2) & C93 | E93: standard | F93: Axial Reflector | G93: Al2O3 | K93: 134.1 | L93: $/Kg | M93: Axial Reflector Mass | Q93: 2017 | R93: Material | S93: NTRD-FCO-2018-000439 | W93: Factory Other | X93: =0.9*$J93 | Y93: =1.5*J93 | Z93: Lognormal | AA93: =0.9*K93 | AB93: =1.3*K93 | AC93: Lognormal | AD93: 0.1 | AE93: 1 | AF93: 0 | AG93: Truncated Normal
A94: 221.311 | B94: =IF(ISNUMBER(A94), IF(AND(A94=INT(A94), MOD(A94, 10) = 0), 0, IF(AND(A94=INT(A94), LEN(A94)=2), 1, IF(AND(A94=INT(A94), LEN(A94)=3), 2, LEN(A94) - FIND(".", A94) + 2) ) ), "") | C94: Radial Reflector | D94: =REPT(" ", B94*2) & C94 | E94: standard | F94: Radial Reflector | G94: MgO | K94: 264 | L94: $/Kg | M94: Radial Reflector Mass | Q94: 2024 | R94: Material | S94: US Research Nanomaterials, Inc | V94: Imported from TEMA Cost_Database.xlsx (new material option not previously in MOUSE database). | W94: Factory Other | X94: =0.9*$J94 | Y94: =1.5*J94 | Z94: Lognormal | AA94: 136 | AB94: 499 | AC94: Lognormal | AD94: 0.1 | AE94: 1 | AF94: 0 | AG94: Truncated Normal
A95: 221.312 | B95: =IF(ISNUMBER(A95), IF(AND(A95=INT(A95), MOD(A95, 10) = 0), 0, IF(AND(A95=INT(A95), LEN(A95)=2), 1, IF(AND(A95=INT(A95), LEN(A95)=3), 2, LEN(A95) - FIND(".", A95) + 2) ) ), "") | C95: Axial Reflector | D95: =REPT(" ", B95*2) & C95 | E95: standard | F95: Axial Reflector | G95: MgO | K95: 264 | L95: $/Kg | M95: Axial Reflector Mass | Q95: 2024 | R95: Material | S95: US Research Nanomaterials, Inc | V95: Imported from TEMA Cost_Database.xlsx (new material option not previously in MOUSE database). | W95: Factory Other | X95: =0.9*$J95 | Y95: =1.5*J95 | Z95: Lognormal | AA95: 136 | AB95: 499 | AC95: Lognormal | AD95: 0.1 | AE95: 1 | AF95: 0 | AG95: Truncated Normal
A96: 221.311 | B96: =IF(ISNUMBER(A96), IF(AND(A96=INT(A96), MOD(A96, 10) = 0), 0, IF(AND(A96=INT(A96), LEN(A96)=2), 1, IF(AND(A96=INT(A96), LEN(A96)=3), 2, LEN(A96) - FIND(".", A96) + 2) ) ), "") | C96: Radial Reflector | D96: =REPT(" ", B96*2) & C96 | E96: standard | F96: Radial Reflector | G96: ZrC | K96: 3457 | L96: $/Kg | M96: Radial Reflector Mass | Q96: 2024 | R96: Material | S96: Atlanta Equipment Engineers | V96: Imported from TEMA Cost_Database.xlsx (new material option not previously in MOUSE database). | W96: Factory Other | X96: =0.9*$J96 | Y96: =1.5*J96 | Z96: Lognormal | AA96: 426 | AB96: 8525 | AC96: Lognormal | AD96: 0.1 | AE96: 1 | AF96: 0 | AG96: Truncated Normal
A97: 221.312 | B97: =IF(ISNUMBER(A97), IF(AND(A97=INT(A97), MOD(A97, 10) = 0), 0, IF(AND(A97=INT(A97), LEN(A97)=2), 1, IF(AND(A97=INT(A97), LEN(A97)=3), 2, LEN(A97) - FIND(".", A97) + 2) ) ), "") | C97: Axial Reflector | D97: =REPT(" ", B97*2) & C97 | E97: standard | F97: Axial Reflector | G97: ZrC | K97: 3457 | L97: $/Kg | M97: Axial Reflector Mass | Q97: 2024 | R97: Material | S97: Atlanta Equipment Engineers | V97: Imported from TEMA Cost_Database.xlsx (new material option not previously in MOUSE database). | W97: Factory Other | X97: =0.9*$J97 | Y97: =1.5*J97 | Z97: Lognormal | AA97: 426 | AB97: 8525 | AC97: Lognormal | AD97: 0.1 | AE97: 1 | AF97: 0 | AG97: Truncated Normal
A98: 221.311 | B98: =IF(ISNUMBER(A98), IF(AND(A98=INT(A98), MOD(A98, 10) = 0), 0, IF(AND(A98=INT(A98), LEN(A98)=2), 1, IF(AND(A98=INT(A98), LEN(A98)=3), 2, LEN(A98) - FIND(".", A98) + 2) ) ), "") | C98: Radial Reflector | D98: =REPT(" ", B98*2) & C98 | E98: standard | F98: Radial Reflector | G98: SiC | K98: 608 | L98: $/Kg | M98: Radial Reflector Mass | Q98: 2024 | R98: Material | S98: HSA Abrasives | V98: Imported from TEMA Cost_Database.xlsx (new material option not previously in MOUSE database). | W98: Factory Other | X98: =0.9*$J98 | Y98: =1.5*J98 | Z98: Lognormal | AA98: 75 | AB98: 1500 | AC98: Lognormal | AD98: 0.1 | AE98: 1 | AF98: 0 | AG98: Truncated Normal
A99: 221.312 | B99: =IF(ISNUMBER(A99), IF(AND(A99=INT(A99), MOD(A99, 10) = 0), 0, IF(AND(A99=INT(A99), LEN(A99)=2), 1, IF(AND(A99=INT(A99), LEN(A99)=3), 2, LEN(A99) - FIND(".", A99) + 2) ) ), "") | C99: Axial Reflector | D99: =REPT(" ", B99*2) & C99 | E99: standard | F99: Axial Reflector | G99: SiC | K99: 608 | L99: $/Kg | M99: Axial Reflector Mass | Q99: 2024 | R99: Material | S99: HSA Abrasives | V99: Imported from TEMA Cost_Database.xlsx (new material option not previously in MOUSE database). | W99: Factory Other | X99: =0.9*$J99 | Y99: =1.5*J99 | Z99: Lognormal | AA99: 75 | AB99: 1500 | AC99: Lognormal | AD99: 0.1 | AE99: 1 | AF99: 0 | AG99: Truncated Normal
A100: 221.32 | B100: =IF(ISNUMBER(A100), IF(AND(A100=INT(A100), MOD(A100, 10) = 0), 0, IF(AND(A100=INT(A100), LEN(A100)=2), 1, IF(AND(A100=INT(A100), LEN(A100)=3), 2, LEN(A100) - FIND(".", A100) + 2) ) ), "") | C100: Shield | D100: =REPT(" ", B100*2) & C100
...

Sheet MARVEL_Cost
A1: Account ID | B1: Account Title | C1: TOTAL COST (2024 USD)
A3: 10 | B3: Capitalized Pre-Construction Costs | C3: =C4
A4: 15 | B4: Plant Studies | C4: 5210451
A5: 20 | B5: Capitalized Direct Costs | C5: =C6+C13+C45+C48+C52+C54
A6: 21 | B6: Structures and Improvements | C6: =C7+C8+C9+C10
A7: 211 | B7: Site Preparation/Yard Work
A8: 212 | B8: Reactor Island Civil Structures | C8: 2573469.9
A9: 213 | B9: Main Function Buildings
A10: 214 | B10: Buildings to Support Main Function | C10: =SUM(C11:C11)
A11: 214.7 | B11: Emergency and Start-up Power Systems | C11: 225536.86
A12: 217 | B12: Miscellaneous Other Structures
A13: 22 | B13: Reactor System | C13: =C14+C32+C41+C42+C43+C44
A14: 221 | B14: Reactor Components | C14: =C15+C19+C25
A15: 221.1 | B15: Reactor vessel and accessories | C15: =C16+C17+C18
A16: 221.11 | B16: Reactor support | C16: 762382.4
A17: 221.12 | B17: Outer vessel structure | C17: 1201688.6
A18: 221.13 | B18: Inner vessel structure | C18: 40781
A19: 221.2 | B19: Reactor control devices | C19: =C20
A20: 221.21 | B20: Reactivity control system | C20: =SUM(C21:C23)
A21: 221.211 | B21: Reactivity Control System Fabrication | C21: 1391560
A22: 221.212 | B22: Installation | C22: 322663
A23: 221.213 | B23: Control Drums Materials (Absorber) | C23: 400000
A24: 221.214 | B24: Control Drums Materials (Reflector)
A25: 221.3 | B25: Non-fuel core internals | C25: =C26+C30+C31
A26: 221.31 | B26: Reflector | C26: 4170231
A27: 221.311 | B27: Reflector (Materials: BeO) | C27: 3200000
A28: 221.312 | B28: Reflector (Materials: Be Metal) | C28: 850000
A29: 221.313 | B29: Reflector (installation | C29: 120231
A30: 221.32 | B30: Shield | C30: 647990.6
A31: 221.33 | B31: Moderator | C31: 0
A32: 222 | B32: Main Heat Transport System | C32: =C33+C34+C38+C39+C40
A33: 222.1 | B33: Fluid circulation drive system | C33: 0
A34: 222.2 | B34: Reactor Heat Hransfer Piping System | C34: 4890230.6
A35: 222.21 | B35: Reactor Heat Hransfer Piping System (Mat) | C35: 1520786
A36: 222.22 | B36: Reactor Heat Hransfer Piping System (Fabrication) | C36: 3341486
A37: 222.23 | B37: Reactor Heat Hransfer Piping System (Installation) | C37: 27958.6
A38: 222.3 | B38: Heat Exchangers | C38: 0
A39: 222.4 | B39: Pressurizer System | C39: 0
A40: 222.5 | B40: Initial Heat Transfer Fluid Inventory | C40: 1018720
A41: 224 | B41: Radioactive Byproduct Processing Systems
A42: 226 | B42: Other Reactor Plant Equipment | C42: 456297
A43: 227 | B43: Reactor Instrumentation and Control (I&C) | C43: 2253208.4
A44: 228 | B44: Reactor Plant Miscellaneous Items | C44: 30960
A45: 23 | B45: Energy Conversion System | C45: =C46
A46: 232 | B46: Energy Applications | C46: =C47
A47: 232.1 | B47: Electricity Generation Systems | C47: 0
A48: 24 | B48: Electrical Equipment | C48: =C49+C50+C51
A49: 244 | B49: Protective Systems Equipment | C49: 1627.02
A50: 245 | B50: Electrical Raceway Systems | C50: 0
A51: 246 | B51: Power and Control Cables and Wiring | C51: 71788.6
A52: 25 | B52: Initial Fuel Inventory | C52: =C53
A53: 254 | B53: First Core Fuel Assembly Fabrication | C53: 9836580.5
A54: 26 | B54: Miscellaneous Equipment
A55: 30 | B55: Capitalized Indirect Services Cost | C55: =C56+C58+C62+C65+C68
A56: 31 | B56: Factory & Field Indirect Costs | C56: =C57
A57: 317 | B57: Field Shops | C57: 1333020.8
A58: 33 | B58: Startup Costs | C58: =C59
A59: 331 | B59: Commissioning and Trial Test Runs | C59: =C60+C61
A60: 331.3 | B60: Initial Fuel Loading Operations | C60: 215000
A61: 331.5 | B61: Test Runs | C61: 2192166.4
A62: 34 | B62: Shipping and Transportation Costs | C62: =C63+C64
A63: 341 | B63: Fuel Shipping and Transportation | C63: 1635355.8
A64: 345 | B64: Other Shipping and Transportation Costs | C64: 29927
A65: 35 | B65: Engineering Services | C65: =C66+C67
A66: 351 | B66: Off-Site | C66: 257261.4
A67: 352 | B67: On-Site | C67: 363052.19
A68: 36 | B68: PM/CM Services | C68: =C69+C70
A69: 361 | B69: Off-Site
A70: 362 | B70: On-Site | C70: 416958.94
A71: 40 | B71: Capitalized Training Costs | C71: =C72
A72: 41 | B72: Staff Recruitment and Training | C72: 4169765
A73: 50 | B73: Capitalized Supplementary Costs | C73: =C74
A74: 54 | B74: Decommissioning | C74: 16408782
A75: 60 | B75: Capitalized Financial Costs | C75: =C76
A76: 61 | B76: Escalation | C76: 6160606
A77: 70 | B77: Annualized O&M Cost | C77: =C78
A78: 71 | B78: O&M Staff | C78: 2456659.2
A79: Non-Recurrung Costs | B79: Non-Recurrung Costs | C79: 33779050

Sheet Design Variables
A1: Variable | B1: Value | C1: Units | D1: Description
A2: Overall System
A3: Thermal power | B3: 83 | C3: kWth | D3: —
A4: Electric Power | B4: 20 | C4: kWe
A5: Core outer radius | B5: 5.5 | C5: inches | D5: —
A6: Reflector outer radius | B6: 16.5 | C6: inches | D6: —
A7: Fuel
A8: Fuel mass | B8: 145.3 | C8: kg | D8: UZrH
A9: U Weight fraction | B9: 30 | C9: wt% | D9: U/UZrH
A10: U enrichment | B10: 19.75 | C10: wt% | D10: High-assay low-enriched uranium (HALEU)
A11: Pins | B11: 36 | C11: # | D11: —
A12: Reflector
A13: Outer reflector material | B13: BeO | C13: — | D13: 99% theoretical density
A14: Elements | B14: 124 | C14: # | D14: Quarter plates
A15: Reflector plate thickness | B15: 1 | C15: inches | D15: —
A16: Reflector plate volume | B16: 818.4 | C16: cm3/plate | D16: —
A17: Mass of BeO reflector | B17: 318 | C17: Kg
A18: Insert volume | B18: 570 | C18: cm3/plate | D18: —
A19: Mass of Be-metal reflector | B19: 0.019 | C19: MT | D19: —
A20: Control Elements
A21: Control drums | B21: 4 | C21: # | D21: —
A22: Shutdown rods | B22: 1 | C22: # | D22: —
A23: Control drum elements | B23: 124 | C23: # | D23: Discs
A24: Drum disc thickness | B24: 1 | C24: inches | D24: —
A25: Drum reflector volume | B25: 880.8 | C25: cm3/plate | D25: BeO 99%
A26: Mass of drum reflector | B26: 309 | C26: Kg | D26: —
A27: Drum poison volume | B27: 49.2 | C27: cm3/plate | D27: B4C
A28: Mass of drum poison | B28: 14 | C28: Kg | D28: —
A29: Mass of rod poison | B29: 14 | C29: Kg | D29: B4C
A30: Instruments and Controls
A31: Control cabinet | B31: 5 | D31: —
A32: Instrument cabinet | B32: 2 | D32: —
A33: Nuclear input/output (IO) | B33: 9 | D33: —
A34: Non-nuclear IO | B34: 213 | D34: —
A35: Stirling engine IO | B35: 48 | C35: — | D35: These should be excluded if there no stirling engine?
A36: TOTAL | B36: 277
A37: Shielding in Vessel
A38: Stainless Steel cans | B38: 54.2 | C38: Kg | D38: Stainless Steel cans of the boron carbide shielding material (SS316H)
A39: Gamma shield material | B39: 56.3 | C39: Kg | D39: Gamma shield material inside the guard vessel (of Tungsten)
A40: Neutron shield material in the guard vessel | B40: 39.7 | C40: Kg | D40: made of natural B4C powder and is located above the core (a donut around the core barrel)—
A41: Boron Carbine shielding | B41: 95.3 | C41: Kg | D41: made of natural B4C (called base shield) below the core
A42: Radial (lead) | B42: 2571.9 | C42: Kg | D42: lead
A43: Radial (WEP) | B43: 925.3 | C43: Kg | D43: made of Water Extended Polyster (WEP)
A44: Shielding in Pit
A45: Mass of the pit neutron shielding | B45: 8.3 | C45: MT | D45: Approximated 6-in.-thick covering whole pit and made of Water-extruded poly (WEP)
A46: Heat Transfer
A47: Mass of coolant | B47: 156 | C47: Kg | D47: —
A48: Number of loops | B48: 4 | C48: # | D48: —
A49: Mass of PCSs | B49: 0.86 | C49: MT | D49: SS316H
A50: Subassembly Structure Masses
A51: Reactor support frame | B51: 1.11 | C51: MT | D51: —
A52: Guard vessel | B52: 1.587 | C52: MT | D52: —

Sheet Inflation Adjustment
A1: Year | B1: General | C1: Labor | D1: Material | E1: Equipment | F1: Lab and Mat and Equip | G1: Lab and Equip
A2: 1978 | B2: 3.1209 | C2: 4.2536 | D2: 3.811 | E2: 5.3954 | F2: =(C2+D2+E2)/3 | G2: =AVERAGE(C2,E2)
A3: 1985 | B3: 2.53801 | C3: 3.3122863 | D3: 3.1461261 | E3: 4.0603969 | F3: =(C3+D3+E3)/3 | G3: =AVERAGE(C3,E3)
A4: 1986 | B4: 2.4877976 | C4: 3.2086278 | D4: 3.1524765 | E4: 3.957082 | F4: =(C4+D4+E4)/3 | G4: =AVERAGE(C4,E4)
A5: 1987 | B5: 2.4278243 | C5: 3.1112605 | D5: 3.0891631 | E5: 3.9210211 | F5: =(C5+D5+E5)/3 | G5: =AVERAGE(C5,E5)
A6: 1988 | B6: 2.3451469 | C6: 2.989825 | D6: 2.9257907 | E6: 3.7360352 | F6: =(C6+D6+E6)/3 | G6: =AVERAGE(C6,E6)
A7: 1989 | B7: 2.2565183 | C7: 2.8925 | D7: 2.8323254 | E7: 3.5114259 | F7: =(C7+D7+E7)/3 | G7: =AVERAGE(C7,E7)
A8: 1990 | B8: 2.1749312 | C8: 2.765278 | D8: 2.828971 | E8: 3.4175276 | F8: =(C8+D8+E8)/3 | G8: =AVERAGE(C8,E8)
A9: 1991 | B9: 2.103917 | C9: 2.6561658 | D9: 2.8109546 | E9: 3.3052946 | F9: =(C9+D9+E9)/3 | G9: =AVERAGE(C9,E9)
A10: 1992 | B10: 2.0570925 | C10: 2.5740904 | D10: 2.7621964 | E10: 3.1693577 | F10: =(C10+D10+E10)/3 | G10: =AVERAGE(C10,E10)
A11: 1993 | B11: 2.0094227 | C11: 2.4922663 | D11: 2.6313537 | E11: 2.9935069 | F11: =(C11+D11+E11)/3 | G11: =AVERAGE(C11,E11)
A12: 1994 | B12: 1.967432 | C12: 2.4032889 | D12: 2.528144 | E12: 2.9062257 | F12: =(C12+D12+E12)/3 | G12: =AVERAGE(C12,E12)
A13: 1995 | B13: 1.9269732 | C13: 2.3615592 | D13: 2.4372516 | E13: 2.8565425 | F13: =(C13+D13+E13)/3 | G13: =AVERAGE(C13,E13)
... A43: 2025 | B43: 1 | C43: 1 | D43: 1 | E43: 1 | F43: =(C43+D43+E43)/3 | G43: =AVERAGE(C43,E43)

Sheet Economics Parameters
A1: Parameter | B1: Value | C1: Note | D1: Reference | E1: Notes
A2: indirect to direct field-related cost | B2: 0.065389932
A3: FTEs Per Onsite Operator (24/7) | B3: 5
A4: FTEs Per Offsite Operator (24/7) | B4: 5
A5: FTEs Per Security Staff (24/7) | B5: 5
A6: Hours Per FTE | B6: 1800
A7: Work Hours Per Shift | B7: 10
A8: Maintenance to Direct Cost Ratio | B8: 0.03
A9: Onsite Learning | B9: 0.08 | C9: FOAK to NOAK Learning Rates | D9: Assessment of Factory Fabrication Considerations for Nuclear Microreactors 10.1080/00295450.2023.2206779 | E9: Calculated based on Refernce Paper + Gyutae's work. Refer to TEM Slides for rationale and methodology
A10: No Learning | B10: 0
A11: Licensing Learning | B11: 0
A12: Factory Primary Structure | B12: 0.1844317
A13: Factory Drums | B13: 0.24138
A14: Factory Other | B14: 0.22962848
A15: Factory Be | B15: 0.41505378
A16: Factory BeO | B16: 0.39914906
A17: Non-nuclear off-the-shelf | B17: 0.05 | D17: Park, et al., Bottom-up levelized cost estimation of low-enriched and low-pressure nuclear batteries. Nuclear Engineering and Design. 2025. | E17: For off-the-shelf commercial components that are not produced in the FB Factory

Sheet Central Facility Database
A1: Account | B1: Level | C1: Account Name | D1: Account Title | E1: Standard Cost Equation? | F1: Count Scaling Variable | G1: Count per Variable | H1: Optional Variable | I1: Optional Value | J1: Fixed Cost ($) | K1: Unit Cost | L1: Unit Cost (units) | M1: Scaling Variable | N1: Scaling Variable Ref Value | O1: Units | P1: Exponent | Q1: Dollar Year | R1: Type | S1: Source | T1: Ref | U1: Link | V1: Notes | W1: FOAK to NOAK Multiplier Type | X1: Fixed Cost Low End | Y1: Fixed Cost High End | Z1: Fixed Cost Distribution | AA1: Unit Cost Low End | AB1: Unit Cost High End | AC1: Unit Cost Distribution | AD1: Exponent std | AE1: Exponent Max | AF1: Exponent Min | AG1: Exponent Distribution
A2: 10 | B2: 0 | C2: Capitalized Pre-Construction Costs | D2: =REPT(" ", B2*2) & C2
A3: 11 | B3: 1 | C3: Land Cost | D3: =REPT(" ", B3*2) & C3 | E3: standard | F3: Constant | G3: 1 | K3: 3800 | L3: $/acres | M3: Land Area | O3: acres | Q3: 2022 | R3: General | S3: The average cost per acre for rural land in 2022 from the US Department of Agriculture | T3: Abou-Jaoude, A., Lohse, C. S., Larsen, L. M., Guaita, N., Trivedi, I., Joseck, F. C., ... & Stein, A. (2024). Meta-analysis of advanced nuclear reactor cost estimations (No. INL/RPT-24-77048-Rev001). Idaho National Laboratory (INL), Idaho Falls, ID (United States). | U3: https://inldigitallibrary.inl.gov/sites/sti/sti/Sort_107010.pdf | W3: No Learning | X3: =0.9*$J3 | Y3: =1.5*J3 | Z3: Lognormal | AA3: =0.9*K3 | AB3: =1.3*K3 | AC3: Lognormal | AD3: 0.1 | AE3: 1 | AF3: 0 | AG3: Truncated Normal
A4: 12 | B4: 1 | C4: Site Permits | D4: =REPT(" ", B4*2) & C4 | E4: standard | F4: Constant | G4: 1 | K4: =10.03*1000 | L4: $/MWe | M4: Power MWe | O4: MWe | Q4: 2022 | R4: Labor | S4: Data from SMR MHTGRs | W4: No Learning | X4: =0.9*$J4 | Y4: =1.5*J4 | Z4: Lognormal | AA4: =0.9*K4 | AB4: =1.3*K4 | AC4: Lognormal | AD4: 0.1 | AE4: 1 | AF4: 0 | AG4: Truncated Normal
A5: 13 | B5: 1 | C5: Plant Licensing | D5: =REPT(" ", B5*2) & C5 | E5: standard | F5: Constant | G5: 1 | J5: =1000000*(45+70)/2 | Q5: 2009 | R5: Labor | S5: NGNP project | T5: Gandrik, A., B. Wallace, L. Demick, S. Melancon and M. Patterson (2011). "Assessment of high temperature gas-cooled reactor (HTGR) capital and operating costs." Idaho National Laboratory, TEV-1196, Idaho Falls, ID. | U5: https://art.inl.gov/NGNP/INL%20Documents/Year%202012/Assessment%20of%20High%20Temperature%20Gas-Cooled%20Reactor%20-%20HTGR%20-%20Capital%20and%20Operating%20Costs.pdf | W5: No Learning | X5: =45*1000000 | Y5: =70*1000000 | Z5: Uniform | AA5: =0.9*K5 | AB5: =1.3*K5 | AC5: Lognormal | AD5: 0.1 | AE5: 1 | AF5: 0 | AG5: Truncated Normal
A6: 14 | B6: 1 | C6: Plant Permits | D6: =REPT(" ", B6*2) & C6 | E6: standard | F6: Constant | G6: 1 | J6: 3000000 | Q6: 2009 | R6: Labor | S6: NGNP project | W6: No Learning | X6: =0.9*$J6 | Y6: =1.5*J6 | Z6: Lognormal | AA6: =0.9*K6 | AB6: =1.3*K6 | AC6: Lognormal | AD6: 0.1 | AE6: 1 | AF6: 0 | AG6: Truncated Normal
A7: 15 | B7: 1 | C7: Plant Studies | D7: =REPT(" ", B7*2) & C7 | E7: standard | F7: Constant | G7: 1 | J7: =MARVEL_Cost!C4 | Q7: 2024 | R7: Labor | S7: MARVEL Project (Labor-adjusted Cost) | T7: Hanna, B. N., Gonzaga de Oliveira, R. G., Mohammad Al Dawood, K. A., Patterson, M. D., Abou Jaoude, A., & Garcia, S. (2024). Technoeconomic Evaluation of Microreactor Using Detailed Bottom-up Estimate (No. INL/RPT-24-80433-Rev000). Idaho National Laboratory (INL), Idaho Falls, ID (United States). | U7: https://inldigitallibrary.inl.gov/sites/sti/sti/Sort_129862.pdf | V7: MARVEL's data were updated | W7: No Learning | X7: =0.9*$J7 | Y7: =1.5*J7 | Z7: Lognormal | AA7: =0.9*K7 | AB7: =1.3*K7 | AC7: Lognormal | AD7: 0.1 | AE7: 1 | AF7: 0 | AG7: Truncated Normal
A8: 20 | B8: 0 | C8: Capitalized Direct Costs | D8: =REPT(" ", B8*2) & C8
A9: 21 | B9: 1 | C9: Structures and Improvements | D9: =REPT(" ", B9*2) & C9
A10: 211 | B10: 2 | C10: Site Preparation/ Yard Work | D10: =REPT(" ", B10*2) & C10
A11: 211.1 | B11: 3 | C11: Cleaning and Grubbing | D11: =REPT(" ", B11*2) & C11 | E11: standard | F11: Constant | G11: 1 | K11: =4408.18*1.33 | L11: $/acres | M11: Land Area | O11: acres | Q11: 2024 | R11: Lab and Equip | S11: RSMeans software: a tool that primarily provides costs for non-nuclear work Nuclear Multiplier have been applied to adjust the costs for nuclear-site-related work | T11: GORDIAN. (2024). "RSMeans data. & Delene, J. G. and I. Hudson, C. R. (1993). Cost estimate guidelines for advanced nuclear power technologies. United States, Oak Ridge National Lab. (ORNL), Oak Ridge, TN (United States): Medium: ED; Size: 159 p. | U11: https://www.rsmeans.com/ & https://www.osti.gov/biblio/10176857 | W11: No Learning | X11: =0.9*$J11 | Y11: =1.5*J11 | Z11: Lognormal | AA11: =0.9*K11 | AB11: =1.3*K11 | AC11: Lognormal | AD11: 0.1 | AE11: 1 | AF11: 0 | AG11: Truncated Normal
A12: 211.2 | B12: 3 | C12: Stripping Topsoil | D12: =REPT(" ", B12*2) & C12 | E12: standard | F12: Constant | G12: 1 | K12: =2565.2*1.33 | L12: $/acres | M12: Land Area | O12: acres | Q12: 2024 | R12: Lab and Equip | W12: No Learning | X12: =0.9*$J12 | Y12: =1.5*J12 | Z12: Lognormal | AA12: =0.9*K12 | AB12: =1.3*K12 | AC12: Lognormal | AD12: 0.1 | AE12: 1 | AF12: 0 | AG12: Truncated Normal
A13: 211.3 | B13: 3 | C13: Excavation | D13: =REPT(" ", B13*2) & C13 | E13: standard | F13: Constant | G13: 1 | K13: =22.86*1.4 | L13: $/m^3 | M13: Excavation Volume | O13: m^3 | Q13: 2024 | R13: Lab and Equip | W13: No Learning | X13: =0.9*$J13 | Y13: =1.5*J13 | Z13: Lognormal | AA13: =0.9*K13 | AB13: =1.3*K13 | AC13: Lognormal | AD13: 0.1 | AE13: 1 | AF13: 0 | AG13: Truncated Normal
A14: 211.4 | B14: =IF(ISNUMBER(A14), IF(AND(A14=INT(A14), MOD(A14, 10) = 0), 0, IF(AND(A14=INT(A14), LEN(A14)=2), 1, IF(AND(A14=INT(A14), LEN(A14)=3), 2, LEN(A14) - FIND(".", A14) + 2) ) ), "") | C14: Roadwork | D14: =REPT(" ", B14*2) & C14 | E14: standard | F14: Constant | G14: 1 | W14: No Learning | X14: =0.9*$J14 | Y14: =1.5*J14 | Z14: Lognormal | AA14: =0.9*K14 | AB14: =1.3*K14 | AC14: Lognormal | AD14: 0.1 | AE14: 1 | AF14: 0 | AG14: Truncated Normal
A15: 211.9 | B15: =IF(ISNUMBER(A15), IF(AND(A15=INT(A15), MOD(A15, 10) = 0), 0, IF(AND(A15=INT(A15), LEN(A15)=2), 1, IF(AND(A15=INT(A15), LEN(A15)=3), 2, LEN(A15) - FIND(".", A15) + 2) ) ), "") | C15: Security Fencing | D15: =REPT(" ", B15*2) & C15 | E15: standard | F15: Constant | G15: 1 | K15: =75/0.3048 | L15: $/m | M15: Site Perimeter | Q15: 2009 | R15: Lab and Equip | S15: Ref Table 2-8 | T15: Kessler. Cost Estimate for an Away-From-Reactor Generic Interim Storage Facility (GISF) for Spent Nuclear Fuel. EPRI. 2009. | U15: https://www.epri.com/research/products/1018722 | W15: No Learning | X15: =0.9*$J15 | Y15: =1.5*J15 | Z15: Lognormal | AA15: =0.9*K15 | AB15: =1.3*K15 | AC15: Lognormal | AD15: 0.1 | AE15: 1 | AF15: 0 | AG15: Truncated Normal
A16: 213 | B16: =IF(ISNUMBER(A16), IF(AND(A16=INT(A16), MOD(A16, 10) = 0), 0, IF(AND(A16=INT(A16), LEN(A16)=2), 1, IF(AND(A16=INT(A16), LEN(A16)=3), 2, LEN(A16) - FIND(".", A16) + 2) ) ), "") | C16: Manufacturing Facility | D16: =REPT(" ", B16*2) & C16
A17: 213.1 | B17: =IF(ISNUMBER(A17), IF(AND(A17=INT(A17), MOD(A17, 10) = 0), 0, IF(AND(A17=INT(A17), LEN(A17)=2), 1, IF(AND(A17=INT(A17), LEN(A17)=3), 2, LEN(A17) - FIND(".", A17) + 2) ) ), "") | C17: Fabrication Building | D17: =REPT(" ", B17*2) & C17
A18: 213.11 | B18: =IF(ISNUMBER(A18), IF(AND(A18=INT(A18), MOD(A18, 10) = 0), 0, IF(AND(A18=INT(A18), LEN(A18)=2), 1, IF(AND(A18=INT(A18), LEN(A18)=3), 2, LEN(A18) - FIND(".", A18) + 2) ) ), "") | C18: =_xlfn.CONCAT(C17," Roof") | D18: =REPT(" ", B18*2) & C18 | E18: standard | F18: Constant | G18: 1 | K18: =1200 | L18: $/m^3 | M18: =_xlfn.CONCAT(C18, " Volume") | O18: m^3 | Q18: 2024 | R18: Lab and Mat and Equip | S18: RSMeans software: a tool that primarily provides costs for non-nuclear work Nuclear Multiplier have not been applied | T18: GORDIAN. (2024). "RSMeans data. & Delene, J. G. and I. Hudson, C. R. (1993). Cost estimate guidelines for advanced nuclear power technologies. United States, Oak Ridge National Lab. (ORNL), Oak Ridge, TN (United States): Medium: ED; Size: 159 p. | U18: https://www.rsmeans.com/ & https://www.osti.gov/biblio/10176857 | W18: No Learning | X18: =0.9*$I18 | Y18: =1.5*J18 | Z18: Lognormal | AA18: =0.9*K18 | AB18: =1.3*K18 | AC18: Lognormal | AD18: 0.1 | AE18: 1 | AF18: 0 | AG18: Truncated Normal
A19: 213.12 | B19: =IF(ISNUMBER(A19), IF(AND(A19=INT(A19), MOD(A19, 10) = 0), 0, IF(AND(A19=INT(A19), LEN(A19)=2), 1, IF(AND(A19=INT(A19), LEN(A19)=3), 2, LEN(A19) - FIND(".", A19) + 2) ) ), "") | C19: =_xlfn.CONCAT(C17," Basement") | D19: =REPT(" ", B19*2) & C19 | E19: standard | F19: Constant | G19: 1 | K19: =943.9 | L19: $/m^3 | M19: =_xlfn.CONCAT(C19, " Volume") | O19: m^3 | Q19: 2024 | R19: Lab and Mat and Equip | W19: No Learning | X19: =0.9*$I19 | Y19: =1.5*J19 | Z19: Lognormal | AA19: =0.9*K19 | AB19: =1.3*K19 | AC19: Lognormal | AD19: 0.1 | AE19: 1 | AF19: 0 | AG19: Truncated Normal
A20: 213.13 | B20: =IF(ISNUMBER(A20), IF(AND(A20=INT(A20), MOD(A20, 10) = 0), 0, IF(AND(A20=INT(A20), LEN(A20)=2), 1, IF(AND(A20=INT(A20), LEN(A20)=3), 2, LEN(A20) - FIND(".", A20) + 2) ) ), "") | C20: =_xlfn.CONCAT(C17," Walls") | D20: =REPT(" ", B20*2) & C20 | E20: standard | F20: Constant | G20: 1 | K20: =721.21 | L20: $/m^3 | M20: =_xlfn.CONCAT(C20, " Volume") | O20: m^3 | Q20: 2024 | R20: Lab and Mat and Equip | W20: No Learning | X20: =0.9*$I20 | Y20: =1.5*J20 | Z20: Lognormal | AA20: =0.9*K20 | AB20: =1.3*K20 | AC20: Lognormal | AD20: 0.1 | AE20: 1 | AF20: 0 | AG20: Truncated Normal
A21: 213.19 | B21: =IF(ISNUMBER(A21), IF(AND(A21=INT(A21), MOD(A21, 10) = 0), 0, IF(AND(A21=INT(A21), LEN(A21)=2), 1, IF(AND(A21=INT(A21), LEN(A21)=3), 2, LEN(A21) - FIND(".", A21) + 2) ) ), "") | C21: HVAC | D21: =REPT(" ", B21*2) & C21 | E21: standard | F21: Constant | G21: 1 | L21: $/m^3 | M21: =_xlfn.CONCAT(C17, " Volume") | O21: m^3 | W21: No Learning | X21: =0.9*$I21 | Y21: =1.5*J21 | Z21: Lognormal | AA21: =0.9*K21 | AB21: =1.3*K21 | AC21: Lognormal | AD21: 0.1 | AE21: 1 | AF21: 0 | AG21: Truncated Normal
A22: 213.2 | B22: =IF(ISNUMBER(A22), IF(AND(A22=INT(A22), MOD(A22, 10) = 0), 0, IF(AND(A22=INT(A22), LEN(A22)=2), 1, IF(AND(A22=INT(A22), LEN(A22)=3), 2, LEN(A22) - FIND(".", A22) + 2) ) ), "") | C22: Feed and Product Warehouse Building | D22: =REPT(" ", B22*2) & C22
A23: 213.21 | B23: =IF(ISNUMBER(A23), IF(AND(A23=INT(A23), MOD(A23, 10) = 0), 0, IF(AND(A23=INT(A23), LEN(A23)=2), 1, IF(AND(A23=INT(A23), LEN(A23)=3), 2, LEN(A23) - FIND(".", A23) + 2) ) ), "") | C23: =_xlfn.CONCAT(C22," Roof") | D23: =REPT(" ", B23*2) & C23 | E23: standard | F23: Constant | G23: 1 | K23: =1200 | L23: $/m^3 | M23: =_xlfn.CONCAT(C23, " Volume") | O23: m^3 | Q23: 2024 | R23: Lab and Mat and Equip | S23: RSMeans software: a tool that primarily provides costs for non-nuclear work Nuclear Multiplier have not been applied | T23: GORDIAN. (2024). "RSMeans data. & Delene, J. G. and I. Hudson, C. R. (1993). Cost estimate guidelines for advanced nuclear power technologies. United States, Oak Ridge National Lab. (ORNL), Oak Ridge, TN (United States): Medium: ED; Size: 159 p. | U23: https://www.rsmeans.com/ & https://www.osti.gov/biblio/10176857 | W23: No Learning | X23: =0.9*$I23 | Y23: =1.5*J23 | Z23: Lognormal | AA23: =0.9*K23 | AB23: =1.3*K23 | AC23: Lognormal | AD23: 0.1 | AE23: 1 | AF23: 0 | AG23: Truncated Normal
A24: 213.22 | B24: =IF(ISNUMBER(A24), IF(AND(A24=INT(A24), MOD(A24, 10) = 0), 0, IF(AND(A24=INT(A24), LEN(A24)=2), 1, IF(AND(A24=INT(A24), LEN(A24)=3), 2, LEN(A24) - FIND(".", A24) + 2) ) ), "") | C24: =_xlfn.CONCAT(C22," Basement") | D24: =REPT(" ", B24*2) & C24 | E24: standard | F24: Constant | G24: 1 | K24: =943.9 | L24: $/m^3 | M24: =_xlfn.CONCAT(C24, " Volume") | O24: m^3 | Q24: 2024 | R24: Lab and Mat and Equip | W24: No Learning | X24: =0.9*$I24 | Y24: =1.5*J24 | Z24: Lognormal | AA24: =0.9*K24 | AB24: =1.3*K24 | AC24: Lognormal | AD24: 0.1 | AE24: 1 | AF24: 0 | AG24: Truncated Normal
A25: 213.23 | B25: =IF(ISNUMBER(A25), IF(AND(A25=INT(A25), MOD(A25, 10) = 0), 0, IF(AND(A25=INT(A25), LEN(A25)=2), 1, IF(AND(A25=INT(A25), LEN(A25)=3), 2, LEN(A25) - FIND(".", A25) + 2) ) ), "") | C25: =_xlfn.CONCAT(C22," Walls") | D25: =REPT(" ", B25*2) & C25 | E25: standard | F25: Constant | G25: 1 | K25: =721.21 | L25: $/m^3 | M25: =_xlfn.CONCAT(C25, " Volume") | O25: m^3 | Q25: 2024 | R25: Lab and Mat and Equip | W25: No Learning | X25: =0.9*$I25 | Y25: =1.5*J25 | Z25: Lognormal | AA25: =0.9*K25 | AB25: =1.3*K25 | AC25: Lognormal | AD25: 0.1 | AE25: 1 | AF25: 0 | AG25: Truncated Normal
A26: 213.29 | B26: =IF(ISNUMBER(A26), IF(AND(A26=INT(A26), MOD(A26, 10) = 0), 0, IF(AND(A26=INT(A26), LEN(A26)=2), 1, IF(AND(A26=INT(A26), LEN(A26)=3), 2, LEN(A26) - FIND(".", A26) + 2) ) ), "") | C26: HVAC | D26: =REPT(" ", B26*2) & C26 | E26: standard | F26: Constant | G26: 1 | L26: $/m^3 | M26: =_xlfn.CONCAT(C22, " Volume") | O26: m^3 | W26: No Learning | X26: =0.9*$I26 | Y26: =1.5*J26 | Z26: Lognormal | AA26: =0.9*K26 | AB26: =1.3*K26 | AC26: Lognormal | AD26: 0.1 | AE26: 1 | AF26: 0 | AG26: Truncated Normal
A27: 213.6 | B27: =IF(ISNUMBER(A27), IF(AND(A27=INT(A27), MOD(A27, 10) = 0), 0, IF(AND(A27=INT(A27), LEN(A27)=2), 1, IF(AND(A27=INT(A27), LEN(A27)=3), 2, LEN(A27) - FIND(".", A27) + 2) ) ), "") | C27: Manufacturing Facility Integrated Control Building | D27: =REPT(" ", B27*2) & C27
A28: 213.61 | B28: =IF(ISNUMBER(A28), IF(AND(A28=INT(A28), MOD(A28, 10) = 0), 0, IF(AND(A28=INT(A28), LEN(A28)=2), 1, IF(AND(A28=INT(A28), LEN(A28)=3), 2, LEN(A28) - FIND(".", A28) + 2) ) ), "") | C28: =_xlfn.CONCAT(C27," Roof") | D28: =REPT(" ", B28*2) & C28 | E28: standard | F28: Constant | G28: 1 | K28: =1200 | L28: $/m^3 | M28: =_xlfn.CONCAT(C28, " Volume") | O28: m^3 | Q28: 2024 | R28: Lab and Mat and Equip | S28: RSMeans software: a tool that primarily provides costs for non-nuclear work Nuclear Multiplier have not been applied | T28: GORDIAN. (2024). "RSMeans data. & Delene, J. G. and I. Hudson, C. R. (1993). Cost estimate guidelines for advanced nuclear power technologies. United States, Oak Ridge National Lab. (ORNL), Oak Ridge, TN (United States): Medium: ED; Size: 159 p. | U28: https://www.rsmeans.com/ & https://www.osti.gov/biblio/10176857 | W28: No Learning | X28: =0.9*$I28 | Y28: =1.5*J28 | Z28: Lognormal | AA28: =0.9*K28 | AB28: =1.3*K28 | AC28: Lognormal | AD28: 0.1 | AE28: 1 | AF28: 0 | AG28: Truncated Normal
A29: 213.62 | B29: =IF(ISNUMBER(A29), IF(AND(A29=INT(A29), MOD(A29, 10) = 0), 0, IF(AND(A29=INT(A29), LEN(A29)=2), 1, IF(AND(A29=INT(A29), LEN(A29)=3), 2, LEN(A29) - FIND(".", A29) + 2) ) ), "") | C29: =_xlfn.CONCAT(C27," Basement") | D29: =REPT(" ", B29*2) & C29 | E29: standard | F29: Constant | G29: 1 | K29: =943.9 | L29: $/m^3 | M29: =_xlfn.CONCAT(C29, " Volume") | O29: m^3 | Q29: 2024 | R29: Lab and Mat and Equip | W29: No Learning | X29: =0.9*$I29 | Y29: =1.5*J29 | Z29: Lognormal | AA29: =0.9*K29 | AB29: =1.3*K29 | AC29: Lognormal | AD29: 0.1 | AE29: 1 | AF29: 0 | AG29: Truncated Normal
A30: 213.63 | B30: =IF(ISNUMBER(A30), IF(AND(A30=INT(A30), MOD(A30, 10) = 0), 0, IF(AND(A30=INT(A30), LEN(A30)=2), 1, IF(AND(A30=INT(A30), LEN(A30)=3), 2, LEN(A30) - FIND(".", A30) + 2) ) ), "") | C30: =_xlfn.CONCAT(C27," Walls") | D30: =REPT(" ", B30*2) & C30 | E30: standard | F30: Constant | G30: 1 | K30: =721.21 | L30: $/m^3 | M30: =_xlfn.CONCAT(C30, " Volume") | O30: m^3 | Q30: 2024 | R30: Lab and Mat and Equip | W30: No Learning | X30: =0.9*$I30 | Y30: =1.5*J30 | Z30: Lognormal | AA30: =0.9*K30 | AB30: =1.3*K30 | AC30: Lognormal | AD30: 0.1 | AE30: 1 | AF30: 0 | AG30: Truncated Normal
A31: 213.69 | B31: =IF(ISNUMBER(A31), IF(AND(A31=INT(A31), MOD(A31, 10) = 0), 0, IF(AND(A31=INT(A31), LEN(A31)=2), 1, IF(AND(A31=INT(A31), LEN(A31)=3), 2, LEN(A31) - FIND(".", A31) + 2) ) ), "") | C31: HVAC | D31: =REPT(" ", B31*2) & C31 | E31: standard | F31: Constant | G31: 1 | L31: $/m^3 | M31: =_xlfn.CONCAT(C27, " Volume") | O31: m^3 | W31: No Learning | X31: =0.9*$I31 | Y31: =1.5*J31 | Z31: Lognormal | AA31: =0.9*K31 | AB31: =1.3*K31 | AC31: Lognormal | AD31: 0.1 | AE31: 1 | AF31: 0 | AG31: Truncated Normal
A32: 213.7 | B32: =IF(ISNUMBER(A32), IF(AND(A32=INT(A32), MOD(A32, 10) = 0), 0, IF(AND(A32=INT(A32), LEN(A32)=2), 1, IF(AND(A32=INT(A32), LEN(A32)=3), 2, LEN(A32) - FIND(".", A32) + 2) ) ), "") | C32: Manufacturing Facility Admin Building | D32: =REPT(" ", B32*2) & C32
A33: 213.71 | B33: =IF(ISNUMBER(A33), IF(AND(A33=INT(A33), MOD(A33, 10) = 0), 0, IF(AND(A33=INT(A33), LEN(A33)=2), 1, IF(AND(A33=INT(A33), LEN(A33)=3), 2, LEN(A33) - FIND(".", A33) + 2) ) ), "") | C33: =_xlfn.CONCAT(C32," Roof") | D33: =REPT(" ", B33*2) & C33 | E33: standard | F33: Constant | G33: 1 | K33: =1200 | L33: $/m^3 | M33: =_xlfn.CONCAT(C33, " Volume") | O33: m^3 | Q33: 2024 | R33: Lab and Mat and Equip | S33: RSMeans software: a tool that primarily provides costs for non-nuclear work Nuclear Multiplier have not been applied | T33: GORDIAN. (2024). "RSMeans data. & Delene, J. G. and I. Hudson, C. R. (1993). Cost estimate guidelines for advanced nuclear power technologies. United States, Oak Ridge National Lab. (ORNL), Oak Ridge, TN (United States): Medium: ED; Size: 159 p. | U33: https://www.rsmeans.com/ & https://www.osti.gov/biblio/10176857 | W33: No Learning | X33: =0.9*$I33 | Y33: =1.5*J33 | Z33: Lognormal | AA33: =0.9*K33 | AB33: =1.3*K33 | AC33: Lognormal | AD33: 0.1 | AE33: 1 | AF33: 0 | AG33: Truncated Normal
A34: 213.72 | B34: =IF(ISNUMBER(A34), IF(AND(A34=INT(A34), MOD(A34, 10) = 0), 0, IF(AND(A34=INT(A34), LEN(A34)=2), 1, IF(AND(A34=INT(A34), LEN(A34)=3), 2, LEN(A34) - FIND(".", A34) + 2) ) ), "") | C34: =_xlfn.CONCAT(C32," Basement") | D34: =REPT(" ", B34*2) & C34 | E34: standard | F34: Constant | G34: 1 | K34: =943.9 | L34: $/m^3 | M34: =_xlfn.CONCAT(C34, " Volume") | O34: m^3 | Q34: 2024 | R34: Lab and Mat and Equip | W34: No Learning | X34: =0.9*$I34 | Y34: =1.5*J34 | Z34: Lognormal | AA34: =0.9*K34 | AB34: =1.3*K34 | AC34: Lognormal | AD34: 0.1 | AE34: 1 | AF34: 0 | AG34: Truncated Normal
A35: 213.73 | B35: =IF(ISNUMBER(A35), IF(AND(A35=INT(A35), MOD(A35, 10) = 0), 0, IF(AND(A35=INT(A35), LEN(A35)=2), 1, IF(AND(A35=INT(A35), LEN(A35)=3), 2, LEN(A35) - FIND(".", A35) + 2) ) ), "") | C35: =_xlfn.CONCAT(C32," Walls") | D35: =REPT(" ", B35*2) & C35 | E35: standard | F35: Constant | G35: 1 | K35: =721.21 | L35: $/m^3 | M35: =_xlfn.CONCAT(C35, " Volume") | O35: m^3 | Q35: 2024 | R35: Lab and Mat and Equip | W35: No Learning | X35: =0.9*$I35 | Y35: =1.5*J35 | Z35: Lognormal | AA35: =0.9*K35 | AB35: =1.3*K35 | AC35: Lognormal | AD35: 0.1 | AE35: 1 | AF35: 0 | AG35: Truncated Normal
A36: 213.79 | B36: =IF(ISNUMBER(A36), IF(AND(A36=INT(A36), MOD(A36, 10) = 0), 0, IF(AND(A36=INT(A36), LEN(A36)=2), 1, IF(AND(A36=INT(A36), LEN(A36)=3), 2, LEN(A36) - FIND(".", A36) + 2) ) ), "") | C36: HVAC | D36: =REPT(" ", B36*2) & C36 | E36: standard | F36: Constant | G36: 1 | L36: $/m^3 | M36: =_xlfn.CONCAT(C32, " Volume") | O36: m^3 | W36: No Learning | X36: =0.9*$I36 | Y36: =1.5*J36 | Z36: Lognormal | AA36: =0.9*K36 | AB36: =1.3*K36 | AC36: Lognormal | AD36: 0.1 | AE36: 1 | AF36: 0 | AG36: Truncated Normal
A37: 213.8 | B37: =IF(ISNUMBER(A37), IF(AND(A37=INT(A37), MOD(A37, 10) = 0), 0, IF(AND(A37=INT(A37), LEN(A37)=2), 1, IF(AND(A37=INT(A37), LEN(A37)=3), 2, LEN(A37) - FIND(".", A37) + 2) ) ), "") | C37: Manufacturing Facility Security Building | D37: =REPT(" ", B37*2) & C37
A38: 213.81 | B38: =IF(ISNUMBER(A38), IF(AND(A38=INT(A38), MOD(A38, 10) = 0), 0, IF(AND(A38=INT(A38), LEN(A38)=2), 1, IF(AND(A38=INT(A38), LEN(A38)=3), 2, LEN(A38) - FIND(".", A38) + 2) ) ), "") | C38: =_xlfn.CONCAT(C37," Roof") | D38: =REPT(" ", B38*2) & C38 | E38: standard | F38: Constant | G38: 1 | K38: =1200 | L38: $/m^3 | M38: =_xlfn.CONCAT(C38, " Volume") | O38: m^3 | Q38: 2024 | R38: Lab and Mat and Equip | S38: RSMeans software: a tool that primarily provides costs for non-nuclear work Nuclear Multiplier have not been applied | T38: GORDIAN. (2024). "RSMeans data. & Delene, J. G. and I. Hudson, C. R. (1993). Cost estimate guidelines for advanced nuclear power technologies. United States, Oak Ridge National Lab. (ORNL), Oak Ridge, TN (United States): Medium: ED; Size: 159 p. | U38: https://www.rsmeans.com/ & https://www.osti.gov/biblio/10176857 | W38: No Learning | X38: =0.9*$I38 | Y38: =1.5*J38 | Z38: Lognormal | AA38: =0.9*K38 | AB38: =1.3*K38 | AC38: Lognormal | AD38: 0.1 | AE38: 1 | AF38: 0 | AG38: Truncated Normal
A39: 213.82 | B39: =IF(ISNUMBER(A39), IF(AND(A39=INT(A39), MOD(A39, 10) = 0), 0, IF(AND(A39=INT(A39), LEN(A39)=2), 1, IF(AND(A39=INT(A39), LEN(A39)=3), 2, LEN(A39) - FIND(".", A39) + 2) ) ), "") | C39: =_xlfn.CONCAT(C37," Basement") | D39: =REPT(" ", B39*2) & C39 | E39: standard | F39: Constant | G39: 1 | K39: =943.9 | L39: $/m^3 | M39: =_xlfn.CONCAT(C39, " Volume") | O39: m^3 | Q39: 2024 | R39: Lab and Mat and Equip | W39: No Learning | X39: =0.9*$I39 | Y39: =1.5*J39 | Z39: Lognormal | AA39: =0.9*K39 | AB39: =1.3*K39 | AC39: Lognormal | AD39: 0.1 | AE39: 1 | AF39: 0 | AG39: Truncated Normal
A40: 213.83 | B40: =IF(ISNUMBER(A40), IF(AND(A40=INT(A40), MOD(A40, 10) = 0), 0, IF(AND(A40=INT(A40), LEN(A40)=2), 1, IF(AND(A40=INT(A40), LEN(A40)=3), 2, LEN(A40) - FIND(".", A40) + 2) ) ), "") | C40: =_xlfn.CONCAT(C37," Walls") | D40: =REPT(" ", B40*2) & C40 | E40: standard | F40: Constant | G40: 1 | K40: =721.21 | L40: $/m^3 | M40: =_xlfn.CONCAT(C40, " Volume") | O40: m^3 | Q40: 2024 | R40: Lab and Mat and Equip | W40: No Learning | X40: =0.9*$I40 | Y40: =1.5*J40 | Z40: Lognormal | AA40: =0.9*K40 | AB40: =1.3*K40 | AC40: Lognormal | AD40: 0.1 | AE40: 1 | AF40: 0 | AG40: Truncated Normal
A41: 213.89 | B41: =IF(ISNUMBER(A41), IF(AND(A41=INT(A41), MOD(A41, 10) = 0), 0, IF(AND(A41=INT(A41), LEN(A41)=2), 1, IF(AND(A41=INT(A41), LEN(A41)=3), 2, LEN(A41) - FIND(".", A41) + 2) ) ), "") | C41: HVAC | D41: =REPT(" ", B41*2) & C41 | E41: standard | F41: Constant | G41: 1 | L41: $/m^3 | M41: =_xlfn.CONCAT(C37, " Volume") | O41: m^3 | W41: No Learning | X41: =0.9*$I41 | Y41: =1.5*J41 | Z41: Lognormal | AA41: =0.9*K41 | AB41: =1.3*K41 | AC41: Lognormal | AD41: 0.1 | AE41: 1 | AF41: 0 | AG41: Truncated Normal
A42: 213.9 | B42: =IF(ISNUMBER(A42), IF(AND(A42=INT(A42), MOD(A42, 10) = 0), 0, IF(AND(A42=INT(A42), LEN(A42)=2), 1, IF(AND(A42=INT(A42), LEN(A42)=3), 2, LEN(A42) - FIND(".", A42) + 2) ) ), "") | C42: Security Fencing | D42: =REPT(" ", B42*2) & C42 | E42: standard | F42: Constant | G42: 1 | K42: =75/0.3048 | L42: $/m | M42: Factory Perimeter | Q42: 2009 | R42: Lab and Equip | S42: Ref Table 2-8 | T42: Kessler. Cost Estimate for an Away-From-Reactor Generic Interim Storage Facility (GISF) for Spent Nuclear Fuel. EPRI. 2009. | U42: https://www.epri.com/research/products/1018722 | W42: No Learning | X42: =0.9*$J42 | Y42: =1.5*J42 | Z42: Lognormal | AA42: =0.9*K42 | AB42: =1.3*K42 | AC42: Lognormal | AD42: 0.1 | AE42: 1 | AF42: 0 | AG42: Truncated Normal
A43: 214 | B43: =IF(ISNUMBER(A43), IF(AND(A43=INT(A43), MOD(A43, 10) = 0), 0, IF(AND(A43=INT(A43), LEN(A43)=2), 1, IF(AND(A43=INT(A43), LEN(A43)=3), 2, LEN(A43) - FIND(".", A43) + 2) ) ), "") | C43: Servicing Facility | D43: =REPT(" ", B43*2) & C43
A44: 214.1 | B44: =IF(ISNUMBER(A44), IF(AND(A44=INT(A44), MOD(A44, 10) = 0), 0, IF(AND(A44=INT(A44), LEN(A44)=2), 1, IF(AND(A44=INT(A44), LEN(A44)=3), 2, LEN(A44) - FIND(".", A44) + 2) ) ), "") | C44: Servicing Building | D44: =REPT(" ", B44*2) & C44
A45: 213.11 | B45: =IF(ISNUMBER(A45), IF(AND(A45=INT(A45), MOD(A45, 10) = 0), 0, IF(AND(A45=INT(A45), LEN(A45)=2), 1, IF(AND(A45=INT(A45), LEN(A45)=3), 2, LEN(A45) - FIND(".", A45) + 2) ) ), "") | C45: =_xlfn.CONCAT(C44," Roof") | D45: =REPT(" ", B45*2) & C45 | E45: standard | F45: Constant | G45: 1 | K45: =1200 *1.53 | L45: $/m^3 | M45: =_xlfn.CONCAT(C45, " Volume") | O45: m^3 | Q45: 2024 | R45: Lab and Mat and Equip | S45: RSMeans software: a tool that primarily provides costs for non-nuclear work Nuclear Multiplier have not been applied | T45: GORDIAN. (2024). "RSMeans data. & Delene, J. G. and I. Hudson, C. R. (1993). Cost estimate guidelines for advanced nuclear power technologies. United States, Oak Ridge National Lab. (ORNL), Oak Ridge, TN (United States): Medium: ED; Size: 159 p. | U45: https://www.rsmeans.com/ & https://www.osti.gov/biblio/10176857 | W45: No Learning | X45: =0.9*$I45 | Y45: =1.5*J45 | Z45: Lognormal | AA45: =0.9*K45 | AB45: =1.3*K45 | AC45: Lognormal | AD45: 0.1 | AE45: 1 | AF45: 0 | AG45: Truncated Normal
A46: 213.12 | B46: =IF(ISNUMBER(A46), IF(AND(A46=INT(A46), MOD(A46, 10) = 0), 0, IF(AND(A46=INT(A46), LEN(A46)=2), 1, IF(AND(A46=INT(A46), LEN(A46)=3), 2, LEN(A46) - FIND(".", A46) + 2) ) ), "") | C46: =_xlfn.CONCAT(C44," Basement") | D46: =REPT(" ", B46*2) & C46 | E46: standard | F46: Constant | G46: 1 | K46: =943.9*1.53 | L46: $/m^3 | M46: =_xlfn.CONCAT(C46, " Volume") | O46: m^3 | Q46: 2024 | R46: Lab and Mat and Equip | W46: No Learning | X46: =0.9*$I46 | Y46: =1.5*J46 | Z46: Lognormal | AA46: =0.9*K46 | AB46: =1.3*K46 | AC46: Lognormal | AD46: 0.1 | AE46: 1 | AF46: 0 | AG46: Truncated Normal
A47: 213.13 | B47: =IF(ISNUMBER(A47), IF(AND(A47=INT(A47), MOD(A47, 10) = 0), 0, IF(AND(A47=INT(A47), LEN(A47)=2), 1, IF(AND(A47=INT(A47), LEN(A47)=3), 2, LEN(A47) - FIND(".", A47) + 2) ) ), "") | C47: =_xlfn.CONCAT(C44," Walls") | D47: =REPT(" ", B47*2) & C47 | E47: standard | F47: Constant | G47: 1 | K47: =721.21*1.53 | L47: $/m^3 | M47: =_xlfn.CONCAT(C47, " Volume") | O47: m^3 | Q47: 2024 | R47: Lab and Mat and Equip | W47: No Learning | X47: =0.9*$I47 | Y47: =1.5*J47 | Z47: Lognormal | AA47: =0.9*K47 | AB47: =1.3*K47 | AC47: Lognormal | AD47: 0.1 | AE47: 1 | AF47: 0 | AG47: Truncated Normal
A48: 214.14 | B48: =IF(ISNUMBER(A48), IF(AND(A48=INT(A48), MOD(A48, 10) = 0), 0, IF(AND(A48=INT(A48), LEN(A48)=2), 1, IF(AND(A48=INT(A48), LEN(A48)=3), 2, LEN(A48) - FIND(".", A48) + 2) ) ), "") | C48: Servicing Hot Cell | D48: =REPT(" ", B48*2) & C48 | E48: standard | F48: Servicing Hot Cell Count | W48: No Learning | X48: =0.8*$I48 | Y48: =2*J48 | Z48: Lognormal | AA48: =0.8*K48 | AB48: =2*K48 | AC48: Lognormal | AD48: 0.1 | AE48: 1 | AF48: 0 | AG48: Truncated Normal
A49: 214.141 | B49: =IF(ISNUMBER(A49), IF(AND(A49=INT(A49), MOD(A49, 10) = 0), 0, IF(AND(A49=INT(A49), LEN(A49)=2), 1, IF(AND(A49=INT(A49), LEN(A49)=3), 2, LEN(A49) - FIND(".", A49) + 2) ) ), "") | C49: Hot Cell Airlock | D49: =REPT(" ", B49*2) & C49 | E49: standard | F49: Servicing Hot Cell Count | G49: 4 | W49: No Learning | X49: =0.8*$I49 | Y49: =2*J49 | Z49: Lognormal | AA49: =0.8*K49 | AB49: =2*K49 | AC49: Lognormal | AD49: 0.1 | AE49: 1 | AF49: 0 | AG49: Truncated Normal
A50: 214.19 | B50: =IF(ISNUMBER(A50), IF(AND(A50=INT(A50), MOD(A50, 10) = 0), 0, IF(AND(A50=INT(A50), LEN(A50)=2), 1, IF(AND(A50=INT(A50), LEN(A50)=3), 2, LEN(A50) - FIND(".", A50) + 2) ) ), "") | C50: HVAC | D50: =REPT(" ", B50*2) & C50 | E50: standard | F50: Constant | G50: 1 | L50: $/m^3 | M50: =_xlfn.CONCAT(C44, " Volume") | W50: No Learning | X50: =0.9*$I50 | Y50: =1.5*J50 | Z50: Lognormal | AA50: =0.9*K50 | AB50: =1.3*K50 | AC50: Lognormal | AD50: 0.1 | AE50: 1 | AF50: 0 | AG50: Truncated Normal
A51: 214.2 | B51: =IF(ISNUMBER(A51), IF(AND(A51=INT(A51), MOD(A51, 10) = 0), 0, IF(AND(A51=INT(A51), LEN(A51)=2), 1, IF(AND(A51=INT(A51), LEN(A51)=3), 2, LEN(A51) - FIND(".", A51) + 2) ) ), "") | C51: Helium Purification and Storage Building
A52: 214.21 | B52: =IF(ISNUMBER(A52), IF(AND(A52=INT(A52), MOD(A52, 10) = 0), 0, IF(AND(A52=INT(A52), LEN(A52)=2), 1, IF(AND(A52=INT(A52), LEN(A52)=3), 2, LEN(A52) - FIND(".", A52) + 2) ) ), "") | C52: =_xlfn.CONCAT(C51," Roof") | D52: =REPT(" ", B52*2) & C52 | E52: standard | F52: Constant | G52: 1 | K52: =1200 *1.53 | L52: $/m^3 | M52: =_xlfn.CONCAT(C52, " Volume") | O52: m^3 | Q52: 2024 | R52: Lab and Mat and Equip | S52: RSMeans software: a tool that primarily provides costs for non-nuclear work Nuclear Multiplier have not been applied | T52: GORDIAN. (2024). "RSMeans data. & Delene, J. G. and I. Hudson, C. R. (1993). Cost estimate guidelines for advanced nuclear power technologies. United States, Oak Ridge National Lab. (ORNL), Oak Ridge, TN (United States): Medium: ED; Size: 159 p. | U52: https://www.rsmeans.com/ & https://www.osti.gov/biblio/10176857 | W52: No Learning | X52: =0.9*$I52 | Y52: =1.5*J52 | Z52: Lognormal | AA52: =0.9*K52 | AB52: =1.3*K52 | AC52: Lognormal | AD52: 0.1 | AE52: 1 | AF52: 0 | AG52: Truncated Normal
A53: 214.22 | B53: =IF(ISNUMBER(A53), IF(AND(A53=INT(A53), MOD(A53, 10) = 0), 0, IF(AND(A53=INT(A53), LEN(A53)=2), 1, IF(AND(A53=INT(A53), LEN(A53)=3), 2, LEN(A53) - FIND(".", A53) + 2) ) ), "") | C53: =_xlfn.CONCAT(C51," Basement") | D53: =REPT(" ", B53*2) & C53 | E53: standard | F53: Constant | G53: 1 | K53: =943.9*1.53 | L53: $/m^3 | M53: =_xlfn.CONCAT(C53, " Volume") | O53: m^3 | Q53: 2024 | R53: Lab and Mat and Equip | W53: No Learning | X53: =0.9*$I53 | Y53: =1.5*J53 | Z53: Lognormal | AA53: =0.9*K53 | AB53: =1.3*K53 | AC53: Lognormal | AD53: 0.1 | AE53: 1 | AF53: 0 | AG53: Truncated Normal
A54: 214.23 | B54: =IF(ISNUMBER(A54), IF(AND(A54=INT(A54), MOD(A54, 10) = 0), 0, IF(AND(A54=INT(A54), LEN(A54)=2), 1, IF(AND(A54=INT(A54), LEN(A54)=3), 2, LEN(A54) - FIND(".", A54) + 2) ) ), "") | C54: =_xlfn.CONCAT(C51," Walls") | D54: =REPT(" ", B54*2) & C54 | E54: standard | F54: Constant | G54: 1 | K54: =721.21*1.53 | L54: $/m^3 | M54: =_xlfn.CONCAT(C54, " Volume") | O54: m^3 | Q54: 2024 | R54: Lab and Mat and Equip | W54: No Learning | X54: =0.9*$I54 | Y54: =1.5*J54 | Z54: Lognormal | AA54: =0.9*K54 | AB54: =1.3*K54 | AC54: Lognormal | AD54: 0.1 | AE54: 1 | AF54: 0 | AG54: Truncated Normal
A55: 214.29 | B55: =IF(ISNUMBER(A55), IF(AND(A55=INT(A55), MOD(A55, 10) = 0), 0, IF(AND(A55=INT(A55), LEN(A55)=2), 1, IF(AND(A55=INT(A55), LEN(A55)=3), 2, LEN(A55) - FIND(".", A55) + 2) ) ), "") | C55: HVAC | D55: =REPT(" ", B55*2) & C55 | E55: standard | F55: Constant | G55: 1 | L55: $/m^3 | M55: =_xlfn.CONCAT(C51, " Volume") | W55: No Learning | X55: =0.9*$I55 | Y55: =1.5*J55 | Z55: Lognormal | AA55: =0.9*K55 | AB55: =1.3*K55 | AC55: Lognormal | AD55: 0.1 | AE55: 1 | AF55: 0 | AG55: Truncated Normal
A56: 214.6 | B56: 3 | C56: Servicing Facility Integrated Control Room | D56: =REPT(" ", B56*2) & C56
A57: 214.61 | B57: 4 | C57: =_xlfn.CONCAT(C56," Roof") | D57: =REPT(" ", B57*2) & C57 | E57: standard | F57: Constant | G57: 1 | K57: =1200 *1.53 | L57: $/m^3 | M57: =_xlfn.CONCAT(C57, " Volume") | O57: m^3 | Q57: 2024 | R57: Lab and Mat and Equip | S57: RSMeans software: a tool that primarily provides costs for non-nuclear work Nuclear Multiplier have not been applied | T57: GORDIAN. (2024). "RSMeans data. & Delene, J. G. and I. Hudson, C. R. (1993). Cost estimate guidelines for advanced nuclear power technologies. United States, Oak Ridge National Lab. (ORNL), Oak Ridge, TN (United States): Medium: ED; Size: 159 p. | U57: https://www.rsmeans.com/ & https://www.osti.gov/biblio/10176857 | W57: No Learning | X57: =0.9*$I57 | Y57: =1.5*J57 | Z57: Lognormal | AA57: =0.9*K57 | AB57: =1.3*K57 | AC57: Lognormal | AD57: 0.1 | AE57: 1 | AF57: 0 | AG57: Truncated Normal
A58: 214.62 | B58: =IF(ISNUMBER(A58), IF(AND(A58=INT(A58), MOD(A58, 10) = 0), 0, IF(AND(A58=INT(A58), LEN(A58)=2), 1, IF(AND(A58=INT(A58), LEN(A58)=3), 2, LEN(A58) - FIND(".", A58) + 2) ) ), "") | C58: =_xlfn.CONCAT(C56," Basement") | D58: =REPT(" ", B58*2) & C58 | E58: standard | F58: Constant | G58: 1 | K58: =943.9*1.53 | L58: $/m^3 | M58: =_xlfn.CONCAT(C58, " Volume") | O58: m^3 | Q58: 2024 | R58: Lab and Mat and Equip | W58: No Learning | X58: =0.9*$I58 | Y58: =1.5*J58 | Z58: Lognormal | AA58: =0.9*K58 | AB58: =1.3*K58 | AC58: Lognormal | AD58: 0.1 | AE58: 1 | AF58: 0 | AG58: Truncated Normal
A59: 214.63 | B59: =IF(ISNUMBER(A59), IF(AND(A59=INT(A59), MOD(A59, 10) = 0), 0, IF(AND(A59=INT(A59), LEN(A59)=2), 1, IF(AND(A59=INT(A59), LEN(A59)=3), 2, LEN(A59) - FIND(".", A59) + 2) ) ), "") | C59: =_xlfn.CONCAT(C56," Walls") | D59: =REPT(" ", B59*2) & C59 | E59: standard | F59: Constant | G59: 1 | K59: =721.21*1.53 | L59: $/m^3 | M59: =_xlfn.CONCAT(C59, " Volume") | O59: m^3 | Q59: 2024 | R59: Lab and Mat and Equip | W59: No Learning | X59: =0.9*$I59 | Y59: =1.5*J59 | Z59: Lognormal | AA59: =0.9*K59 | AB59: =1.3*K59 | AC59: Lognormal | AD59: 0.1 | AE59: 1 | AF59: 0 | AG59: Truncated Normal
A60: 214.69 | B60: =IF(ISNUMBER(A60), IF(AND(A60=INT(A60), MOD(A60, 10) = 0), 0, IF(AND(A60=INT(A60), LEN(A60)=2), 1, IF(AND(A60=INT(A60), LEN(A60)=3), 2, LEN(A60) - FIND(".", A60) + 2) ) ), "") | C60: HVAC | D60: =REPT(" ", B60*2) & C60 | E60: standard | F60: Constant | G60: 1 | L60: $/m^3 | M60: =_xlfn.CONCAT(C56, " Volume") | O60: m^3 | W60: No Learning | X60: =0.9*$I60 | Y60: =1.5*J60 | Z60: Lognormal | AA60: =0.9*K60 | AB60: =1.3*K60 | AC60: Lognormal | AD60: 0.1 | AE60: 1 | AF60: 0 | AG60: Truncated Normal
A61: 214.7 | B61: =IF(ISNUMBER(A61), IF(AND(A61=INT(A61), MOD(A61, 10) = 0), 0, IF(AND(A61=INT(A61), LEN(A61)=2), 1, IF(AND(A61=INT(A61), LEN(A61)=3), 2, LEN(A61) - FIND(".", A61) + 2) ) ), "") | C61: Servicing Facility Admin Building | D61: =REPT(" ", B61*2) & C61
A62: 214.71 | B62: =IF(ISNUMBER(A62), IF(AND(A62=INT(A62), MOD(A62, 10) = 0), 0, IF(AND(A62=INT(A62), LEN(A62)=2), 1, IF(AND(A62=INT(A62), LEN(A62)=3), 2, LEN(A62) - FIND(".", A62) + 2) ) ), "") | C62: =_xlfn.CONCAT(C61," Roof") | D62: =REPT(" ", B62*2) & C62 | E62: standard | F62: Constant | G62: 1 | K62: =1200 | L62: $/m^3 | M62: =_xlfn.CONCAT(C62, " Volume") | O62: m^3 | Q62: 2024 | R62: Lab and Mat and Equip | S62: RSMeans software: a tool that primarily provides costs for non-nuclear work Nuclear Multiplier have not been applied | T62: GORDIAN. (2024). "RSMeans data. & Delene, J. G. and I. Hudson, C. R. (1993). Cost estimate guidelines for advanced nuclear power technologies. United States, Oak Ridge National Lab. (ORNL), Oak Ridge, TN (United States): Medium: ED; Size: 159 p. | U62: https://www.rsmeans.com/ & https://www.osti.gov/biblio/10176857 | W62: No Learning | X62: =0.9*$I62 | Y62: =1.5*J62 | Z62: Lognormal | AA62: =0.9*K62 | AB62: =1.3*K62 | AC62: Lognormal | AD62: 0.1 | AE62: 1 | AF62: 0 | AG62: Truncated Normal
A63: 214.72 | B63: =IF(ISNUMBER(A63), IF(AND(A63=INT(A63), MOD(A63, 10) = 0), 0, IF(AND(A63=INT(A63), LEN(A63)=2), 1, IF(AND(A63=INT(A63), LEN(A63)=3), 2, LEN(A63) - FIND(".", A63) + 2) ) ), "") | C63: =_xlfn.CONCAT(C61," Basement") | D63: =REPT(" ", B63*2) & C63 | E63: standard | F63: Constant | G63: 1 | K63: =943.9 | L63: $/m^3 | M63: =_xlfn.CONCAT(C63, " Volume") | O63: m^3 | Q63: 2024 | R63: Lab and Mat and Equip | W63: No Learning | X63: =0.9*$I63 | Y63: =1.5*J63 | Z63: Lognormal | AA63: =0.9*K63 | AB63: =1.3*K63 | AC63: Lognormal | AD63: 0.1 | AE63: 1 | AF63: 0 | AG63: Truncated Normal
A64: 214.73 | B64: =IF(ISNUMBER(A64), IF(AND(A64=INT(A64), MOD(A64, 10) = 0), 0, IF(AND(A64=INT(A64), LEN(A64)=2), 1, IF(AND(A64=INT(A64), LEN(A64)=3), 2, LEN(A64) - FIND(".", A64) + 2) ) ), "") | C64: =_xlfn.CONCAT(C61," Walls") | D64: =REPT(" ", B64*2) & C64 | E64: standard | F64: Constant | G64: 1 | K64: =721.21 | L64: $/m^3 | M64: =_xlfn.CONCAT(C64, " Volume") | O64: m^3 | Q64: 2024 | R64: Lab and Mat and Equip | W64: No Learning | X64: =0.9*$I64 | Y64: =1.5*J64 | Z64: Lognormal | AA64: =0.9*K64 | AB64: =1.3*K64 | AC64: Lognormal | AD64: 0.1 | AE64: 1 | AF64: 0 | AG64: Truncated Normal
A65: 214.79 | B65: =IF(ISNUMBER(A65), IF(AND(A65=INT(A65), MOD(A65, 10) = 0), 0, IF(AND(A65=INT(A65), LEN(A65)=2), 1, IF(AND(A65=INT(A65), LEN(A65)=3), 2, LEN(A65) - FIND(".", A65) + 2) ) ), "") | C65: HVAC | D65: =REPT(" ", B65*2) & C65 | E65: standard | F65: Constant | G65: 1 | L65: $/m^3 | M65: =_xlfn.CONCAT(C61, " Volume") | O65: m^3 | W65: No Learning | X65: =0.9*$I65 | Y65: =1.5*J65 | Z65: Lognormal | AA65: =0.9*K65 | AB65: =1.3*K65 | AC65: Lognormal | AD65: 0.1 | AE65: 1 | AF65: 0 | AG65: Truncated Normal
A66: 214.8 | B66: =IF(ISNUMBER(A66), IF(AND(A66=INT(A66), MOD(A66, 10) = 0), 0, IF(AND(A66=INT(A66), LEN(A66)=2), 1, IF(AND(A66=INT(A66), LEN(A66)=3), 2, LEN(A66) - FIND(".", A66) + 2) ) ), "") | C66: Servicing Facility Security Building | D66: =REPT(" ", B66*2) & C66
A67: 214.81 | B67: =IF(ISNUMBER(A67), IF(AND(A67=INT(A67), MOD(A67, 10) = 0), 0, IF(AND(A67=INT(A67), LEN(A67)=2), 1, IF(AND(A67=INT(A67), LEN(A67)=3), 2, LEN(A67) - FIND(".", A67) + 2) ) ), "") | C67: =_xlfn.CONCAT(C66," Roof") | D67: =REPT(" ", B67*2) & C67 | E67: standard | F67: Constant | G67: 1 | K67: =1200 | L67: $/m^3 | M67: =_xlfn.CONCAT(C67, " Volume") | O67: m^3 | Q67: 2024 | R67: Lab and Mat and Equip | S67: RSMeans software: a tool that primarily provides costs for non-nuclear work Nuclear Multiplier have not been applied | T67: GORDIAN. (2024). "RSMeans data. & Delene, J. G. and I. Hudson, C. R. (1993). Cost estimate guidelines for advanced nuclear power technologies. United States, Oak Ridge National Lab. (ORNL), Oak Ridge, TN (United States): Medium: ED; Size: 159 p. | U67: https://www.rsmeans.com/ & https://www.osti.gov/biblio/10176857 | W67: No Learning | X67: =0.9*$I67 | Y67: =1.5*J67 | Z67: Lognormal | AA67: =0.9*K67 | AB67: =1.3*K67 | AC67: Lognormal | AD67: 0.1 | AE67: 1 | AF67: 0 | AG67: Truncated Normal
A68: 214.82 | B68: =IF(ISNUMBER(A68), IF(AND(A68=INT(A68), MOD(A68, 10) = 0), 0, IF(AND(A68=INT(A68), LEN(A68)=2), 1, IF(AND(A68=INT(A68), LEN(A68)=3), 2, LEN(A68) - FIND(".", A68) + 2) ) ), "") | C68: =_xlfn.CONCAT(C66," Basement") | D68: =REPT(" ", B68*2) & C68 | E68: standard | F68: Constant | G68: 1 | K68: =943.9 | L68: $/m^3 | M68: =_xlfn.CONCAT(C68, " Volume") | O68: m^3 | Q68: 2024 | R68: Lab and Mat and Equip | W68: No Learning | X68: =0.9*$I68 | Y68: =1.5*J68 | Z68: Lognormal | AA68: =0.9*K68 | AB68: =1.3*K68 | AC68: Lognormal | AD68: 0.1 | AE68: 1 | AF68: 0 | AG68: Truncated Normal
A69: 214.83 | B69: =IF(ISNUMBER(A69), IF(AND(A69=INT(A69), MOD(A69, 10) = 0), 0, IF(AND(A69=INT(A69), LEN(A69)=2), 1, IF(AND(A69=INT(A69), LEN(A69)=3), 2, LEN(A69) - FIND(".", A69) + 2) ) ), "") | C69: =_xlfn.CONCAT(C66," Walls") | D69: =REPT(" ", B69*2) & C69 | E69: standard | F69: Constant | G69: 1 | K69: =721.21 | L69: $/m^3 | M69: =_xlfn.CONCAT(C69, " Volume") | O69: m^3 | Q69: 2024 | R69: Lab and Mat and Equip | W69: No Learning | X69: =0.9*$I69 | Y69: =1.5*J69 | Z69: Lognormal | AA69: =0.9*K69 | AB69: =1.3*K69 | AC69: Lognormal | AD69: 0.1 | AE69: 1 | AF69: 0 | AG69: Truncated Normal
A70: 214.89 | B70: =IF(ISNUMBER(A70), IF(AND(A70=INT(A70), MOD(A70, 10) = 0), 0, IF(AND(A70=INT(A70), LEN(A70)=2), 1, IF(AND(A70=INT(A70), LEN(A70)=3), 2, LEN(A70) - FIND(".", A70) + 2) ) ), "") | C70: HVAC | D70: =REPT(" ", B70*2) & C70 | E70: standard | F70: Constant | G70: 1 | L70: $/m^3 | M70: =_xlfn.CONCAT(C66, " Volume") | O70: m^3 | W70: No Learning | X70: =0.9*$I70 | Y70: =1.5*J70 | Z70: Lognormal | AA70: =0.9*K70 | AB70: =1.3*K70 | AC70: Lognormal | AD70: 0.1 | AE70: 1 | AF70: 0 | AG70: Truncated Normal
A71: 214.9 | B71: =IF(ISNUMBER(A71), IF(AND(A71=INT(A71), MOD(A71, 10) = 0), 0, IF(AND(A71=INT(A71), LEN(A71)=2), 1, IF(AND(A71=INT(A71), LEN(A71)=3), 2, LEN(A71) - FIND(".", A71) + 2) ) ), "") | C71: Security Fencing | D71: =REPT(" ", B71*2) & C71 | E71: standard | F71: Constant | G71: 1 | K71: =75/0.3048 | L71: $/m | M71: Servicing Facility Perimeter | Q71: 2009 | R71: Lab and Equip | S71: Ref Table 2-8 | T71: Kessler. Cost Estimate for an Away-From-Reactor Generic Interim Storage Facility (GISF) for Spent Nuclear Fuel. EPRI. 2009. | U71: https://www.epri.com/research/products/1018722 | W71: No Learning | X71: =0.9*$J71 | Y71: =1.5*J71 | Z71: Lognormal | AA71: =0.9*K71 | AB71: =1.3*K71 | AC71: Lognormal | AD71: 0.1 | AE71: 1 | AF71: 0 | AG71: Truncated Normal
A72: 215 | B72: =IF(ISNUMBER(A72), IF(AND(A72=INT(A72), MOD(A72, 10) = 0), 0, IF(AND(A72=INT(A72), LEN(A72)=2), 1, IF(AND(A72=INT(A72), LEN(A72)=3), 2, LEN(A72) - FIND(".", A72) + 2) ) ), "") | C72: New Reactor Fuel and Testing Facility | D72: =REPT(" ", B72*2) & C72
A73: 215.1 | B73: =IF(ISNUMBER(A73), IF(AND(A73=INT(A73), MOD(A73, 10) = 0), 0, IF(AND(A73=INT(A73), LEN(A73)=2), 1, IF(AND(A73=INT(A73), LEN(A73)=3), 2, LEN(A73) - FIND(".", A73) + 2) ) ), "") | C73: Fresh Fuel Storage and Inspection Building | D73: =REPT(" ", B73*2) & C73
A74: 215.11 | B74: =IF(ISNUMBER(A74), IF(AND(A74=INT(A74), MOD(A74, 10) = 0), 0, IF(AND(A74=INT(A74), LEN(A74)=2), 1, IF(AND(A74=INT(A74), LEN(A74)=3), 2, LEN(A74) - FIND(".", A74) + 2) ) ), "") | C74: =_xlfn.CONCAT(C73," Roof") | D74: =REPT(" ", B74*2) & C74 | E74: standard | F74: Constant | G74: 1 | K74: =1200 *1.53 | L74: $/m^3 | M74: =_xlfn.CONCAT(C74, " Volume") | O74: m^3 | Q74: 2024 | R74: Lab and Mat and Equip | S74: RSMeans software: a tool that primarily provides costs for non-nuclear work Nuclear Multiplier have been applied to adjust the costs for nuclear-site-related work | T74: GORDIAN. (2024). "RSMeans data. & Delene, J. G. and I. Hudson, C. R. (1993). Cost estimate guidelines for advanced nuclear power technologies. United States, Oak Ridge National Lab. (ORNL), Oak Ridge, TN (United States): Medium: ED; Size: 159 p. | U74: https://www.rsmeans.com/ & https://www.osti.gov/biblio/10176857 | W74: No Learning | X74: =0.9*$I74 | Y74: =1.5*J74 | Z74: Lognormal | AA74: =0.9*K74 | AB74: =1.3*K74 | AC74: Lognormal | AD74: 0.1 | AE74: 1 | AF74: 0 | AG74: Truncated Normal
A75: 215.12 | B75: =IF(ISNUMBER(A75), IF(AND(A75=INT(A75), MOD(A75, 10) = 0), 0, IF(AND(A75=INT(A75), LEN(A75)=2), 1, IF(AND(A75=INT(A75), LEN(A75)=3), 2, LEN(A75) - FIND(".", A75) + 2) ) ), "") | C75: =_xlfn.CONCAT(C73," Basement") | D75: =REPT(" ", B75*2) & C75 | E75: standard | F75: Constant | G75: 1 | K75: =943.9*1.53 | L75: $/m^3 | M75: =_xlfn.CONCAT(C75, " Volume") | O75: m^3 | Q75: 2024 | R75: Lab and Mat and Equip | W75: No Learning | X75: =0.9*$I75 | Y75: =1.5*J75 | Z75: Lognormal | AA75: =0.9*K75 | AB75: =1.3*K75 | AC75: Lognormal | AD75: 0.1 | AE75: 1 | AF75: 0 | AG75: Truncated Normal
A76: 215.13 | B76: =IF(ISNUMBER(A76), IF(AND(A76=INT(A76), MOD(A76, 10) = 0), 0, IF(AND(A76=INT(A76), LEN(A76)=2), 1, IF(AND(A76=INT(A76), LEN(A76)=3), 2, LEN(A76) - FIND(".", A76) + 2) ) ), "") | C76: =_xlfn.CONCAT(C73," Walls") | D76: =REPT(" ", B76*2) & C76 | E76: standard | F76: Constant | G76: 1 | K76: =721.21*1.53 | L76: $/m^3 | M76: =_xlfn.CONCAT(C76, " Volume") | O76: m^3 | Q76: 2024 | R76: Lab and Mat and Equip | W76: No Learning | X76: =0.9*$I76 | Y76: =1.5*J76 | Z76: Lognormal | AA76: =0.9*K76 | AB76: =1.3*K76 | AC76: Lognormal | AD76: 0.1 | AE76: 1 | AF76: 0 | AG76: Truncated Normal
A77: 215.19 | B77: =IF(ISNUMBER(A77), IF(AND(A77=INT(A77), MOD(A77, 10) = 0), 0, IF(AND(A77=INT(A77), LEN(A77)=2), 1, IF(AND(A77=INT(A77), LEN(A77)=3), 2, LEN(A77) - FIND(".", A77) + 2) ) ), "") | C77: HVAC | D77: =REPT(" ", B77*2) & C77 | E77: standard | F77: Constant | G77: 1 | L77: $/m^3 | M77: =_xlfn.CONCAT(C73, " Volume") | O77: m^3 | W77: No Learning | X77: =0.9*$I77 | Y77: =1.5*J77 | Z77: Lognormal | AA77: =0.9*K77 | AB77: =1.3*K77 | AC77: Lognormal | AD77: 0.1 | AE77: 1 | AF77: 0 | AG77: Truncated Normal
A78: 215.2 | B78: =IF(ISNUMBER(A78), IF(AND(A78=INT(A78), MOD(A78, 10) = 0), 0, IF(AND(A78=INT(A78), LEN(A78)=2), 1, IF(AND(A78=INT(A78), LEN(A78)=3), 2, LEN(A78) - FIND(".", A78) + 2) ) ), "") | C78: Reactor Fueling Building | D78: =REPT(" ", B78*2) & C78
A79: 215.21 | B79: =IF(ISNUMBER(A79), IF(AND(A79=INT(A79), MOD(A79, 10) = 0), 0, IF(AND(A79=INT(A79), LEN(A79)=2), 1, IF(AND(A79=INT(A79), LEN(A79)=3), 2, LEN(A79) - FIND(".", A79) + 2) ) ), "") | C79: =_xlfn.CONCAT(C78," Roof") | D79: =REPT(" ", B79*2) & C79 | E79: standard | F79: Constant | G79: 1 | K79: =1200 *1.53 | L79: $/m^3 | M79: =_xlfn.CONCAT(C79, " Volume") | O79: m^3 | Q79: 2024 | R79: Lab and Mat and Equip | S79: RSMeans software: a tool that primarily provides costs for non-nuclear work Nuclear Multiplier have been applied to adjust the costs for nuclear-site-related work | T79: GORDIAN. (2024). "RSMeans data. & Delene, J. G. and I. Hudson, C. R. (1993). Cost estimate guidelines for advanced nuclear power technologies. United States, Oak Ridge National Lab. (ORNL), Oak Ridge, TN (United States): Medium: ED; Size: 159 p. | U79: https://www.rsmeans.com/ & https://www.osti.gov/biblio/10176857 | W79: No Learning | X79: =0.9*$I79 | Y79: =1.5*J79 | Z79: Lognormal | AA79: =0.9*K79 | AB79: =1.3*K79 | AC79: Lognormal | AD79: 0.1 | AE79: 1 | AF79: 0 | AG79: Truncated Normal
A80: 215.22 | B80: =IF(ISNUMBER(A80), IF(AND(A80=INT(A80), MOD(A80, 10) = 0), 0, IF(AND(A80=INT(A80), LEN(A80)=2), 1, IF(AND(A80=INT(A80), LEN(A80)=3), 2, LEN(A80) - FIND(".", A80) + 2) ) ), "") | C80: =_xlfn.CONCAT(C78," Basement") | D80: =REPT(" ", B80*2) & C80 | E80: standard | F80: Constant | G80: 1 | K80: =943.9*1.53 | L80: $/m^3 | M80: =_xlfn.CONCAT(C80, " Volume") | O80: m^3 | Q80: 2024 | R80: Lab and Mat and Equip | W80: No Learning | X80: =0.9*$I80 | Y80: =1.5*J80 | Z80: Lognormal | AA80: =0.9*K80 | AB80: =1.3*K80 | AC80: Lognormal | AD80: 0.1 | AE80: 1 | AF80: 0 | AG80: Truncated Normal
A81: 215.23 | B81: =IF(ISNUMBER(A81), IF(AND(A81=INT(A81), MOD(A81, 10) = 0), 0, IF(AND(A81=INT(A81), LEN(A81)=2), 1, IF(AND(A81=INT(A81), LEN(A81)=3), 2, LEN(A81) - FIND(".", A81) + 2) ) ), "") | C81: =_xlfn.CONCAT(C78," Walls") | D81: =REPT(" ", B81*2) & C81 | E81: standard | F81: Constant | G81: 1 | K81: =721.21*1.53 | L81: $/m^3 | M81: =_xlfn.CONCAT(C81, " Volume") | O81: m^3 | Q81: 2024 | R81: Lab and Mat and Equip | W81: No Learning | X81: =0.9*$I81 | Y81: =1.5*J81 | Z81: Lognormal | AA81: =0.9*K81 | AB81: =1.3*K81 | AC81: Lognormal | AD81: 0.1 | AE81: 1 | AF81: 0 | AG81: Truncated Normal
A82: 215.24 | B82: =IF(ISNUMBER(A82), IF(AND(A82=INT(A82), MOD(A82, 10) = 0), 0, IF(AND(A82=INT(A82), LEN(A82)=2), 1, IF(AND(A82=INT(A82), LEN(A82)=3), 2, LEN(A82) - FIND(".", A82) + 2) ) ), "") | C82: Reactor Fueling Hot Cell | D82: =REPT(" ", B82*2) & C82 | E82: standard | F82: New Reactor Fueling Line Count | W82: No Learning | X82: =0.8*$I82 | Y82: =2*J82 | Z82: Lognormal | AA82: =0.8*K82 | AB82: =2*K82 | AC82: Lognormal | AD82: 0.1 | AE82: 1 | AF82: 0 | AG82: Truncated Normal
A83: 215.241 | B83: =IF(ISNUMBER(A83), IF(AND(A83=INT(A83), MOD(A83, 10) = 0), 0, IF(AND(A83=INT(A83), LEN(A83)=2), 1, IF(AND(A83=INT(A83), LEN(A83)=3), 2, LEN(A83) - FIND(".", A83) + 2) ) ), "") | C83: Hot Cell Airlock | D83: =REPT(" ", B83*2) & C83 | E83: standard | F83: Servicing Hot Cell Count | G83: 4 | W83: No Learning | X83: =0.8*$I83 | Y83: =2*J83 | Z83: Lognormal | AA83: =0.8*K83 | AB83: =2*K83 | AC83: Lognormal | AD83: 0.1 | AE83: 1 | AF83: 0 | AG83: Truncated Normal
A84: 215.29 | B84: =IF(ISNUMBER(A84), IF(AND(A84=INT(A84), MOD(A84, 10) = 0), 0, IF(AND(A84=INT(A84), LEN(A84)=2), 1, IF(AND(A84=INT(A84), LEN(A84)=3), 2, LEN(A84) - FIND(".", A84) + 2) ) ), "") | C84: HVAC | D84: =REPT(" ", B84*2) & C84 | E84: standard | F84: Constant | G84: 1 | L84: $/m^3 | M84: =_xlfn.CONCAT(C78, " Volume") | O84: m^3 | W84: No Learning | X84: =0.9*$I84 | Y84: =1.5*J84 | Z84: Lognormal | AA84: =0.9*K84 | AB84: =1.3*K84 | AC84: Lognormal | AD84: 0.1 | AE84: 1 | AF84: 0 | AG84: Truncated Normal
A85: 215.3 | B85: =IF(ISNUMBER(A85), IF(AND(A85=INT(A85), MOD(A85, 10) = 0), 0, IF(AND(A85=INT(A85), LEN(A85)=2), 1, IF(AND(A85=INT(A85), LEN(A85)=3), 2, LEN(A85) - FIND(".", A85) + 2) ) ), "") | C85: Reactor Testing Building | D85: =REPT(" ", B85*2) & C85
A86: 215.31 | B86: =IF(ISNUMBER(A86), IF(AND(A86=INT(A86), MOD(A86, 10) = 0), 0, IF(AND(A86=INT(A86), LEN(A86)=2), 1, IF(AND(A86=INT(A86), LEN(A86)=3), 2, LEN(A86) - FIND(".", A86) + 2) ) ), "") | C86: =_xlfn.CONCAT(C85," Roof") | D86: =REPT(" ", B86*2) & C86 | E86: standard | F86: Constant | G86: 1 | K86: =1200 *1.53 | L86: $/m^3 | M86: =_xlfn.CONCAT(C86, " Volume") | O86: m^3 | Q86: 2024 | R86: Lab and Mat and Equip | S86: RSMeans software: a tool that primarily provides costs for non-nuclear work Nuclear Multiplier have been applied to adjust the costs for nuclear-site-related work | T86: GORDIAN. (2024). "RSMeans data. & Delene, J. G. and I. Hudson, C. R. (1993). Cost estimate guidelines for advanced nuclear power technologies. United States, Oak Ridge National Lab. (ORNL), Oak Ridge, TN (United States): Medium: ED; Size: 159 p. | U86: https://www.rsmeans.com/ & https://www.osti.gov/biblio/10176857 | W86: No Learning | X86: =0.9*$I86 | Y86: =1.5*J86 | Z86: Lognormal | AA86: =0.9*K86 | AB86: =1.3*K86 | AC86: Lognormal | AD86: 0.1 | AE86: 1 | AF86: 0 | AG86: Truncated Normal
A87: 215.32 | B87: =IF(ISNUMBER(A87), IF(AND(A87=INT(A87), MOD(A87, 10) = 0), 0, IF(AND(A87=INT(A87), LEN(A87)=2), 1, IF(AND(A87=INT(A87), LEN(A87)=3), 2, LEN(A87) - FIND(".", A87) + 2) ) ), "") | C87: =_xlfn.CONCAT(C85," Basement") | D87: =REPT(" ", B87*2) & C87 | E87: standard | F87: Constant | G87: 1 | K87: =943.9*1.53 | L87: $/m^3 | M87: =_xlfn.CONCAT(C87, " Volume") | O87: m^3 | Q87: 2024 | R87: Lab and Mat and Equip | W87: No Learning | X87: =0.9*$I87 | Y87: =1.5*J87 | Z87: Lognormal | AA87: =0.9*K87 | AB87: =1.3*K87 | AC87: Lognormal | AD87: 0.1 | AE87: 1 | AF87: 0 | AG87: Truncated Normal
A88: 215.33 | B88: =IF(ISNUMBER(A88), IF(AND(A88=INT(A88), MOD(A88, 10) = 0), 0, IF(AND(A88=INT(A88), LEN(A88)=2), 1, IF(AND(A88=INT(A88), LEN(A88)=3), 2, LEN(A88) - FIND(".", A88) + 2) ) ), "") | C88: =_xlfn.CONCAT(C85," Walls") | D88: =REPT(" ", B88*2) & C88 | E88: standard | F88: Constant | G88: 1 | K88: =721.21*1.53 | L88: $/m^3 | M88: =_xlfn.CONCAT(C88, " Volume") | O88: m^3 | Q88: 2024 | R88: Lab and Mat and Equip | W88: No Learning | X88: =0.9*$I88 | Y88: =1.5*J88 | Z88: Lognormal | AA88: =0.9*K88 | AB88: =1.3*K88 | AC88: Lognormal | AD88: 0.1 | AE88: 1 | AF88: 0 | AG88: Truncated Normal
A89: 215.34 | B89: =IF(ISNUMBER(A89), IF(AND(A89=INT(A89), MOD(A89, 10) = 0), 0, IF(AND(A89=INT(A89), LEN(A89)=2), 1, IF(AND(A89=INT(A89), LEN(A89)=3), 2, LEN(A89) - FIND(".", A89) + 2) ) ), "") | C89: Reactor Testing Hot Cell | D89: =REPT(" ", B89*2) & C89 | E89: standard | F89: New Reactor Testing Line Count | W89: No Learning | X89: =0.8*$I89 | Y89: =2*J89 | Z89: Lognormal | AA89: =0.8*K89 | AB89: =2*K89 | AC89: Lognormal | AD89: 0.1 | AE89: 1 | AF89: 0 | AG89: Truncated Normal
A90: 215.341 | B90: =IF(ISNUMBER(A90), IF(AND(A90=INT(A90), MOD(A90, 10) = 0), 0, IF(AND(A90=INT(A90), LEN(A90)=2), 1, IF(AND(A90=INT(A90), LEN(A90)=3), 2, LEN(A90) - FIND(".", A90) + 2) ) ), "") | C90: Hot Cell Airlock | D90: =REPT(" ", B90*2) & C90 | E90: standard | F90: New Reactor Fueling Line Count | G90: 4 | W90: No Learning | X90: =0.8*$I90 | Y90: =2*J90 | Z90: Lognormal | AA90: =0.8*K90 | AB90: =2*K90 | AC90: Lognormal | AD90: 0.1 | AE90: 1 | AF90: 0 | AG90: Truncated Normal
A91: 215.39 | B91: =IF(ISNUMBER(A91), IF(AND(A91=INT(A91), MOD(A91, 10) = 0), 0, IF(AND(A91=INT(A91), LEN(A91)=2), 1, IF(AND(A91=INT(A91), LEN(A91)=3), 2, LEN(A91) - FIND(".", A91) + 2) ) ), "") | C91: HVAC | D91: =REPT(" ", B91*2) & C91 | E91: standard | F91: Constant | G91: 1 | M91: =_xlfn.CONCAT(C85, " Volume") | W91: No Learning | X91: =0.9*$I91 | Y91: =1.5*J91 | Z91: Lognormal | AA91: =0.9*K91 | AB91: =1.3*K91 | AC91: Lognormal | AD91: 0.1 | AE91: 1 | AF91: 0 | AG91: Truncated Normal
A92: 215.7 | B92: =IF(ISNUMBER(A92), IF(AND(A92=INT(A92), MOD(A92, 10) = 0), 0, IF(AND(A92=INT(A92), LEN(A92)=2), 1, IF(AND(A92=INT(A92), LEN(A92)=3), 2, LEN(A92) - FIND(".", A92) + 2) ) ), "") | C92: New Reactor Fuel and Testing Facility Admin Building | D92: =REPT(" ", B92*2) & C92
A93: 215.71 | B93: =IF(ISNUMBER(A93), IF(AND(A93=INT(A93), MOD(A93, 10) = 0), 0, IF(AND(A93=INT(A93), LEN(A93)=2), 1, IF(AND(A93=INT(A93), LEN(A93)=3), 2, LEN(A93) - FIND(".", A93) + 2) ) ), "") | C93: =_xlfn.CONCAT(C92," Roof") | D93: =REPT(" ", B93*2) & C93 | E93: standard | F93: Constant | G93: 1 | K93: =1200 | L93: $/m^3 | M93: =_xlfn.CONCAT(C93, " Volume") | O93: m^3 | Q93: 2024 | R93: Lab and Mat and Equip | S93: RSMeans software: a tool that primarily provides costs for non-nuclear work Nuclear Multiplier have not been applied | T93: GORDIAN. (2024). "RSMeans data. & Delene, J. G. and I. Hudson, C. R. (1993). Cost estimate guidelines for advanced nuclear power technologies. United States, Oak Ridge National Lab. (ORNL), Oak Ridge, TN (United States): Medium: ED; Size: 159 p. | U93: https://www.rsmeans.com/ & https://www.osti.gov/biblio/10176857 | W93: No Learning | X93: =0.9*$I93 | Y93: =1.5*J93 | Z93: Lognormal | AA93: =0.9*K93 | AB93: =1.3*K93 | AC93: Lognormal | AD93: 0.1 | AE93: 1 | AF93: 0 | AG93: Truncated Normal
A94: 215.72 | B94: =IF(ISNUMBER(A94), IF(AND(A94=INT(A94), MOD(A94, 10) = 0), 0, IF(AND(A94=INT(A94), LEN(A94)=2), 1, IF(AND(A94=INT(A94), LEN(A94)=3), 2, LEN(A94) - FIND(".", A94) + 2) ) ), "") | C94: =_xlfn.CONCAT(C92," Basement") | D94: =REPT(" ", B94*2) & C94 | E94: standard | F94: Constant | G94: 1 | K94: =943.9 | L94: $/m^3 | M94: =_xlfn.CONCAT(C94, " Volume") | O94: m^3 | Q94: 2024 | R94: Lab and Mat and Equip | W94: No Learning | X94: =0.9*$I94 | Y94: =1.5*J94 | Z94: Lognormal | AA94: =0.9*K94 | AB94: =1.3*K94 | AC94: Lognormal | AD94: 0.1 | AE94: 1 | AF94: 0 | AG94: Truncated Normal
A95: 215.73 | B95: =IF(ISNUMBER(A95), IF(AND(A95=INT(A95), MOD(A95, 10) = 0), 0, IF(AND(A95=INT(A95), LEN(A95)=2), 1, IF(AND(A95=INT(A95), LEN(A95)=3), 2, LEN(A95) - FIND(".", A95) + 2) ) ), "") | C95: =_xlfn.CONCAT(C92," Walls") | D95: =REPT(" ", B95*2) & C95 | E95: standard | F95: Constant | G95: 1 | K95: =721.21 | L95: $/m^3 | M95: =_xlfn.CONCAT(C95, " Volume") | O95: m^3 | Q95: 2024 | R95: Lab and Mat and Equip | W95: No Learning | X95: =0.9*$I95 | Y95: =1.5*J95 | Z95: Lognormal | AA95: =0.9*K95 | AB95: =1.3*K95 | AC95: Lognormal | AD95: 0.1 | AE95: 1 | AF95: 0 | AG95: Truncated Normal
A96: 215.79 | B96: =IF(ISNUMBER(A96), IF(AND(A96=INT(A96), MOD(A96, 10) = 0), 0, IF(AND(A96=INT(A96), LEN(A96)=2), 1, IF(AND(A96=INT(A96), LEN(A96)=3), 2, LEN(A96) - FIND(".", A96) + 2) ) ), "") | C96: HVAC | D96: =REPT(" ", B96*2) & C96 | E96: standard | F96: Constant | G96: 1 | L96: $/m^3 | M96: =_xlfn.CONCAT(C92, " Volume") | O96: m^3 | W96: No Learning | X96: =0.9*$I96 | Y96: =1.5*J96 | Z96: Lognormal | AA96: =0.9*K96 | AB96: =1.3*K96 | AC96: Lognormal | AD96: 0.1 | AE96: 1 | AF96: 0 | AG96: Truncated Normal
A97: 215.8 | B97: =IF(ISNUMBER(A97), IF(AND(A97=INT(A97), MOD(A97, 10) = 0), 0, IF(AND(A97=INT(A97), LEN(A97)=2), 1, IF(AND(A97=INT(A97), LEN(A97)=3), 2, LEN(A97) - FIND(".", A97) + 2) ) ), "") | C97: New Reactor Fuel and Testing Facility Security Building | D97: =REPT(" ", B97*2) & C97
A98: 215.81 | B98: =IF(ISNUMBER(A98), IF(AND(A98=INT(A98), MOD(A98, 10) = 0), 0, IF(AND(A98=INT(A98), LEN(A98)=2), 1, IF(AND(A98=INT(A98), LEN(A98)=3), 2, LEN(A98) - FIND(".", A98) + 2) ) ), "") | C98: =_xlfn.CONCAT(C97," Roof") | D98: =REPT(" ", B98*2) & C98 | E98: standard | F98: Constant | G98: 1 | K98: =1200 | L98: $/m^3 | M98: =_xlfn.CONCAT(C98, " Volume") | O98: m^3 | Q98: 2024 | R98: Lab and Mat and Equip | S98: RSMeans software: a tool that primarily provides costs for non-nuclear work Nuclear Multiplier have not been applied | T98: GORDIAN. (2024). "RSMeans data. & Delene, J. G. and I. Hudson, C. R. (1993). Cost estimate guidelines for advanced nuclear power technologies. United States, Oak Ridge National Lab. (ORNL), Oak Ridge, TN (United States): Medium: ED; Size: 159 p. | U98: https://www.rsmeans.com/ & https://www.osti.gov/biblio/10176857 | W98: No Learning | X98: =0.9*$I98 | Y98: =1.5*J98 | Z98: Lognormal | AA98: =0.9*K98 | AB98: =1.3*K98 | AC98: Lognormal | AD98: 0.1 | AE98: 1 | AF98: 0 | AG98: Truncated Normal
A99: 215.82 | B99: =IF(ISNUMBER(A99), IF(AND(A99=INT(A99), MOD(A99, 10) = 0), 0, IF(AND(A99=INT(A99), LEN(A99)=2), 1, IF(AND(A99=INT(A99), LEN(A99)=3), 2, LEN(A99) - FIND(".", A99) + 2) ) ), "") | C99: =_xlfn.CONCAT(C97," Basement") | D99: =REPT(" ", B99*2) & C99 | E99: standard | F99: Constant | G99: 1 | K99: =943.9 | L99: $/m^3 | M99: =_xlfn.CONCAT(C99, " Volume") | O99: m^3 | Q99: 2024 | R99: Lab and Mat and Equip | W99: No Learning | X99: =0.9*$I99 | Y99: =1.5*J99 | Z99: Lognormal | AA99: =0.9*K99 | AB99: =1.3*K99 | AC99: Lognormal | AD99: 0.1 | AE99: 1 | AF99: 0 | AG99: Truncated Normal
A100: 215.83 | B100: =IF(ISNUMBER(A100), IF(AND(A100=INT(A100), MOD(A100, 10) = 0), 0, IF(AND(A100=INT(A100), LEN(A100)=2), 1, IF(AND(A100=INT(A100), LEN(A100)=3), 2, LEN(A100) - FIND(".", A100) + 2) ) ), "") | C100: =_xlfn.CONCAT(C97," Walls") | D100: =REPT(" ", B100*2) & C100 | E100: standard | F100: Constant | G100: 1 | K100: =721.21 | L100: $/m^3 | M100: =_xlfn.CONCAT(C100, " Volume") | O100: m^3 | Q100: 2024 | R100: Lab and Mat and Equip | W100: No Learning | X100: =0.9*$I100 | Y100: =1.5*J100 | Z100: Lognormal | AA100: =0.9*K100 | AB100: =1.3*K100 | AC100: Lognormal | AD100: 0.1 | AE100: 1 | AF100: 0 | AG100: Truncated Normal
...
