Workbook
Name CRF: #REF!
Name DiscountRate: #REF!
Name FacilityLifetime: #REF!
Name GeneralDataManufacturingLocations: #REF!
Name MaterialData316SSStandardDensity: #REF!
Name MaterialDataA36CSStandardDensity: #REF!
Name MaterialDataB4CNaturalTheoreticalDensity: #REF!
Name MaterialDataConcreteNominalSolidDensity: #REF!
Name MaterialDataGeneralInsulationStandardDensity: #REF!
Name MaterialDataGR22StandardDensity: #REF!
Name MaterialDataInconel718StandardDensity: #REF!
Name UC_m_in: #REF!

Sheet Cost Database
A1: Account | B1: Level | C1: Account Name | D1: Account Title | E1: Standard Cost Equation? | F1: Optional Variable | G1: Optional Value | H1: Sec Optional Variable | I1: Sec Optional Value | J1: Fixed Cost ($) | K1: Unit Cost | L1: Unit Cost (units) | M1: Scaling Variable | N1: Scaling Variable Ref Value | O1: Units | P1: Exponent | Q1: Dollar Year | R1: Type | S1: Source | T1: Ref | U1: Link | V1: Notes | W1: FOAK to NOAK Multiplier Type | X1: Fixed Cost Low End | Y1: Fixed Cost High End | Z1: Fixed Cost Distribution | AA1: Unit Cost Low End | AB1: Unit Cost High End | AC1: Unit Cost Distribution | AD1: Exponent std | AE1: Exponent Max | AF1: Exponent Min | AG1: Exponent Distribution
A2: 10 | B2: =IF(ISNUMBER(A2), IF(AND(A2=INT(A2), MOD(A2, 10) = 0), 0, IF(AND(A2=INT(A2), LEN(A2)=2), 1, IF(AND(A2=INT(A2), LEN(A2)=3), 2, LEN(A2) - FIND(".", A2) + 2) ) ), "") -> 0 | C2: Capitalized Pre-Construction Costs | D2: =REPT(" ", B2*2) & C2 -> Capitalized Pre-Construction Costs
A3: 11 | B3: =IF(ISNUMBER(A3), IF(AND(A3=INT(A3), MOD(A3, 10) = 0), 0, IF(AND(A3=INT(A3), LEN(A3)=2), 1, IF(AND(A3=INT(A3), LEN(A3)=3), 2, LEN(A3) - FIND(".", A3) + 2) ) ), "") -> 1 | C3: Land Cost | D3: =REPT(" ", B3*2) & C3 -> Land Cost | E3: standard | K3: 3800 | L3: $/acres | M3: Land Area | O3: acres | Q3: 2022 | R3: General | S3: The average cost per acre for rural land in 2022 from the US Department of Agriculture | T3: Abou-Jaoude, A., Lohse, C. S., Larsen, L. M., Guaita, N., Trivedi, I., Joseck, F. C., ... & Stein, A. (2024). Meta-analysis of advanced nuclear reactor cost estimations (No. INL/RPT-24-77048-Rev001). Idaho National Laboratory (INL), Idaho Falls, ID (United States). | U3: https://inldigitallibrary.inl.gov/sites/sti/sti/Sort_107010.pdf | W3: No Learning | X3: =0.9*$J3 -> 0 | Y3: =1.5*J3 -> 0 | Z3: Lognormal | AA3: =0.9*K3 -> 3420 | AB3: =1.3*K3 -> 4940 | AC3: Lognormal | AD3: 0.1 | AE3: 1 | AF3: 0 | AG3: Truncated Normal
A4: 12 | B4: =IF(ISNUMBER(A4), IF(AND(A4=INT(A4), MOD(A4, 10) = 0), 0, IF(AND(A4=INT(A4), LEN(A4)=2), 1, IF(AND(A4=INT(A4), LEN(A4)=3), 2, LEN(A4) - FIND(".", A4) + 2) ) ), "") -> 1 | C4: Site Permits | D4: =REPT(" ", B4*2) & C4 -> Site Permits | E4: standard | K4: =10.03*1000 -> 10030 | L4: $/MWe | M4: Power MWe | O4: MWe | Q4: 2022 | R4: Labor | S4: Data from SMR MHTGRs | W4: No Learning | X4: =0.9*$J4 -> 0 | Y4: =1.5*J4 -> 0 | Z4: Lognormal | AA4: =0.9*K4 -> 9027 | AB4: =1.3*K4 -> 13039 | AC4: Lognormal | AD4: 0.1 | AE4: 1 | AF4: 0 | AG4: Truncated Normal
A5: 13 | B5: =IF(ISNUMBER(A5), IF(AND(A5=INT(A5), MOD(A5, 10) = 0), 0, IF(AND(A5=INT(A5), LEN(A5)=2), 1, IF(AND(A5=INT(A5), LEN(A5)=3), 2, LEN(A5) - FIND(".", A5) + 2) ) ), "") -> 1 | C5: Plant Licensing | D5: =REPT(" ", B5*2) & C5 -> Plant Licensing | E5: standard | J5: =0.5*(X5+Y5) -> 27025000 | Q5: 2024 | R5: Labor | S5: NRC Website | T5: Using data from the NRC website that the cost is between 45 and 70M https://www.nrc.gov/about-nrc/regulatory/licensing/general-fee-questions.pdf Also, using recent change to the NRC fees by a factor of 0.47 https://ignition-news.com/the-nrc-passes-new-rules-for-advanced-reactor-companies/#:~:text=Under%20a%20rule%20published%20in,2024%2C%20which%20takes%20effect%20Oct. | U5: https://art.inl.gov/NGNP/INL%20Documents/Year%202012/Assessment%20of%20High%20Temperature%20Gas-Cooled%20Reactor%20-%20HTGR%20-%20Capital%20and%20Operating%20Costs.pdf | W5: Licensing Learning | X5: =0.47*45*1000000 -> 21150000 | Y5: =0.47*70*1000000 -> 32900000 | Z5: Uniform | AA5: =0.9*K5 -> 0 | AB5: =1.3*K5 -> 0 | AC5: Lognormal | AD5: 0.1 | AE5: 1 | AF5: 0 | AG5: Truncated Normal
A6: 14 | B6: =IF(ISNUMBER(A6), IF(AND(A6=INT(A6), MOD(A6, 10) = 0), 0, IF(AND(A6=INT(A6), LEN(A6)=2), 1, IF(AND(A6=INT(A6), LEN(A6)=3), 2, LEN(A6) - FIND(".", A6) + 2) ) ), "") -> 1 | C6: Plant Permits | D6: =REPT(" ", B6*2) & C6 -> Plant Permits | E6: standard | J6: 3000000 | Q6: 2009 | R6: Labor | S6: NGNP project | T6: Gandrik, A., B. Wallace, L. Demick, S. Melancon and M. Patterson (2011). "Assessment of high temperature gas-cooled reactor (HTGR) capital and operating costs." Idaho National Laboratory, TEV-1196, Idaho Falls, ID. | W6: No Learning | X6: =0.9*$J6 -> 2700000 | Y6: =1.5*J6 -> 4500000 | Z6: Lognormal | AA6: =0.9*K6 -> 0 | AB6: =1.3*K6 -> 0 | AC6: Lognormal | AD6: 0.1 | AE6: 1 | AF6: 0 | AG6: Truncated Normal
A7: 15 | B7: =IF(ISNUMBER(A7), IF(AND(A7=INT(A7), MOD(A7, 10) = 0), 0, IF(AND(A7=INT(A7), LEN(A7)=2), 1, IF(AND(A7=INT(A7), LEN(A7)=3), 2, LEN(A7) - FIND(".", A7) + 2) ) ), "") -> 1 | C7: Plant Studies | D7: =REPT(" ", B7*2) & C7 -> Plant Studies | E7: standard | J7: =MARVEL_Cost!C4 -> 5210451 | Q7: 2024 | R7: Labor | S7: MARVEL Project (Labor-adjusted Cost) | T7: Hanna, B. N., Gonzaga de Oliveira, R. G., Mohammad Al Dawood, K. A., Patterson, M. D., Abou Jaoude, A., & Garcia, S. (2024). Technoeconomic Evaluation of Microreactor Using Detailed Bottom-up Estimate (No. INL/RPT-24-80433-Rev000). Idaho National Laboratory (INL), Idaho Falls, ID (United States). | U7: https://inldigitallibrary.inl.gov/sites/sti/sti/Sort_129862.pdf | V7: MARVEL's data were updated | W7: No Learning | X7: =0.9*$J7 -> 4689405.9 | Y7: =1.5*J7 -> 7815676.5 | Z7: Lognormal | AA7: =0.9*K7 -> 0 | AB7: =1.3*K7 -> 0 | AC7: Lognormal | AD7: 0.1 | AE7: 1 | AF7: 0 | AG7: Truncated Normal
A8: 20 | B8: =IF(ISNUMBER(A8), IF(AND(A8=INT(A8), MOD(A8, 10) = 0), 0, IF(AND(A8=INT(A8), LEN(A8)=2), 1, IF(AND(A8=INT(A8), LEN(A8)=3), 2, LEN(A8) - FIND(".", A8) + 2) ) ), "") -> 0 | C8: Capitalized Direct Costs | D8: =REPT(" ", B8*2) & C8 -> Capitalized Direct Costs
A9: 21 | B9: =IF(ISNUMBER(A9), IF(AND(A9=INT(A9), MOD(A9, 10) = 0), 0, IF(AND(A9=INT(A9), LEN(A9)=2), 1, IF(AND(A9=INT(A9), LEN(A9)=3), 2, LEN(A9) - FIND(".", A9) + 2) ) ), "") -> 1 | C9: Structures and Improvements | D9: =REPT(" ", B9*2) & C9 -> Structures and Improvements
A10: 211 | B10: =IF(ISNUMBER(A10), IF(AND(A10=INT(A10), MOD(A10, 10) = 0), 0, IF(AND(A10=INT(A10), LEN(A10)=2), 1, IF(AND(A10=INT(A10), LEN(A10)=3), 2, LEN(A10) - FIND(".", A10) + 2) ) ), "") -> 2 | C10: Site Preparation/ Yard Work | D10: =REPT(" ", B10*2) & C10 -> Site Preparation/ Yard Work
A11: 211.1 | B11: =IF(ISNUMBER(A11), IF(AND(A11=INT(A11), MOD(A11, 10) = 0), 0, IF(AND(A11=INT(A11), LEN(A11)=2), 1, IF(AND(A11=INT(A11), LEN(A11)=3), 2, LEN(A11) - FIND(".", A11) + 2) ) ), "") -> 3 | C11: Cleaning and Grubbing | D11: =REPT(" ", B11*2) & C11 -> Cleaning and Grubbing | E11: standard | K11: =4408.18*1.33 -> 5862.8794 | L11: $/acres | M11: Land Area | O11: acres | Q11: 2024 | R11: Lab and Equip | S11: RSMeans software: a tool that primarily provides costs for non-nuclear work Nuclear Multiplier have been applied to adjust the costs for nuclear-site-related work | T11: GORDIAN. (2024). "RSMeans data. & Delene, J. G. and I. Hudson, C. R. (1993). Cost estimate guidelines for advanced nuclear power technologies. United States, Oak Ridge National Lab. (ORNL), Oak Ridge, TN (United States): Medium: ED; Size: 159 p. | U11: https://www.rsmeans.com/ & https://www.osti.gov/biblio/10176857 | W11: Onsite Learning | X11: =0.9*$J11 -> 0 | Y11: =1.5*J11 -> 0 | Z11: Lognormal | AA11: =0.9*K11 -> 5276.5915 | AB11: =1.3*K11 -> 7621.7432 | AC11: Lognormal | AD11: 0.1 | AE11: 1 | AF11: 0 | AG11: Truncated Normal
A12: 211.2 | B12: =IF(ISNUMBER(A12), IF(AND(A12=INT(A12), MOD(A12, 10) = 0), 0, IF(AND(A12=INT(A12), LEN(A12)=2), 1, IF(AND(A12=INT(A12), LEN(A12)=3), 2, LEN(A12) - FIND(".", A12) + 2) ) ), "") -> 3 | C12: Stripping Topsoil | D12: =REPT(" ", B12*2) & C12 -> Stripping Topsoil | E12: standard | K12: =2565.2*1.33 -> 3411.716 | L12: $/acres | M12: Land Area | O12: acres | Q12: 2024 | R12: Lab and Equip | W12: Onsite Learning | X12: =0.9*$J12 -> 0 | Y12: =1.5*J12 -> 0 | Z12: Lognormal | AA12: =0.9*K12 -> 3070.5444 | AB12: =1.3*K12 -> 4435.2308 | AC12: Lognormal | AD12: 0.1 | AE12: 1 | AF12: 0 | AG12: Truncated Normal
A13: 211.3 | B13: =IF(ISNUMBER(A13), IF(AND(A13=INT(A13), MOD(A13, 10) = 0), 0, IF(AND(A13=INT(A13), LEN(A13)=2), 1, IF(AND(A13=INT(A13), LEN(A13)=3), 2, LEN(A13) - FIND(".", A13) + 2) ) ), "") -> 3 | C13: Excavation | D13: =REPT(" ", B13*2) & C13 -> Excavation | E13: standard | K13: =22.86*1.4 -> 32.004 | L13: $/m^3 | M13: Excavation Volume | O13: m^3 | Q13: 2024 | R13: Lab and Equip | W13: Onsite Learning | X13: =0.9*$J13 -> 0 | Y13: =1.5*J13 -> 0 | Z13: Lognormal | AA13: =0.9*K13 -> 28.8036 | AB13: =1.3*K13 -> 41.6052 | AC13: Lognormal | AD13: 0.1 | AE13: 1 | AF13: 0 | AG13: Truncated Normal
A14: 212 | B14: =IF(ISNUMBER(A14), IF(AND(A14=INT(A14), MOD(A14, 10) = 0), 0, IF(AND(A14=INT(A14), LEN(A14)=2), 1, IF(AND(A14=INT(A14), LEN(A14)=3), 2, LEN(A14) - FIND(".", A14) + 2) ) ), "") -> 2 | C14: Reactor Island Civil Structures | D14: =REPT(" ", B14*2) & C14 -> Reactor Island Civil Structures
A15: 212.1 | B15: =IF(ISNUMBER(A15), IF(AND(A15=INT(A15), MOD(A15, 10) = 0), 0, IF(AND(A15=INT(A15), LEN(A15)=2), 1, IF(AND(A15=INT(A15), LEN(A15)=3), 2, LEN(A15) - FIND(".", A15) + 2) ) ), "") -> 3 | C15: Reactor Building Slab Roof | D15: =REPT(" ", B15*2) & C15 -> Reactor Building Slab Roof | E15: standard | K15: =1200 *1.53 -> 1836 | L15: $/m^3 | M15: Reactor Building Slab Roof Volume | O15: m^3 | Q15: 2024 | R15: Lab and Mat and Equip | S15: RSMeans software: a tool that primarily provides costs for non-nuclear work Nuclear Multiplier have been applied to adjust the costs for nuclear-site-related work | T15: GORDIAN. (2024). "RSMeans data. & Delene, J. G. and I. Hudson, C. R. (1993). Cost estimate guidelines for advanced nuclear power technologies. United States, Oak Ridge National Lab. (ORNL), Oak Ridge, TN (United States): Medium: ED; Size: 159 p. | U15: https://www.rsmeans.com/ & https://www.osti.gov/biblio/10176857 | W15: Onsite Learning | X15: =0.9*$J15 -> 0 | Y15: =1.5*J15 -> 0 | Z15: Lognormal | AA15: =0.9*K15 -> 1652.4 | AB15: =1.3*K15 -> 2386.8 | AC15: Lognormal | AD15: 0.1 | AE15: 1 | AF15: 0 | AG15: Truncated Normal
A16: 212.2 | B16: =IF(ISNUMBER(A16), IF(AND(A16=INT(A16), MOD(A16, 10) = 0), 0, IF(AND(A16=INT(A16), LEN(A16)=2), 1, IF(AND(A16=INT(A16), LEN(A16)=3), 2, LEN(A16) - FIND(".", A16) + 2) ) ), "") -> 3 | C16: Reactor Building Basement | D16: =REPT(" ", B16*2) & C16 -> Reactor Building Basement | E16: standard | K16: =943.9*1.53 -> 1444.167 | L16: $/m^3 | M16: Reactor Building Basement Volume | O16: m^3 | Q16: 2024 | R16: Lab and Mat and Equip | W16: Onsite Learning | X16: =0.9*$J16 -> 0 | Y16: =1.5*J16 -> 0 | Z16: Lognormal | AA16: =0.9*K16 -> 1299.7503 | AB16: =1.3*K16 -> 1877.4171 | AC16: Lognormal | AD16: 0.1 | AE16: 1 | AF16: 0 | AG16: Truncated Normal
A17: 212.3 | B17: =IF(ISNUMBER(A17), IF(AND(A17=INT(A17), MOD(A17, 10) = 0), 0, IF(AND(A17=INT(A17), LEN(A17)=2), 1, IF(AND(A17=INT(A17), LEN(A17)=3), 2, LEN(A17) - FIND(".", A17) + 2) ) ), "") -> 3 | C17: Reactor Building Walls | D17: =REPT(" ", B17*2) & C17 -> Reactor Building Walls | E17: standard | K17: =721.21*1.53 -> 1103.4513 | L17: $/m^3 | M17: Reactor Building Exterior Walls Volume | O17: m^3 | Q17: 2024 | R17: Lab and Mat and Equip | W17: Onsite Learning | X17: =0.9*$J17 -> 0 | Y17: =1.5*J17 -> 0 | Z17: Lognormal | AA17: =0.9*K17 -> 993.10617 | AB17: =1.3*K17 -> 1434.4867 | AC17: Lognormal | AD17: 0.1 | AE17: 1 | AF17: 0 | AG17: Truncated Normal
A18: 212.4 | B18: =IF(ISNUMBER(A18), IF(AND(A18=INT(A18), MOD(A18, 10) = 0), 0, IF(AND(A18=INT(A18), LEN(A18)=2), 1, IF(AND(A18=INT(A18), LEN(A18)=3), 2, LEN(A18) - FIND(".", A18) + 2) ) ), "") -> 3 | C18: Reactor Building Liner | D18: =REPT(" ", B18*2) & C18 -> Reactor Building Liner | E18: standard | K18: =60848829/9373 -> 6491.9267 | L18: $/m^2 | M18: Reactor Building Superstructure Area | N18: 9373 | O18: m^2 | P18: 1 | Q18: 2018 | R18: Lab and Mat and Equip | S18: Stewart W.R., Shirvan K., "Capital cost estimation for advanced nuclear power plants," Renewable and Sustainable Energy Reviews, Nov. 2021, 111880 | T18: Stewart W.R., Shirvan K., "Capital cost estimation for advanced nuclear power plants," Renewable and Sustainable Energy Reviews, Nov. 2021, 111880 | U18: https://doi.org/10.1016/j.rser.2021.111880 | W18: Onsite Learning | X18: =0.9*$J18 -> 0 | Y18: =1.5*J18 -> 0 | Z18: Lognormal | AA18: =0.9*K18 -> 5842.734 | AB18: =1.3*K18 -> 8439.5047 | AC18: Lognormal | AD18: 0.1 | AE18: 1 | AF18: 0 | AG18: Truncated Normal
A19: 212.5 | B19: =IF(ISNUMBER(A19), IF(AND(A19=INT(A19), MOD(A19, 10) = 0), 0, IF(AND(A19=INT(A19), LEN(A19)=2), 1, IF(AND(A19=INT(A19), LEN(A19)=3), 2, LEN(A19) - FIND(".", A19) + 2) ) ), "") -> 3 | C19: Reactor Building HVAC | D19: =REPT(" ", B19*2) & C19 -> Reactor Building HVAC | E19: standard | K19: =5917967/N19 -> 1731.9189 | L19: $/MWt | M19: Power MWt | N19: 3417 | O19: MWt | P19: 0.8 | Q19: 2018 | R19: Lab and Mat and Equip | S19: Stewart W.R., Shirvan K., "Capital cost estimation for advanced nuclear power plants," Renewable and Sustainable Energy Reviews, Nov. 2021, 111880 | T19: Stewart W.R., Shirvan K., "Capital cost estimation for advanced nuclear power plants," Renewable and Sustainable Energy Reviews, Nov. 2021, 111880 | U19: https://doi.org/10.1016/j.rser.2021.111880 | W19: Onsite Learning | X19: =0.9*$J19 -> 0 | Y19: =1.5*J19 -> 0 | Z19: Lognormal | AA19: =0.9*K19 -> 1558.727 | AB19: =1.3*K19 -> 2251.4946 | AC19: Lognormal | AD19: 0.1 | AE19: 1 | AF19: 0 | AG19: Truncated Normal
A20: 213 | B20: =IF(ISNUMBER(A20), IF(AND(A20=INT(A20), MOD(A20, 10) = 0), 0, IF(AND(A20=INT(A20), LEN(A20)=2), 1, IF(AND(A20=INT(A20), LEN(A20)=3), 2, LEN(A20) - FIND(".", A20) + 2) ) ), "") -> 2 | C20: Main Function Buildings | D20: =REPT(" ", B20*2) & C20 -> Main Function Buildings
A21: 213.1 | B21: =IF(ISNUMBER(A21), IF(AND(A21=INT(A21), MOD(A21, 10) = 0), 0, IF(AND(A21=INT(A21), LEN(A21)=2), 1, IF(AND(A21=INT(A21), LEN(A21)=3), 2, LEN(A21) - FIND(".", A21) + 2) ) ), "") -> 3 | C21: Energy conversion Building | D21: =REPT(" ", B21*2) & C21 -> Energy conversion Building
A22: 213.11 | B22: =IF(ISNUMBER(A22), IF(AND(A22=INT(A22), MOD(A22, 10) = 0), 0, IF(AND(A22=INT(A22), LEN(A22)=2), 1, IF(AND(A22=INT(A22), LEN(A22)=3), 2, LEN(A22) - FIND(".", A22) + 2) ) ), "") -> 4 | C22: Energy Conversion Building Slab Roof | D22: =REPT(" ", B22*2) & C22 -> Energy Conversion Building Slab Roof | E22: standard | K22: =1200 -> 1200 | L22: $/m^3 | M22: Turbine Building Slab Roof Volume | O22: m^3 | Q22: 2024 | R22: Lab and Mat and Equip | S22: RSMeans software: a tool that primarily provides costs for non-nuclear work | T22: GORDIAN. (2024). "RSMeans data. & Delene, J. G. and I. Hudson, C. R. (1993). Cost estimate guidelines for advanced nuclear power technologies. United States, Oak Ridge National Lab. (ORNL), Oak Ridge, TN (United States): Medium: ED; Size: 159 p. | U22: https://www.rsmeans.com/ & https://www.osti.gov/biblio/10176857 | W22: Onsite Learning | X22: =0.9*$J22 -> 0 | Y22: =1.5*J22 -> 0 | Z22: Lognormal | AA22: =0.9*K22 -> 1080 | AB22: =1.3*K22 -> 1560 | AC22: Lognormal | AD22: 0.1 | AE22: 1 | AF22: 0 | AG22: Truncated Normal
A23: 213.12 | B23: =IF(ISNUMBER(A23), IF(AND(A23=INT(A23), MOD(A23, 10) = 0), 0, IF(AND(A23=INT(A23), LEN(A23)=2), 1, IF(AND(A23=INT(A23), LEN(A23)=3), 2, LEN(A23) - FIND(".", A23) + 2) ) ), "") -> 4 | C23: Energy Conversion Building Basement | D23: =REPT(" ", B23*2) & C23 -> Energy Conversion Building Basement | E23: standard | K23: =943.9 -> 943.9 | L23: $/m^3 | M23: Turbine Building Basement Volume | O23: m^3 | Q23: 2024 | R23: Lab and Mat and Equip | W23: Onsite Learning | X23: =0.9*$J23 -> 0 | Y23: =1.5*J23 -> 0 | Z23: Lognormal | AA23: =0.9*K23 -> 849.51 | AB23: =1.3*K23 -> 1227.07 | AC23: Lognormal | AD23: 0.1 | AE23: 1 | AF23: 0 | AG23: Truncated Normal
A24: 213.13 | B24: =IF(ISNUMBER(A24), IF(AND(A24=INT(A24), MOD(A24, 10) = 0), 0, IF(AND(A24=INT(A24), LEN(A24)=2), 1, IF(AND(A24=INT(A24), LEN(A24)=3), 2, LEN(A24) - FIND(".", A24) + 2) ) ), "") -> 4 | C24: Energy Conversion Building Walls | D24: =REPT(" ", B24*2) & C24 -> Energy Conversion Building Walls | E24: standard | K24: =721.21 -> 721.21 | L24: $/m^3 | M24: Turbine Building Exterior Walls Volume | O24: m^3 | Q24: 2024 | R24: Lab and Mat and Equip | W24: Onsite Learning | X24: =0.9*$J24 -> 0 | Y24: =1.5*J24 -> 0 | Z24: Lognormal | AA24: =0.9*K24 -> 649.089 | AB24: =1.3*K24 -> 937.573 | AC24: Lognormal | AD24: 0.1 | AE24: 1 | AF24: 0 | AG24: Truncated Normal
A25: 213.2 | B25: =IF(ISNUMBER(A25), IF(AND(A25=INT(A25), MOD(A25, 10) = 0), 0, IF(AND(A25=INT(A25), LEN(A25)=2), 1, IF(AND(A25=INT(A25), LEN(A25)=3), 2, LEN(A25) - FIND(".", A25) + 2) ) ), "") -> 3 | C25: Control building | D25: =REPT(" ", B25*2) & C25 -> Control building
A26: 213.21 | B26: =IF(ISNUMBER(A26), IF(AND(A26=INT(A26), MOD(A26, 10) = 0), 0, IF(AND(A26=INT(A26), LEN(A26)=2), 1, IF(AND(A26=INT(A26), LEN(A26)=3), 2, LEN(A26) - FIND(".", A26) + 2) ) ), "") -> 4 | C26: Control Building Slab Roof | D26: =REPT(" ", B26*2) & C26 -> Control Building Slab Roof | E26: standard | K26: =1200 -> 1200 | L26: $/m^3 | M26: Control Building Slab Roof Volume | O26: m^3 | Q26: 2024 | R26: Lab and Mat and Equip | S26: RSMeans software: a tool that primarily provides costs for non-nuclear work | T26: GORDIAN. (2024). "RSMeans data. & Delene, J. G. and I. Hudson, C. R. (1993). Cost estimate guidelines for advanced nuclear power technologies. United States, Oak Ridge National Lab. (ORNL), Oak Ridge, TN (United States): Medium: ED; Size: 159 p. | U26: https://www.rsmeans.com/ & https://www.osti.gov/biblio/10176857 | W26: Onsite Learning | X26: =0.9*$J26 -> 0 | Y26: =1.5*J26 -> 0 | Z26: Lognormal | AA26: =0.9*K26 -> 1080 | AB26: =1.3*K26 -> 1560 | AC26: Lognormal | AD26: 0.1 | AE26: 1 | AF26: 0 | AG26: Truncated Normal
A27: 213.22 | B27: =IF(ISNUMBER(A27), IF(AND(A27=INT(A27), MOD(A27, 10) = 0), 0, IF(AND(A27=INT(A27), LEN(A27)=2), 1, IF(AND(A27=INT(A27), LEN(A27)=3), 2, LEN(A27) - FIND(".", A27) + 2) ) ), "") -> 4 | C27: Control Building Basement | D27: =REPT(" ", B27*2) & C27 -> Control Building Basement | E27: standard | K27: =943.9 -> 943.9 | L27: $/m^3 | M27: Control Building Basement Volume | O27: m^3 | Q27: 2024 | R27: Lab and Mat and Equip | W27: Onsite Learning | X27: =0.9*$J27 -> 0 | Y27: =1.5*J27 -> 0 | Z27: Lognormal | AA27: =0.9*K27 -> 849.51 | AB27: =1.3*K27 -> 1227.07 | AC27: Lognormal | AD27: 0.1 | AE27: 1 | AF27: 0 | AG27: Truncated Normal
A28: 213.23 | B28: =IF(ISNUMBER(A28), IF(AND(A28=INT(A28), MOD(A28, 10) = 0), 0, IF(AND(A28=INT(A28), LEN(A28)=2), 1, IF(AND(A28=INT(A28), LEN(A28)=3), 2, LEN(A28) - FIND(".", A28) + 2) ) ), "") -> 4 | C28: Control Building Walls | D28: =REPT(" ", B28*2) & C28 -> Control Building Walls | E28: standard | K28: =721.21 -> 721.21 | L28: $/m^3 | M28: Control Building Exterior Walls Volume | O28: m^3 | Q28: 2024 | R28: Lab and Mat and Equip | W28: Onsite Learning | X28: =0.9*$J28 -> 0 | Y28: =1.5*J28 -> 0 | Z28: Lognormal | AA28: =0.9*K28 -> 649.089 | AB28: =1.3*K28 -> 937.573 | AC28: Lognormal | AD28: 0.1 | AE28: 1 | AF28: 0 | AG28: Truncated Normal
A29: 213.3 | B29: =IF(ISNUMBER(A29), IF(AND(A29=INT(A29), MOD(A29, 10) = 0), 0, IF(AND(A29=INT(A29), LEN(A29)=2), 1, IF(AND(A29=INT(A29), LEN(A29)=3), 2, LEN(A29) - FIND(".", A29) + 2) ) ), "") -> 3 | C29: Integrated Heat Exchanger Building | D29: =REPT(" ", B29*2) & C29 -> Integrated Heat Exchanger Building | F29: reactor type | G29: GCMR
A30: 213.31 | B30: =IF(ISNUMBER(A30), IF(AND(A30=INT(A30), MOD(A30, 10) = 0), 0, IF(AND(A30=INT(A30), LEN(A30)=2), 1, IF(AND(A30=INT(A30), LEN(A30)=3), 2, LEN(A30) - FIND(".", A30) + 2) ) ), "") -> 4 | C30: Integrated Heat Exchanger Building Slab Roof | D30: =REPT(" ", B30*2) & C30 -> Integrated Heat Exchanger Building Slab Roof | E30: standard | F30: reactor type | G30: GCMR | K30: =1200 -> 1200 | L30: $/m^3 | M30: Integrated Heat Exchanger Building Slab Roof Volume | O30: m^3 | Q30: 2024 | R30: Lab and Mat and Equip | S30: RSMeans software: a tool that primarily provides costs for non-nuclear work | T30: GORDIAN. (2024). "RSMeans data. & Delene, J. G. and I. Hudson, C. R. (1993). Cost estimate guidelines for advanced nuclear power technologies. United States, Oak Ridge National Lab. (ORNL), Oak Ridge, TN (United States): Medium: ED; Size: 159 p. | U30: https://www.rsmeans.com/ & https://www.osti.gov/biblio/10176857 | W30: Onsite Learning | X30: =0.9*$J30 -> 0 | Y30: =1.5*J30 -> 0 | Z30: Lognormal | AA30: =0.9*K30 -> 1080 | AB30: =1.3*K30 -> 1560 | AC30: Lognormal | AD30: 0.1 | AE30: 1 | AF30: 0 | AG30: Truncated Normal
A31: 213.32 | B31: =IF(ISNUMBER(A31), IF(AND(A31=INT(A31), MOD(A31, 10) = 0), 0, IF(AND(A31=INT(A31), LEN(A31)=2), 1, IF(AND(A31=INT(A31), LEN(A31)=3), 2, LEN(A31) - FIND(".", A31) + 2) ) ), "") -> 4 | C31: Integrated Heat Exchanger Building Basement | D31: =REPT(" ", B31*2) & C31 -> Integrated Heat Exchanger Building Basement | E31: standard | F31: reactor type | G31: GCMR | K31: =943.9 -> 943.9 | L31: $/m^3 | M31: Integrated Heat Exchanger Building Basement Volume | O31: m^3 | Q31: 2024 | R31: Lab and Mat and Equip | W31: Onsite Learning | X31: =0.9*$J31 -> 0 | Y31: =1.5*J31 -> 0 | Z31: Lognormal | AA31: =0.9*K31 -> 849.51 | AB31: =1.3*K31 -> 1227.07 | AC31: Lognormal | AD31: 0.1 | AE31: 1 | AF31: 0 | AG31: Truncated Normal
A32: 213.33 | B32: =IF(ISNUMBER(A32), IF(AND(A32=INT(A32), MOD(A32, 10) = 0), 0, IF(AND(A32=INT(A32), LEN(A32)=2), 1, IF(AND(A32=INT(A32), LEN(A32)=3), 2, LEN(A32) - FIND(".", A32) + 2) ) ), "") -> 4 | C32: Integrated Heat Exchanger Building Walls | D32: =REPT(" ", B32*2) & C32 -> Integrated Heat Exchanger Building Walls | E32: standard | F32: reactor type | G32: GCMR | K32: =721.21 -> 721.21 | L32: $/m^3 | M32: Integrated Heat Exchanger Building Exterior Walls Volume | O32: m^3 | Q32: 2024 | R32: Lab and Mat and Equip | W32: Onsite Learning | X32: =0.9*$J32 -> 0 | Y32: =1.5*J32 -> 0 | Z32: Lognormal | AA32: =0.9*K32 -> 649.089 | AB32: =1.3*K32 -> 937.573 | AC32: Lognormal | AD32: 0.1 | AE32: 1 | AF32: 0 | AG32: Truncated Normal
A33: 213.34 | B33: =IF(ISNUMBER(A33), IF(AND(A33=INT(A33), MOD(A33, 10) = 0), 0, IF(AND(A33=INT(A33), LEN(A33)=2), 1, IF(AND(A33=INT(A33), LEN(A33)=3), 2, LEN(A33) - FIND(".", A33) + 2) ) ), "") -> 4 | C33: Integrated Heat Exchanger Building Liner | D33: =REPT(" ", B33*2) & C33 -> Integrated Heat Exchanger Building Liner | E33: standard | F33: reactor type | G33: GCMR | K33: =60848829/9373 -> 6491.9267 | L33: $/m^2 | M33: Integrated Heat Exchanger Building Superstructure Area | N33: 9373 | O33: m^2 | P33: 1 | Q33: 2018 | R33: Lab and Mat and Equip | S33: Stewart W.R., Shirvan K., "Capital cost estimation for advanced nuclear power plants," Renewable and Sustainable Energy Reviews, Nov. 2021, 111880 | T33: Stewart W.R., Shirvan K., "Capital cost estimation for advanced nuclear power plants," Renewable and Sustainable Energy Reviews, Nov. 2021, 111880 | U33: https://doi.org/10.1016/j.rser.2021.111880 | W33: Onsite Learning | X33: =0.9*$J33 -> 0 | Y33: =1.5*J33 -> 0 | Z33: Lognormal | AA33: =0.9*K33 -> 5842.734 | AB33: =1.3*K33 -> 8439.5047 | AC33: Lognormal | AD33: 0.1 | AE33: 1 | AF33: 0 | AG33: Truncated Normal
A34: 214 | B34: =IF(ISNUMBER(A34), IF(AND(A34=INT(A34), MOD(A34, 10) = 0), 0, IF(AND(A34=INT(A34), LEN(A34)=2), 1, IF(AND(A34=INT(A34), LEN(A34)=3), 2, LEN(A34) - FIND(".", A34) + 2) ) ), "") -> 2 | C34: Buildings to Support Main Function | D34: =REPT(" ", B34*2) & C34 -> Buildings to Support Main Function
A35: 214.1 | B35: =IF(ISNUMBER(A35), IF(AND(A35=INT(A35), MOD(A35, 10) = 0), 0, IF(AND(A35=INT(A35), LEN(A35)=2), 1, IF(AND(A35=INT(A35), LEN(A35)=3), 2, LEN(A35) - FIND(".", A35) + 2) ) ), "") -> 3 | C35: Fuel Management Buildings | D35: =REPT(" ", B35*2) & C35 -> Fuel Management Buildings
A36: 214.11 | B36: =IF(ISNUMBER(A36), IF(AND(A36=INT(A36), MOD(A36, 10) = 0), 0, IF(AND(A36=INT(A36), LEN(A36)=2), 1, IF(AND(A36=INT(A36), LEN(A36)=3), 2, LEN(A36) - FIND(".", A36) + 2) ) ), "") -> 4 | C36: Refueling Building | D36: =REPT(" ", B36*2) & C36 -> Refueling Building
A37: 214.111 | B37: =IF(ISNUMBER(A37), IF(AND(A37=INT(A37), MOD(A37, 10) = 0), 0, IF(AND(A37=INT(A37), LEN(A37)=2), 1, IF(AND(A37=INT(A37), LEN(A37)=3), 2, LEN(A37) - FIND(".", A37) + 2) ) ), "") -> 5 | C37: Refueling Building Slab Roof | D37: =REPT(" ", B37*2) & C37 -> Refueling Building Slab Roof | E37: standard | K37: =1200 *1.53 -> 1836 | L37: $/m^3 | M37: Refueling Building Slab Roof Volume | O37: m^3 | Q37: 2024 | R37: Lab and Mat and Equip | S37: RSMeans software: a tool that primarily provides costs for non-nuclear work Nuclear Multiplier have been applied to adjust the costs for nuclear-site-related work | T37: GORDIAN. (2024). "RSMeans data. & Delene, J. G. and I. Hudson, C. R. (1993). Cost estimate guidelines for advanced nuclear power technologies. United States, Oak Ridge National Lab. (ORNL), Oak Ridge, TN (United States): Medium: ED; Size: 159 p. | U37: https://www.rsmeans.com/ & https://www.osti.gov/biblio/10176857 | W37: Onsite Learning | X37: =0.9*$J37 -> 0 | Y37: =1.5*J37 -> 0 | AA37: =0.9*K37 -> 1652.4 | AB37: =1.3*K37 -> 2386.8 | AC37: Lognormal | AD37: 0.1 | AE37: 1 | AF37: 0 | AG37: Truncated Normal
A38: 214.112 | B38: =IF(ISNUMBER(A38), IF(AND(A38=INT(A38), MOD(A38, 10) = 0), 0, IF(AND(A38=INT(A38), LEN(A38)=2), 1, IF(AND(A38=INT(A38), LEN(A38)=3), 2, LEN(A38) - FIND(".", A38) + 2) ) ), "") -> 5 | C38: Refueling Building Basement | D38: =REPT(" ", B38*2) & C38 -> Refueling Building Basement | E38: standard | K38: =943.9*1.53 -> 1444.167 | L38: $/m^3 | M38: Refueling Building Basement Volume | O38: m^3 | Q38: 2024 | R38: Lab and Mat and Equip | W38: Onsite Learning | X38: =0.9*$J38 -> 0 | Y38: =1.5*J38 -> 0 | Z38: Lognormal | AA38: =0.9*K38 -> 1299.7503 | AB38: =1.3*K38 -> 1877.4171 | AC38: Lognormal | AD38: 0.1 | AE38: 1 | AF38: 0 | AG38: Truncated Normal
A39: 214.113 | B39: =IF(ISNUMBER(A39), IF(AND(A39=INT(A39), MOD(A39, 10) = 0), 0, IF(AND(A39=INT(A39), LEN(A39)=2), 1, IF(AND(A39=INT(A39), LEN(A39)=3), 2, LEN(A39) - FIND(".", A39) + 2) ) ), "") -> 5 | C39: Refueling Building Walls | D39: =REPT(" ", B39*2) & C39 -> Refueling Building Walls | E39: standard | K39: =721.21*1.53 -> 1103.4513 | L39: $/m^3 | M39: Refueling Building Exterior Walls Volume | O39: m^3 | Q39: 2024 | R39: Lab and Mat and Equip | W39: Onsite Learning | X39: =0.9*$J39 -> 0 | Y39: =1.5*J39 -> 0 | Z39: Lognormal | AA39: =0.9*K39 -> 993.10617 | AB39: =1.3*K39 -> 1434.4867 | AC39: Lognormal | AD39: 0.1 | AE39: 1 | AF39: 0 | AG39: Truncated Normal
A40: 214.12 | B40: =IF(ISNUMBER(A40), IF(AND(A40=INT(A40), MOD(A40, 10) = 0), 0, IF(AND(A40=INT(A40), LEN(A40)=2), 1, IF(AND(A40=INT(A40), LEN(A40)=3), 2, LEN(A40) - FIND(".", A40) + 2) ) ), "") -> 4 | C40: Spent Fuel Building | D40: =REPT(" ", B40*2) & C40 -> Spent Fuel Building
A41: 214.121 | B41: =IF(ISNUMBER(A41), IF(AND(A41=INT(A41), MOD(A41, 10) = 0), 0, IF(AND(A41=INT(A41), LEN(A41)=2), 1, IF(AND(A41=INT(A41), LEN(A41)=3), 2, LEN(A41) - FIND(".", A41) + 2) ) ), "") -> 5 | C41: Spent Fuel Building Slab Roof | D41: =REPT(" ", B41*2) & C41 -> Spent Fuel Building Slab Roof | E41: standard | K41: =1200 *1.53 -> 1836 | L41: $/m^3 | M41: Spent Fuel Building Slab Roof Volume | O41: m^3 | Q41: 2024 | R41: Lab and Mat and Equip | S41: RSMeans software: a tool that primarily provides costs for non-nuclear work Nuclear Multiplier have been applied to adjust the costs for nuclear-site-related work | T41: GORDIAN. (2024). "RSMeans data. & Delene, J. G. and I. Hudson, C. R. (1993). Cost estimate guidelines for advanced nuclear power technologies. United States, Oak Ridge National Lab. (ORNL), Oak Ridge, TN (United States): Medium: ED; Size: 159 p. | U41: https://www.rsmeans.com/ & https://www.osti.gov/biblio/10176857 | W41: Onsite Learning | X41: =0.9*$J41 -> 0 | Y41: =1.5*J41 -> 0 | Z41: Lognormal | AA41: =0.9*K41 -> 1652.4 | AB41: =1.3*K41 -> 2386.8 | AC41: Lognormal | AD41: 0.1 | AE41: 1 | AF41: 0 | AG41: Truncated Normal
A42: 214.122 | B42: =IF(ISNUMBER(A42), IF(AND(A42=INT(A42), MOD(A42, 10) = 0), 0, IF(AND(A42=INT(A42), LEN(A42)=2), 1, IF(AND(A42=INT(A42), LEN(A42)=3), 2, LEN(A42) - FIND(".", A42) + 2) ) ), "") -> 5 | C42: Spent Fuel Building Basement | D42: =REPT(" ", B42*2) & C42 -> Spent Fuel Building Basement | E42: standard | K42: =943.9*1.53 -> 1444.167 | L42: $/m^3 | M42: Spent Fuel Building Basement Volume | O42: m^3 | Q42: 2024 | R42: Lab and Mat and Equip | W42: Onsite Learning | X42: =0.9*$J42 -> 0 | Y42: =1.5*J42 -> 0 | Z42: Lognormal | AA42: =0.9*K42 -> 1299.7503 | AB42: =1.3*K42 -> 1877.4171 | AC42: Lognormal | AD42: 0.1 | AE42: 1 | AF42: 0 | AG42: Truncated Normal
A43: 214.123 | B43: =IF(ISNUMBER(A43), IF(AND(A43=INT(A43), MOD(A43, 10) = 0), 0, IF(AND(A43=INT(A43), LEN(A43)=2), 1, IF(AND(A43=INT(A43), LEN(A43)=3), 2, LEN(A43) - FIND(".", A43) + 2) ) ), "") -> 5 | C43: Spent Fuel Building Walls | D43: =REPT(" ", B43*2) & C43 -> Spent Fuel Building Walls | E43: standard | K43: =721.21*1.53 -> 1103.4513 | L43: $/m^3 | M43: Spent Fuel Building Exterior Walls Volume | O43: m^3 | Q43: 2024 | R43: Lab and Mat and Equip | W43: Onsite Learning | X43: =0.9*$J43 -> 0 | Y43: =1.5*J43 -> 0 | Z43: Lognormal | AA43: =0.9*K43 -> 993.10617 | AB43: =1.3*K43 -> 1434.4867 | AC43: Lognormal | AD43: 0.1 | AE43: 1 | AF43: 0 | AG43: Truncated Normal
A44: 214.7 | B44: =IF(ISNUMBER(A44), IF(AND(A44=INT(A44), MOD(A44, 10) = 0), 0, IF(AND(A44=INT(A44), LEN(A44)=2), 1, IF(AND(A44=INT(A44), LEN(A44)=3), 2, LEN(A44) - FIND(".", A44) + 2) ) ), "") -> 3 | C44: Emergency and Start-up Power Systems Building | D44: =REPT(" ", B44*2) & C44 -> Emergency and Start-up Power Systems Building
A45: 214.71 | B45: =IF(ISNUMBER(A45), IF(AND(A45=INT(A45), MOD(A45, 10) = 0), 0, IF(AND(A45=INT(A45), LEN(A45)=2), 1, IF(AND(A45=INT(A45), LEN(A45)=3), 2, LEN(A45) - FIND(".", A45) + 2) ) ), "") -> 4 | C45: Emergency Building | D45: =REPT(" ", B45*2) & C45 -> Emergency Building
A46: 214.711 | B46: =IF(ISNUMBER(A46), IF(AND(A46=INT(A46), MOD(A46, 10) = 0), 0, IF(AND(A46=INT(A46), LEN(A46)=2), 1, IF(AND(A46=INT(A46), LEN(A46)=3), 2, LEN(A46) - FIND(".", A46) + 2) ) ), "") -> 5 | C46: Emergency Building Slab Roof | D46: =REPT(" ", B46*2) & C46 -> Emergency Building Slab Roof | E46: standard | K46: =1200 -> 1200 | L46: $/m^3 | M46: Emergency Building Slab Roof Volume | O46: m^3 | Q46: 2024 | R46: Lab and Mat and Equip | S46: RSMeans software: a tool that primarily provides costs for non-nuclear work | T46: GORDIAN. (2024). "RSMeans data. & Delene, J. G. and I. Hudson, C. R. (1993). Cost estimate guidelines for advanced nuclear power technologies. United States, Oak Ridge National Lab. (ORNL), Oak Ridge, TN (United States): Medium: ED; Size: 159 p. | U46: https://www.rsmeans.com/ & https://www.osti.gov/biblio/10176857 | W46: Onsite Learning | X46: =0.9*$J46 -> 0 | Y46: =1.5*J46 -> 0 | Z46: Lognormal | AA46: =0.9*K46 -> 1080 | AB46: =1.3*K46 -> 1560 | AC46: Lognormal | AD46: 0.1 | AE46: 1 | AF46: 0 | AG46: Truncated Normal
A47: 214.712 | B47: =IF(ISNUMBER(A47), IF(AND(A47=INT(A47), MOD(A47, 10) = 0), 0, IF(AND(A47=INT(A47), LEN(A47)=2), 1, IF(AND(A47=INT(A47), LEN(A47)=3), 2, LEN(A47) - FIND(".", A47) + 2) ) ), "") -> 5 | C47: Emergency Building Basement | D47: =REPT(" ", B47*2) & C47 -> Emergency Building Basement | E47: standard | K47: =943.9 -> 943.9 | L47: $/m^3 | M47: Emergency Building Basement Volume | O47: m^3 | Q47: 2024 | R47: Lab and Mat and Equip | W47: Onsite Learning | X47: =0.9*$J47 -> 0 | Y47: =1.5*J47 -> 0 | Z47: Lognormal | AA47: =0.9*K47 -> 849.51 | AB47: =1.3*K47 -> 1227.07 | AC47: Lognormal | AD47: 0.1 | AE47: 1 | AF47: 0 | AG47: Truncated Normal
A48: 214.713 | B48: =IF(ISNUMBER(A48), IF(AND(A48=INT(A48), MOD(A48, 10) = 0), 0, IF(AND(A48=INT(A48), LEN(A48)=2), 1, IF(AND(A48=INT(A48), LEN(A48)=3), 2, LEN(A48) - FIND(".", A48) + 2) ) ), "") -> 5 | C48: Emergency Building Walls | D48: =REPT(" ", B48*2) & C48 -> Emergency Building Walls | E48: standard | K48: =721.21 -> 721.21 | L48: $/m^3 | M48: Emergency Building Exterior Walls Volume | O48: m^3 | Q48: 2024 | R48: Lab and Mat and Equip | W48: Onsite Learning | X48: =0.9*$J48 -> 0 | Y48: =1.5*J48 -> 0 | Z48: Lognormal | AA48: =0.9*K48 -> 649.089 | AB48: =1.3*K48 -> 937.573 | AC48: Lognormal | AD48: 0.1 | AE48: 1 | AF48: 0 | AG48: Truncated Normal
A49: 214.72 | B49: =IF(ISNUMBER(A49), IF(AND(A49=INT(A49), MOD(A49, 10) = 0), 0, IF(AND(A49=INT(A49), LEN(A49)=2), 1, IF(AND(A49=INT(A49), LEN(A49)=3), 2, LEN(A49) - FIND(".", A49) + 2) ) ), "") -> 4 | C49: Diesel Generator | D49: =REPT(" ", B49*2) & C49 -> Diesel Generator | E49: standard | K49: =MARVEL_Cost!C11/N49 -> 2717311.6 | L49: $/MWt | M49: Power MWt | N49: ='Design Variables'!B3/1000 -> 0.083 | O49: MWt | P49: 0.7 | Q49: 2024 | R49: Equipment | S49: MARVEL (for the cost of the diesel generator) The exponent is based on the work by Koruoush considering cost scaling from nuclear ad non nuclear power plants. When using the power as scaling variable, the exponent ranges between 0..6 and 0.8 so 0.7 is used here | T49: Hanna, B. N., Gonzaga de Oliveira, R. G., Mohammad Al Dawood, K. A., Patterson, M. D., Abou Jaoude, A., & Garcia, S. (2024). Technoeconomic Evaluation of Microreactor Using Detailed Bottom-up Estimate (No. INL/RPT-24-80433-Rev000). Idaho National Laboratory (INL), Idaho Falls, ID (United States). Stewart, W. R., & Shirvan, K. (2022). Capital cost estimation for advanced nuclear power plants. Renewable and Sustainable Energy Reviews, 155, 111880. | U49: https://inldigitallibrary.inl.gov/sites/sti/sti/Sort_129862.pdf https://www.sciencedirect.com/science/article/pii/S1364032121011473 | W49: Factory Other | X49: =0.9*$J49 -> 0 | Y49: =1.5*J49 -> 0 | Z49: Lognormal | AA49: =0.9*K49 -> 2445580.4 | AB49: =1.3*K49 -> 3532505 | AC49: Lognormal | AD49: 0.1 | AE49: 1 | AF49: 0 | AG49: Truncated Normal
A50: 214.8 | B50: =IF(ISNUMBER(A50), IF(AND(A50=INT(A50), MOD(A50, 10) = 0), 0, IF(AND(A50=INT(A50), LEN(A50)=2), 1, IF(AND(A50=INT(A50), LEN(A50)=3), 2, LEN(A50) - FIND(".", A50) + 2) ) ), "") -> 3 | C50: Auxilliary Building | D50: =REPT(" ", B50*2) & C50 -> Auxilliary Building
A51: 214.81 | B51: =IF(ISNUMBER(A51), IF(AND(A51=INT(A51), MOD(A51, 10) = 0), 0, IF(AND(A51=INT(A51), LEN(A51)=2), 1, IF(AND(A51=INT(A51), LEN(A51)=3), 2, LEN(A51) - FIND(".", A51) + 2) ) ), "") -> 4 | C51: Maniplator Building | D51: =REPT(" ", B51*2) & C51 -> Maniplator Building
A52: 214.811 | B52: =IF(ISNUMBER(A52), IF(AND(A52=INT(A52), MOD(A52, 10) = 0), 0, IF(AND(A52=INT(A52), LEN(A52)=2), 1, IF(AND(A52=INT(A52), LEN(A52)=3), 2, LEN(A52) - FIND(".", A52) + 2) ) ), "") -> 5 | C52: Manipulator Building Slab Roof | D52: =REPT(" ", B52*2) & C52 -> Manipulator Building Slab Roof | E52: standard | K52: =1200 -> 1200 | L52: $/m^3 | M52: Manipulator Building Slab Roof Volume | O52: m^3 | Q52: 2024 | R52: Lab and Mat and Equip | S52: RSMeans software: a tool that primarily provides costs for non-nuclear work | T52: GORDIAN. (2024). "RSMeans data. & Delene, J. G. and I. Hudson, C. R. (1993). Cost estimate guidelines for advanced nuclear power technologies. United States, Oak Ridge National Lab. (ORNL), Oak Ridge, TN (United States): Medium: ED; Size: 159 p. | U52: https://www.rsmeans.com/ & https://www.osti.gov/biblio/10176857 | V52: Added a custom building for GCMR based on CAD drawing | W52: Onsite Learning | X52: =0.9*$J52 -> 0 | Y52: =1.5*J52 -> 0 | Z52: Lognormal | AA52: =0.9*K52 -> 1080 | AB52: =1.3*K52 -> 1560 | AC52: Lognormal | AD52: 0.1 | AE52: 1 | AF52: 0 | AG52: Truncated Normal
A53: 214.812 | B53: =IF(ISNUMBER(A53), IF(AND(A53=INT(A53), MOD(A53, 10) = 0), 0, IF(AND(A53=INT(A53), LEN(A53)=2), 1, IF(AND(A53=INT(A53), LEN(A53)=3), 2, LEN(A53) - FIND(".", A53) + 2) ) ), "") -> 5 | C53: ManipulatorBuilding Basement | D53: =REPT(" ", B53*2) & C53 -> ManipulatorBuilding Basement | E53: standard | K53: =943.9 -> 943.9 | L53: $/m^3 | M53: Manipulator Building Basement Volume | O53: m^3 | Q53: 2024 | R53: Lab and Mat and Equip | W53: Onsite Learning | X53: =0.9*$J53 -> 0 | Y53: =1.5*J53 -> 0 | Z53: Lognormal | AA53: =0.9*K53 -> 849.51 | AB53: =1.3*K53 -> 1227.07 | AC53: Lognormal | AD53: 0.1 | AE53: 1 | AF53: 0 | AG53: Truncated Normal
A54: 214.813 | B54: =IF(ISNUMBER(A54), IF(AND(A54=INT(A54), MOD(A54, 10) = 0), 0, IF(AND(A54=INT(A54), LEN(A54)=2), 1, IF(AND(A54=INT(A54), LEN(A54)=3), 2, LEN(A54) - FIND(".", A54) + 2) ) ), "") -> 5 | C54: Manipulator Building Exterior Walls | D54: =REPT(" ", B54*2) & C54 -> Manipulator Building Exterior Walls | E54: standard | K54: =721.21 -> 721.21 | L54: $/m^3 | M54: Manipulator Building Exterior Walls Volume | O54: m^3 | Q54: 2024 | R54: Lab and Mat and Equip | W54: Onsite Learning | X54: =0.9*$J54 -> 0 | Y54: =1.5*J54 -> 0 | Z54: Lognormal | AA54: =0.9*K54 -> 649.089 | AB54: =1.3*K54 -> 937.573 | AC54: Lognormal | AD54: 0.1 | AE54: 1 | AF54: 0 | AG54: Truncated Normal
A55: 215 | B55: =IF(ISNUMBER(A55), IF(AND(A55=INT(A55), MOD(A55, 10) = 0), 0, IF(AND(A55=INT(A55), LEN(A55)=2), 1, IF(AND(A55=INT(A55), LEN(A55)=3), 2, LEN(A55) - FIND(".", A55) + 2) ) ), "") -> 2 | C55: Supply Chain Buildings | D55: =REPT(" ", B55*2) & C55 -> Supply Chain Buildings
A56: 215.1 | B56: =IF(ISNUMBER(A56), IF(AND(A56=INT(A56), MOD(A56, 10) = 0), 0, IF(AND(A56=INT(A56), LEN(A56)=2), 1, IF(AND(A56=INT(A56), LEN(A56)=3), 2, LEN(A56) - FIND(".", A56) + 2) ) ), "") -> 3 | C56: Storage Building | D56: =REPT(" ", B56*2) & C56 -> Storage Building
A57: 215.11 | B57: =IF(ISNUMBER(A57), IF(AND(A57=INT(A57), MOD(A57, 10) = 0), 0, IF(AND(A57=INT(A57), LEN(A57)=2), 1, IF(AND(A57=INT(A57), LEN(A57)=3), 2, LEN(A57) - FIND(".", A57) + 2) ) ), "") -> 4 | C57: Storage Building Slab Roof | D57: =REPT(" ", B57*2) & C57 -> Storage Building Slab Roof | E57: standard | K57: =1200 -> 1200 | L57: $/m^3 | M57: Storage Building Slab Roof Volume | O57: m^3 | Q57: 2024 | R57: Lab and Mat and Equip | S57: RSMeans software: a tool that primarily provides costs for non-nuclear work | T57: GORDIAN. (2024). "RSMeans data. & Delene, J. G. and I. Hudson, C. R. (1993). Cost estimate guidelines for advanced nuclear power technologies. United States, Oak Ridge National Lab. (ORNL), Oak Ridge, TN (United States): Medium: ED; Size: 159 p. | U57: https://www.rsmeans.com/ & https://www.osti.gov/biblio/10176857 | W57: Onsite Learning | X57: =0.9*$J57 -> 0 | Y57: =1.5*J57 -> 0 | Z57: Lognormal | AA57: =0.9*K57 -> 1080 | AB57: =1.3*K57 -> 1560 | AC57: Lognormal | AD57: 0.1 | AE57: 1 | AF57: 0 | AG57: Truncated Normal
A58: 215.12 | B58: =IF(ISNUMBER(A58), IF(AND(A58=INT(A58), MOD(A58, 10) = 0), 0, IF(AND(A58=INT(A58), LEN(A58)=2), 1, IF(AND(A58=INT(A58), LEN(A58)=3), 2, LEN(A58) - FIND(".", A58) + 2) ) ), "") -> 4 | C58: Storage Building Basement | D58: =REPT(" ", B58*2) & C58 -> Storage Building Basement | E58: standard | K58: =943.9 -> 943.9 | L58: $/m^3 | M58: Storage Building Basement Volume | O58: m^3 | Q58: 2024 | R58: Lab and Mat and Equip | W58: Onsite Learning | X58: =0.9*$J58 -> 0 | Y58: =1.5*J58 -> 0 | Z58: Lognormal | AA58: =0.9*K58 -> 849.51 | AB58: =1.3*K58 -> 1227.07 | AC58: Lognormal | AD58: 0.1 | AE58: 1 | AF58: 0 | AG58: Truncated Normal
A59: 215.13 | B59: =IF(ISNUMBER(A59), IF(AND(A59=INT(A59), MOD(A59, 10) = 0), 0, IF(AND(A59=INT(A59), LEN(A59)=2), 1, IF(AND(A59=INT(A59), LEN(A59)=3), 2, LEN(A59) - FIND(".", A59) + 2) ) ), "") -> 4 | C59: Storage Building Walls | D59: =REPT(" ", B59*2) & C59 -> Storage Building Walls | E59: standard | K59: =721.21 -> 721.21 | L59: $/m^3 | M59: Storage Building Exterior Walls Volume | O59: m^3 | Q59: 2024 | R59: Lab and Mat and Equip | W59: Onsite Learning | X59: =0.9*$J59 -> 0 | Y59: =1.5*J59 -> 0 | Z59: Lognormal | AA59: =0.9*K59 -> 649.089 | AB59: =1.3*K59 -> 937.573 | AC59: Lognormal | AD59: 0.1 | AE59: 1 | AF59: 0 | AG59: Truncated Normal
A60: 215.4 | B60: =IF(ISNUMBER(A60), IF(AND(A60=INT(A60), MOD(A60, 10) = 0), 0, IF(AND(A60=INT(A60), LEN(A60)=2), 1, IF(AND(A60=INT(A60), LEN(A60)=3), 2, LEN(A60) - FIND(".", A60) + 2) ) ), "") -> 3 | C60: Radwaste Building | D60: =REPT(" ", B60*2) & C60 -> Radwaste Building
A61: 215.41 | B61: =IF(ISNUMBER(A61), IF(AND(A61=INT(A61), MOD(A61, 10) = 0), 0, IF(AND(A61=INT(A61), LEN(A61)=2), 1, IF(AND(A61=INT(A61), LEN(A61)=3), 2, LEN(A61) - FIND(".", A61) + 2) ) ), "") -> 4 | C61: Radwaste Building Slab Roof | D61: =REPT(" ", B61*2) & C61 -> Radwaste Building Slab Roof | E61: standard | K61: =1200 *1.53 -> 1836 | L61: $/m^3 | M61: Radwaste Building Slab Roof Volume | O61: m^3 | Q61: 2024 | R61: Lab and Mat and Equip | S61: RSMeans software: a tool that primarily provides costs for non-nuclear work Nuclear Multiplier have been applied to adjust the costs for nuclear-site-related work | T61: GORDIAN. (2024). "RSMeans data. & Delene, J. G. and I. Hudson, C. R. (1993). Cost estimate guidelines for advanced nuclear power technologies. United States, Oak Ridge National Lab. (ORNL), Oak Ridge, TN (United States): Medium: ED; Size: 159 p. | U61: https://www.rsmeans.com/ & https://www.osti.gov/biblio/10176857 | W61: Onsite Learning | X61: =0.9*$J61 -> 0 | Y61: =1.5*J61 -> 0 | Z61: Lognormal | AA61: =0.9*K61 -> 1652.4 | AB61: =1.3*K61 -> 2386.8 | AC61: Lognormal | AD61: 0.1 | AE61: 1 | AF61: 0 | AG61: Truncated Normal
A62: 215.42 | B62: =IF(ISNUMBER(A62), IF(AND(A62=INT(A62), MOD(A62, 10) = 0), 0, IF(AND(A62=INT(A62), LEN(A62)=2), 1, IF(AND(A62=INT(A62), LEN(A62)=3), 2, LEN(A62) - FIND(".", A62) + 2) ) ), "") -> 4 | C62: Radwaste Building Basement | D62: =REPT(" ", B62*2) & C62 -> Radwaste Building Basement | E62: standard | K62: =943.9*1.53 -> 1444.167 | L62: $/m^3 | M62: Radwaste Building Basement Volume | O62: m^3 | Q62: 2024 | R62: Lab and Mat and Equip | W62: Onsite Learning | X62: =0.9*$J62 -> 0 | Y62: =1.5*J62 -> 0 | Z62: Lognormal | AA62: =0.9*K62 -> 1299.7503 | AB62: =1.3*K62 -> 1877.4171 | AC62: Lognormal | AD62: 0.1 | AE62: 1 | AF62: 0 | AG62: Truncated Normal
A63: 215.43 | B63: =IF(ISNUMBER(A63), IF(AND(A63=INT(A63), MOD(A63, 10) = 0), 0, IF(AND(A63=INT(A63), LEN(A63)=2), 1, IF(AND(A63=INT(A63), LEN(A63)=3), 2, LEN(A63) - FIND(".", A63) + 2) ) ), "") -> 4 | C63: Radwaste Building Walls | D63: =REPT(" ", B63*2) & C63 -> Radwaste Building Walls | E63: standard | K63: =721.21*1.53 -> 1103.4513 | L63: $/m^3 | M63: Radwaste Building Exterior Walls Volume | O63: m^3 | Q63: 2024 | R63: Lab and Mat and Equip | W63: Onsite Learning | X63: =0.9*$J63 -> 0 | Y63: =1.5*J63 -> 0 | Z63: Lognormal | AA63: =0.9*K63 -> 993.10617 | AB63: =1.3*K63 -> 1434.4867 | AC63: Lognormal | AD63: 0.1 | AE63: 1 | AF63: 0 | AG63: Truncated Normal
A64: 22 | B64: =IF(ISNUMBER(A64), IF(AND(A64=INT(A64), MOD(A64, 10) = 0), 0, IF(AND(A64=INT(A64), LEN(A64)=2), 1, IF(AND(A64=INT(A64), LEN(A64)=3), 2, LEN(A64) - FIND(".", A64) + 2) ) ), "") -> 1 | C64: Reactor System | D64: =REPT(" ", B64*2) & C64 -> Reactor System
A65: 221 | B65: =IF(ISNUMBER(A65), IF(AND(A65=INT(A65), MOD(A65, 10) = 0), 0, IF(AND(A65=INT(A65), LEN(A65)=2), 1, IF(AND(A65=INT(A65), LEN(A65)=3), 2, LEN(A65) - FIND(".", A65) + 2) ) ), "") -> 2 | C65: Reactor Components | D65: =REPT(" ", B65*2) & C65 -> Reactor Components
A66: 221.1 | B66: =IF(ISNUMBER(A66), IF(AND(A66=INT(A66), MOD(A66, 10) = 0), 0, IF(AND(A66=INT(A66), LEN(A66)=2), 1, IF(AND(A66=INT(A66), LEN(A66)=3), 2, LEN(A66) - FIND(".", A66) + 2) ) ), "") -> 3 | C66: Reactor Vessel and Accessories | D66: =REPT(" ", B66*2) & C66 -> Reactor Vessel and Accessories
A67: 221.11 | B67: =IF(ISNUMBER(A67), IF(AND(A67=INT(A67), MOD(A67, 10) = 0), 0, IF(AND(A67=INT(A67), LEN(A67)=2), 1, IF(AND(A67=INT(A67), LEN(A67)=3), 2, LEN(A67) - FIND(".", A67) + 2) ) ), "") -> 4 | C67: Reactor Support | D67: =REPT(" ", B67*2) & C67 -> Reactor Support | E67: standard | K67: =MARVEL_Cost!C16/N67 -> 311.55799 | L67: $/Kg | M67: Total Vessels Mass | N67: =1000*('Design Variables'!B52+'Design Variables'!B49) -> 2447 | O67: Kg | P67: 0.85 | Q67: 2018 | R67: Lab and Mat and Equip | S67: PWR12-ME | V67: Unit cost is the cost of support structure divided by the cost of guard vessel plus PCS | W67: Factory Primary Structure | X67: =0.9*$J67 -> 0 | Y67: =1.5*J67 -> 0 | Z67: Lognormal | AA67: =0.9*K67 -> 280.40219 | AB67: =1.3*K67 -> 405.02539 | AC67: Lognormal | AD67: 0.1 | AE67: 1 | AF67: 0 | AG67: Truncated Normal
A68: 221.12 | B68: =IF(ISNUMBER(A68), IF(AND(A68=INT(A68), MOD(A68, 10) = 0), 0, IF(AND(A68=INT(A68), LEN(A68)=2), 1, IF(AND(A68=INT(A68), LEN(A68)=3), 2, LEN(A68) - FIND(".", A68) + 2) ) ), "") -> 4 | C68: Outer Vessel Structure | D68: =REPT(" ", B68*2) & C68 -> Outer Vessel Structure | E68: standard | F68: Guard Vessel Material | G68: stainless_steel | K68: =MARVEL_Cost!C17/N68 -> 757.20769 | L68: $/Kg | M68: Guard Vessel Mass | N68: ='Design Variables'!B52*1000 -> 1587 | O68: Kg | Q68: 2017 | R68: Lab and Mat and Equip | S68: Ganda et al., 2018 | T68: Ganda, F., Hoffman, E., Taiwo, T. A., Kim, T. K., & Hansen, J. (2019). Report on the ACCERT cost algorithms tool (No. ANL/NSE-19/10). Argonne National Lab.(ANL), Argonne, IL (United States). | W68: Factory Primary Structure | X68: =0.9*$J68 -> 0 | Y68: =1.5*J68 -> 0 | Z68: Lognormal | AA68: =0.9*K68 -> 681.48692 | AB68: =1.3*K68 -> 984.36999 | AC68: Lognormal | AD68: 0.1 | AE68: 1 | AF68: 0 | AG68: Truncated Normal
A69: 221.12 | B69: =IF(ISNUMBER(A69), IF(AND(A69=INT(A69), MOD(A69, 10) = 0), 0, IF(AND(A69=INT(A69), LEN(A69)=2), 1, IF(AND(A69=INT(A69), LEN(A69)=3), 2, LEN(A69) - FIND(".", A69) + 2) ) ), "") -> 4 | C69: Outer Vessel Structure | D69: =REPT(" ", B69*2) & C69 -> Outer Vessel Structure | E69: standard | F69: Guard Vessel Material | G69: low_alloy_steel | K69: 154.08 | L69: $/Kg | M69: Guard Vessel Mass | Q69: 2017 | R69: Lab and Mat and Equip | S69: Ganda et al., 2018 | W69: Factory Primary Structure | X69: =0.9*$J69 -> 0 | Y69: =1.5*J69 -> 0 | Z69: Lognormal | AA69: =0.9*K69 -> 138.672 | AB69: =1.3*K69 -> 200.304 | AC69: Lognormal | AD69: 0.1 | AE69: 1 | AF69: 0 | AG69: Truncated Normal
A70: 221.12 | B70: =IF(ISNUMBER(A70), IF(AND(A70=INT(A70), MOD(A70, 10) = 0), 0, IF(AND(A70=INT(A70), LEN(A70)=2), 1, IF(AND(A70=INT(A70), LEN(A70)=3), 2, LEN(A70) - FIND(".", A70) + 2) ) ), "") -> 4 | C70: Outer Vessel Structure | D70: =REPT(" ", B70*2) & C70 -> Outer Vessel Structure | E70: standard | F70: Guard Vessel Material | G70: incoloy | K70: 444.08 | L70: $/Kg | M70: Guard Vessel Mass | Q70: 2017 | R70: Lab and Mat and Equip | S70: Ganda et al., 2018 | W70: Factory Primary Structure | X70: =0.9*$J70 -> 0 | Y70: =1.5*J70 -> 0 | Z70: Lognormal | AA70: =0.9*K70 -> 399.672 | AB70: =1.3*K70 -> 577.304 | AC70: Lognormal | AD70: 0.1 | AE70: 1 | AF70: 0 | AG70: Truncated Normal
A71: 221.13 | B71: =IF(ISNUMBER(A71), IF(AND(A71=INT(A71), MOD(A71, 10) = 0), 0, IF(AND(A71=INT(A71), LEN(A71)=2), 1, IF(AND(A71=INT(A71), LEN(A71)=3), 2, LEN(A71) - FIND(".", A71) + 2) ) ), "") -> 4 | C71: Inner Vessel Structure | D71: =REPT(" ", B71*2) & C71 -> Inner Vessel Structure | E71: standard | F71: Vessel Material | G71: stainless_steel | J71: =MARVEL_Cost!C37+MARVEL_Cost!C36 -> 3369444.6 | K71: =(MARVEL_Cost!C35)/N71 -> 1768.3558 | L71: $/Kg | M71: Vessel Mass | N71: =1000*'Design Variables'!B49 -> 860 | Q71: 2017 | R71: Lab and Mat and Equip | S71: Ganda et al., 2018 | V71: Unit cost if the PCS cost (in MARVEL) divided by the PCS mass in MARVEL | W71: Factory Primary Structure | X71: =0.9*$J71 -> 3032500.1 | Y71: =1.5*J71 -> 5054166.9 | Z71: Lognormal | AA71: =0.9*K71 -> 1591.5202 | AB71: =1.3*K71 -> 2298.8626 | AC71: Lognormal | AD71: 0.1 | AE71: 1 | AF71: 0 | AG71: Truncated Normal
A72: 221.13 | B72: =IF(ISNUMBER(A72), IF(AND(A72=INT(A72), MOD(A72, 10) = 0), 0, IF(AND(A72=INT(A72), LEN(A72)=2), 1, IF(AND(A72=INT(A72), LEN(A72)=3), 2, LEN(A72) - FIND(".", A72) + 2) ) ), "") -> 4 | C72: Inner Vessel Structure | D72: =REPT(" ", B72*2) & C72 -> Inner Vessel Structure | E72: standard | F72: Vessel Material | G72: low_alloy_steel | K72: 154.08 | L72: $/Kg | M72: Vessel Mass | Q72: 2017 | R72: Lab and Mat and Equip | S72: Ganda et al., 2018 | W72: Factory Primary Structure | X72: =0.9*$J72 -> 0 | Y72: =1.5*J72 -> 0 | Z72: Lognormal | AA72: =0.9*K72 -> 138.672 | AB72: =1.3*K72 -> 200.304 | AC72: Lognormal | AD72: 0.1 | AE72: 1 | AF72: 0 | AG72: Truncated Normal
A73: 221.13 | B73: =IF(ISNUMBER(A73), IF(AND(A73=INT(A73), MOD(A73, 10) = 0), 0, IF(AND(A73=INT(A73), LEN(A73)=2), 1, IF(AND(A73=INT(A73), LEN(A73)=3), 2, LEN(A73) - FIND(".", A73) + 2) ) ), "") -> 4 | C73: Inner Vessel Structure | D73: =REPT(" ", B73*2) & C73 -> Inner Vessel Structure | E73: standard | F73: Vessel Material | G73: incoloy | K73: 444.08 | L73: $/Kg | M73: Vessel Mass | Q73: 2017 | R73: Lab and Mat and Equip | S73: Ganda et al., 2018 | W73: Factory Primary Structure | X73: =0.9*$J73 -> 0 | Y73: =1.5*J73 -> 0 | Z73: Lognormal | AA73: =0.9*K73 -> 399.672 | AB73: =1.3*K73 -> 577.304 | AC73: Lognormal | AD73: 0.1 | AE73: 1 | AF73: 0 | AG73: Truncated Normal
A74: 221.2 | B74: =IF(ISNUMBER(A74), IF(AND(A74=INT(A74), MOD(A74, 10) = 0), 0, IF(AND(A74=INT(A74), LEN(A74)=2), 1, IF(AND(A74=INT(A74), LEN(A74)=3), 2, LEN(A74) - FIND(".", A74) + 2) ) ), "") -> 3 | C74: Reactor Control Devices | D74: =REPT(" ", B74*2) & C74 -> Reactor Control Devices
A75: 221.21 | B75: =IF(ISNUMBER(A75), IF(AND(A75=INT(A75), MOD(A75, 10) = 0), 0, IF(AND(A75=INT(A75), LEN(A75)=2), 1, IF(AND(A75=INT(A75), LEN(A75)=3), 2, LEN(A75) - FIND(".", A75) + 2) ) ), "") -> 4 | C75: Reactivity Control System | D75: =REPT(" ", B75*2) & C75 -> Reactivity Control System
A76: 221.211 | B76: =IF(ISNUMBER(A76), IF(AND(A76=INT(A76), MOD(A76, 10) = 0), 0, IF(AND(A76=INT(A76), LEN(A76)=2), 1, IF(AND(A76=INT(A76), LEN(A76)=3), 2, LEN(A76) - FIND(".", A76) + 2) ) ), "") -> 5 | C76: Reactivity Control System Fabrication | D76: =REPT(" ", B76*2) & C76 -> Reactivity Control System Fabrication | E76: standard | K76: =MARVEL_Cost!C21/'Design Variables'!B21 -> 347890 | L76: $/Drum | M76: Drum Count | Q76: 2024 | R76: Lab and Mat and Equip | S76: MARVEL Project | T76: Updated MARVEL Cost Estimate + Communication with MARVEL Team | U76: Gerstner, D., & Arafat, Y. (2023). MARVEL 90% Final Design Report (No. INL/RPT-23-74280-Rev000). Idaho National Laboratory (INL), Idaho Falls, ID (United States). Hanna, B. N., Gonzaga de Oliveira, R. G., Mohammad Al Dawood, K. A., Patterson, M. D., Abou Jaoude, A., & Garcia, S. (2024). Technoeconomic Evaluation of Microreactor Using Detailed Bottom-up Estimate (No. INL/RPT-24-80433-Rev000). Idaho National Laboratory (INL), Idaho Falls, ID (United States). | V76: The scaling variable here is the total mass of all the control drums | W76: Factory Drums | X76: =0.9*$J76 -> 0 | Y76: =1.5*J76 -> 0 | Z76: Lognormal | AA76: =0.9*K76 -> 313101 | AB76: =1.3*K76 -> 452257 | AC76: Lognormal | AD76: 0.1 | AE76: 1 | AF76: 0 | AG76: Truncated Normal
A77: 221.212 | B77: =IF(ISNUMBER(A77), IF(AND(A77=INT(A77), MOD(A77, 10) = 0), 0, IF(AND(A77=INT(A77), LEN(A77)=2), 1, IF(AND(A77=INT(A77), LEN(A77)=3), 2, LEN(A77) - FIND(".", A77) + 2) ) ), "") -> 5 | C77: Installation | D77: =REPT(" ", B77*2) & C77 -> Installation | E77: standard | K77: =MARVEL_Cost!C22/'Design Variables'!B21 -> 80665.75 | L77: $/Drum | M77: Drum Count | Q77: 2024 | R77: Lab and Equip | S77: MARVEL Project | W77: Factory Drums | X77: =0.9*$J77 -> 0 | Y77: =1.5*J77 -> 0 | Z77: Lognormal | AA77: =0.9*K77 -> 72599.175 | AB77: =1.3*K77 -> 104865.48 | AC77: Lognormal | AD77: 0.1 | AE77: 1 | AF77: 0 | AG77: Truncated Normal
A78: 221.213 | B78: =IF(ISNUMBER(A78), IF(AND(A78=INT(A78), MOD(A78, 10) = 0), 0, IF(AND(A78=INT(A78), LEN(A78)=2), 1, IF(AND(A78=INT(A78), LEN(A78)=3), 2, LEN(A78) - FIND(".", A78) + 2) ) ), "") -> 5 | C78: Control Drums Materials (Absorber) | D78: =REPT(" ", B78*2) & C78 -> Control Drums Materials (Absorber) | E78: standard | F78: Control Drum Absorber | G78: B4C_natural | K78: =400000/N78 -> 14285.714 | L78: $/Kg | M78: Control Drum Absorber Mass | N78: ='Design Variables'!B28+'Design Variables'!B29 -> 28 | O78: Kg | P78: 1 | Q78: 2024 | R78: Material | S78: MARVEL Project | W78: Factory Other | X78: =0.9*$J78 -> 0 | Y78: =1.5*J78 -> 0 | Z78: Lognormal | AA78: =0.9*K78 -> 12857.143 | AB78: =1.3*K78 -> 18571.429 | AC78: Lognormal | AD78: 0.1 | AE78: 1 | AF78: 0 | AG78: Truncated Normal
A79: 221.213 | B79: =IF(ISNUMBER(A79), IF(AND(A79=INT(A79), MOD(A79, 10) = 0), 0, IF(AND(A79=INT(A79), LEN(A79)=2), 1, IF(AND(A79=INT(A79), LEN(A79)=3), 2, LEN(A79) - FIND(".", A79) + 2) ) ), "") -> 5 | C79: Control Drums Materials (Absorber) | D79: =REPT(" ", B79*2) & C79 -> Control Drums Materials (Absorber) | E79: standard | F79: Control Drum Absorber | G79: B4C_enriched | K79: 10064 | L79: $/Kg | M79: Control Drum Absorber Mass | Q79: 2023 | R79: Material | S79: Prosser et al., 2023 | W79: Factory Other | X79: =0.9*$J79 -> 0 | Y79: =1.5*J79 -> 0 | Z79: Lognormal | AA79: =0.9*K79 -> 9057.6 | AB79: =1.3*K79 -> 13083.2 | AC79: Lognormal | AD79: 0.1 | AE79: 1 | AF79: 0 | AG79: Truncated Normal
A80: 221.214 | B80: =IF(ISNUMBER(A80), IF(AND(A80=INT(A80), MOD(A80, 10) = 0), 0, IF(AND(A80=INT(A80), LEN(A80)=2), 1, IF(AND(A80=INT(A80), LEN(A80)=3), 2, LEN(A80) - FIND(".", A80) + 2) ) ), "") -> 5 | C80: Control Drums Materials (Reflector) | D80: =REPT(" ", B80*2) & C80 -> Control Drums Materials (Reflector) | E80: standard | F80: Control Drum Reflector | G80: BeO | K80: =MARVEL_Cost!C27/N80 -> 10062.893 | L80: $/Kg | M80: Control Drum Reflector Mass | N80: ='Design Variables'!B17 -> 318 | O80: Kg | P80: 1 | Q80: 2024 | R80: Material | S80: MARVEL Project | W80: Factory BeO | X80: =0.9*$J80 -> 0 | Y80: =1.5*J80 -> 0 | Z80: Lognormal | AA80: =0.9*K80 -> 9056.6038 | AB80: =1.3*K80 -> 13081.761 | AC80: Lognormal | AD80: 0.1 | AE80: 1 | AF80: 0 | AG80: Truncated Normal
A81: 221.214 | B81: =IF(ISNUMBER(A81), IF(AND(A81=INT(A81), MOD(A81, 10) = 0), 0, IF(AND(A81=INT(A81), LEN(A81)=2), 1, IF(AND(A81=INT(A81), LEN(A81)=3), 2, LEN(A81) - FIND(".", A81) + 2) ) ), "") -> 5 | C81: Control Drums Materials (Reflector) | D81: =REPT(" ", B81*2) & C81 -> Control Drums Materials (Reflector) | E81: standard | F81: Control Drum Reflector | G81: Be | K81: =MARVEL_Cost!C28/N81 -> 44736.842 | L81: $/Kg | M81: Control Drum Reflector Mass | N81: =1000*'Design Variables'!B19 -> 19 | O81: Kg | P81: 1 | Q81: 2024 | R81: Material | S81: MARVEL Project | W81: Factory Be | X81: =0.9*$J81 -> 0 | Y81: =1.5*J81 -> 0 | Z81: Lognormal | AA81: =0.9*K81 -> 40263.158 | AB81: =1.3*K81 -> 58157.895 | AC81: Lognormal | AD81: 0.1 | AE81: 1 | AF81: 0 | AG81: Truncated Normal
A82: 221.214 | B82: =IF(ISNUMBER(A82), IF(AND(A82=INT(A82), MOD(A82, 10) = 0), 0, IF(AND(A82=INT(A82), LEN(A82)=2), 1, IF(AND(A82=INT(A82), LEN(A82)=3), 2, LEN(A82) - FIND(".", A82) + 2) ) ), "") -> 5 | C82: Control Drums Materials (Reflector) | D82: =REPT(" ", B82*2) & C82 -> Control Drums Materials (Reflector) | E82: standard | F82: Control Drum Reflector | G82: Graphite | K82: 80 | L82: $/Kg | M82: Control Drum Reflector Mass | Q82: 2022 | R82: Material | S82: Naranjo de Candido and Shirvan, 2022 | T82: Naranjo De Candido and Shirvan. (2022). Graphite Life-Cycle Cost Model for HTGRs, International High-Level Radioactive Waste Management Conference | W82: Factory Other | X82: =0.9*$J82 -> 0 | Y82: =1.5*J82 -> 0 | Z82: Lognormal | AA82: =0.9*K82 -> 72 | AB82: =1.3*K82 -> 104 | AC82: Lognormal | AD82: 0.1 | AE82: 1 | AF82: 0 | AG82: Truncated Normal
A83: 221.215 | B83: =IF(ISNUMBER(A83), IF(AND(A83=INT(A83), MOD(A83, 10) = 0), 0, IF(AND(A83=INT(A83), LEN(A83)=2), 1, IF(AND(A83=INT(A83), LEN(A83)=3), 2, LEN(A83) - FIND(".", A83) + 2) ) ), "") -> 5 | C83: Control System Drive Mechanism | D83: =REPT(" ", B83*2) & C83 -> Control System Drive Mechanism | E83: standard | K83: 74759 | L83: $/Drum | M83: Drum Count | Q83: 2023 | R83: Lab and Mat and Equip | S83: Prosser et al., 2023 | T83: First-Principles Cost Estimation of a Sodium Fast Reactor Nuclear Plant. INL/RPT-23-74316 Table 38, 39 | V83: Bottom-up Estimation of components with nuclear escalation + contingency | W83: Factory Drums | X83: =0.9*$J83 -> 0 | Y83: =1.5*J83 -> 0 | Z83: Lognormal | AA83: =0.9*K83 -> 67283.1 | AB83: =1.3*K83 -> 97186.7 | AC83: Lognormal | AD83: 0.1 | AE83: 1 | AF83: 0 | AG83: Truncated Normal
A84: 221.3 | B84: =IF(ISNUMBER(A84), IF(AND(A84=INT(A84), MOD(A84, 10) = 0), 0, IF(AND(A84=INT(A84), LEN(A84)=2), 1, IF(AND(A84=INT(A84), LEN(A84)=3), 2, LEN(A84) - FIND(".", A84) + 2) ) ), "") -> 3 | C84: Non-Fuel Core Internals | D84: =REPT(" ", B84*2) & C84 -> Non-Fuel Core Internals | E84: standard
A85: 221.31 | B85: =IF(ISNUMBER(A85), IF(AND(A85=INT(A85), MOD(A85, 10) = 0), 0, IF(AND(A85=INT(A85), LEN(A85)=2), 1, IF(AND(A85=INT(A85), LEN(A85)=3), 2, LEN(A85) - FIND(".", A85) + 2) ) ), "") -> 4 | C85: Reflector | D85: =REPT(" ", B85*2) & C85 -> Reflector | E85: standard | F85: Reflector | G85: BeO | J85: =MARVEL_Cost!C29 -> 120231 | K85: =MARVEL_Cost!C27/N85 -> 10062.893 | L85: $/Kg | M85: Reflector Mass | N85: ='Design Variables'!B17 -> 318 | O85: Kg | P85: 1 | Q85: 2024 | R85: Material | S85: MARVEL Project | T85: Updated MARVEL Cost Estimate + Communication with MARVEL Team | U85: Gerstner, D., & Arafat, Y. (2023). MARVEL 90% Final Design Report (No. INL/RPT-23-74280-Rev000). Idaho National Laboratory (INL), Idaho Falls, ID (United States). Hanna, B. N., Gonzaga de Oliveira, R. G., Mohammad Al Dawood, K. A., Patterson, M. D., Abou Jaoude, A., & Garcia, S. (2024). Technoeconomic Evaluation of Microreactor Using Detailed Bottom-up Estimate (No. INL/RPT-24-80433-Rev000). Idaho National Laboratory (INL), Idaho Falls, ID (United States). | W85: Factory BeO | X85: =0.9*$J85 -> 108207.9 | Y85: =1.5*J85 -> 180346.5 | Z85: Lognormal | AA85: =0.9*K85 -> 9056.6038 | AB85: =1.3*K85 -> 13081.761 | AC85: Lognormal | AD85: 0.1 | AE85: 1 | AF85: 0 | AG85: Truncated Normal
A86: 221.31 | B86: =IF(ISNUMBER(A86), IF(AND(A86=INT(A86), MOD(A86, 10) = 0), 0, IF(AND(A86=INT(A86), LEN(A86)=2), 1, IF(AND(A86=INT(A86), LEN(A86)=3), 2, LEN(A86) - FIND(".", A86) + 2) ) ), "") -> 4 | C86: Reflector | D86: =REPT(" ", B86*2) & C86 -> Reflector | E86: standard | F86: Reflector | G86: Be | K86: =MARVEL_Cost!C28/N81 -> 44736.842 | L86: $/Kg | M86: Reflector Mass | N86: =1000*'Design Variables'!B19 -> 19 | O86: Kg | P86: 1 | Q86: 2024 | R86: Material | S86: MARVEL Project | T86: Updated MARVEL Cost Estimate + Communication with MARVEL Team | W86: Factory Be | X86: =0.9*$J86 -> 0 | Y86: =1.5*J86 -> 0 | Z86: Lognormal | AA86: =0.9*K86 -> 40263.158 | AB86: =1.3*K86 -> 58157.895 | AC86: Lognormal | AD86: 0.1 | AE86: 1 | AF86: 0 | AG86: Truncated Normal
A87: 221.31 | B87: =IF(ISNUMBER(A87), IF(AND(A87=INT(A87), MOD(A87, 10) = 0), 0, IF(AND(A87=INT(A87), LEN(A87)=2), 1, IF(AND(A87=INT(A87), LEN(A87)=3), 2, LEN(A87) - FIND(".", A87) + 2) ) ), "") -> 4 | C87: Reflector | D87: =REPT(" ", B87*2) & C87 -> Reflector | E87: standard | F87: Reflector | G87: Graphite | K87: 80 | L87: $/Kg | M87: Reflector Mass | Q87: 2022 | R87: Material | S87: Naranjo de Candido and Shirvan, 2022 | T87: Naranjo De Candido and Shirvan. (2022). Graphite Life-Cycle Cost Model for HTGRs, International High-Level Radioactive Waste Management Conference | W87: Factory Other | X87: =0.9*$J87 -> 0 | Y87: =1.5*J87 -> 0 | Z87: Lognormal | AA87: =0.9*K87 -> 72 | AB87: =1.3*K87 -> 104 | AC87: Lognormal | AD87: 0.1 | AE87: 1 | AF87: 0 | AG87: Truncated Normal
A88: 221.31 | B88: =IF(ISNUMBER(A88), IF(AND(A88=INT(A88), MOD(A88, 10) = 0), 0, IF(AND(A88=INT(A88), LEN(A88)=2), 1, IF(AND(A88=INT(A88), LEN(A88)=3), 2, LEN(A88) - FIND(".", A88) + 2) ) ), "") -> 4 | C88: Reflector | D88: =REPT(" ", B88*2) & C88 -> Reflector | E88: standard | F88: Reflector | G88: Al2O3 | K88: 134.1 | L88: $/Kg | M88: Reflector Mass | Q88: 2017 | R88: Material | S88: NTRD-FCO-2018-000439 | W88: Factory Other | X88: =0.9*$J88 -> 0 | Y88: =1.5*J88 -> 0 | Z88: Lognormal | AA88: =0.9*K88 -> 120.69 | AB88: =1.3*K88 -> 174.33 | AC88: Lognormal | AD88: 0.1 | AE88: 1 | AF88: 0 | AG88: Truncated Normal
A89: 221.32 | B89: =IF(ISNUMBER(A89), IF(AND(A89=INT(A89), MOD(A89, 10) = 0), 0, IF(AND(A89=INT(A89), LEN(A89)=2), 1, IF(AND(A89=INT(A89), LEN(A89)=3), 2, LEN(A89) - FIND(".", A89) + 2) ) ), "") -> 4 | C89: Shield | D89: =REPT(" ", B89*2) & C89 -> Shield
A90: 221.321 | B90: =IF(ISNUMBER(A90), IF(AND(A90=INT(A90), MOD(A90, 10) = 0), 0, IF(AND(A90=INT(A90), LEN(A90)=2), 1, IF(AND(A90=INT(A90), LEN(A90)=3), 2, LEN(A90) - FIND(".", A90) + 2) ) ), "") -> 5 | C90: In Vessel Shield Materials | D90: =REPT(" ", B90*2) & C90 -> In Vessel Shield Materials | E90: standard | F90: In Vessel Shield Material | G90: B4C_natural | J90: =MARVEL_Cost!C30 -> 647990.6 | K90: =K78 -> 14285.714 | L90: $/Kg | M90: In Vessel Shield Mass | N90: =N78 -> 28 | O90: Kg | P90: 1 | Q90: 2024 | R90: Material | S90: MARVEL Project | W90: Factory Other | X90: =0.9*$J90 -> 583191.54 | Y90: =1.5*J90 -> 971985.9 | Z90: Lognormal | AA90: =0.9*K90 -> 12857.143 | AB90: =1.3*K90 -> 18571.429 | AC90: Lognormal | AD90: 0.1 | AE90: 1 | AF90: 0 | AG90: Truncated Normal
A91: 221.322 | B91: =IF(ISNUMBER(A91), IF(AND(A91=INT(A91), MOD(A91, 10) = 0), 0, IF(AND(A91=INT(A91), LEN(A91)=2), 1, IF(AND(A91=INT(A91), LEN(A91)=3), 2, LEN(A91) - FIND(".", A91) + 2) ) ), "") -> 5 | C91: Out The Vessel Shield Materials | D91: =REPT(" ", B91*2) & C91 -> Out The Vessel Shield Materials | E91: standard | F91: Out Of Vessel Shield Material | G91: WEP | K91: 20 | L91: $/Kg | M91: Out Of Vessel Shield Mass | N91: ='Design Variables'!B43 -> 925.3 | O91: Kg | P91: 1 | Q91: 2024 | R91: Material | S91: MARVEL Project | W91: Factory Other | X91: =0.9*$J91 -> 0 | Y91: =1.5*J91 -> 0 | Z91: Lognormal | AA91: =0.9*K91 -> 18 | AB91: =1.3*K91 -> 26 | AC91: Lognormal | AD91: 0.1 | AE91: 1 | AF91: 0 | AG91: Truncated Normal
A92: 221.33 | B92: =IF(ISNUMBER(A92), IF(AND(A92=INT(A92), MOD(A92, 10) = 0), 0, IF(AND(A92=INT(A92), LEN(A92)=2), 1, IF(AND(A92=INT(A92), LEN(A92)=3), 2, LEN(A92) - FIND(".", A92) + 2) ) ), "") -> 4 | C92: Moderator | D92: =REPT(" ", B92*2) & C92 -> Moderator | E92: standard | F92: Moderator | G92: Graphite | K92: 80 | L92: $/Kg | M92: Moderator Mass | O92: Kg | Q92: 2022 | R92: Material | S92: Naranjo de Candido and Shirvan, 2022 | T92: Naranjo De Candido and Shirvan. (2022). Graphite Life-Cycle Cost Model for HTGRs, International High-Level Radioactive Waste Management Conference | W92: Factory Other | Z92: Lognormal | AA92: =0.9*K92 -> 72 | AB92: =1.3*K92 -> 104 | AC92: Lognormal | AD92: 0.1 | AE92: 1 | AF92: 0 | AG92: Truncated Normal
A93: 221.33 | B93: =IF(ISNUMBER(A93), IF(AND(A93=INT(A93), MOD(A93, 10) = 0), 0, IF(AND(A93=INT(A93), LEN(A93)=2), 1, IF(AND(A93=INT(A93), LEN(A93)=3), 2, LEN(A93) - FIND(".", A93) + 2) ) ), "") -> 4 | C93: Moderator | D93: =REPT(" ", B93*2) & C93 -> Moderator | E93: standard | F93: Moderator | G93: YHx | K93: 4560 | L93: $/Kg | M93: Moderator Mass | O93: Kg | Q93: 2017 | R93: Material | W93: Factory Other | Z93: Lognormal | AA93: =0.9*K93 -> 4104 | AB93: =1.3*K93 -> 5928 | AC93: Lognormal | AD93: 0.1 | AE93: 1 | AF93: 0 | AG93: Truncated Normal
A94: 221.33 | B94: =IF(ISNUMBER(A94), IF(AND(A94=INT(A94), MOD(A94, 10) = 0), 0, IF(AND(A94=INT(A94), LEN(A94)=2), 1, IF(AND(A94=INT(A94), LEN(A94)=3), 2, LEN(A94) - FIND(".", A94) + 2) ) ), "") -> 4 | C94: Moderator | D94: =REPT(" ", B94*2) & C94 -> Moderator | E94: standard | F94: Moderator | G94: ZrH | K94: 1520 | L94: $/Kg | M94: Moderator Mass | O94: Kg | Q94: 2017 | R94: Material | S94: the Fuel SA&I Cost Basis Report | T94: Abou-Jaoude, A., C. S. Lohse, L. M. Larsen, N. Guaita, I. Trivedi, F. C. Joseck, E. Hoffman, N. Stauff, K. Shirvan and A. Stein (2024). Meta-Analysis of Advanced Nuclear Reactor Cost Estimations, Idaho National Laboratory (INL), Idaho Falls, ID (United States). | W94: Factory Other | Z94: Lognormal | AA94: =0.9*K94 -> 1368 | AB94: =1.3*K94 -> 1976 | AC94: Lognormal | AD94: 0.1 | AE94: 1 | AF94: 0 | AG94: Truncated Normal
A95: 221.34 | B95: =IF(ISNUMBER(A95), IF(AND(A95=INT(A95), MOD(A95, 10) = 0), 0, IF(AND(A95=INT(A95), LEN(A95)=2), 1, IF(AND(A95=INT(A95), LEN(A95)=3), 2, LEN(A95) - FIND(".", A95) + 2) ) ), "") -> 4 | C95: Moderator (Booster) | D95: =REPT(" ", B95*2) & C95 -> Moderator (Booster) | E95: standard | F95: Moderator Booster | G95: YHx | K95: 4560 | L95: $/Kg | M95: Moderator Booster Mass | O95: Kg | Q95: 2017 | R95: Material | W95: Factory Other | Z95: Lognormal | AA95: =0.9*K95 -> 4104 | AB95: =1.3*K95 -> 5928 | AC95: Lognormal | AD95: 0.1 | AE95: 1 | AF95: 0 | AG95: Truncated Normal
A96: 221.34 | B96: =IF(ISNUMBER(A96), IF(AND(A96=INT(A96), MOD(A96, 10) = 0), 0, IF(AND(A96=INT(A96), LEN(A96)=2), 1, IF(AND(A96=INT(A96), LEN(A96)=3), 2, LEN(A96) - FIND(".", A96) + 2) ) ), "") -> 4 | C96: Moderator (Booster) | D96: =REPT(" ", B96*2) & C96 -> Moderator (Booster) | E96: standard | F96: Moderator Booster | G96: Graphite | K96: 80 | L96: $/Kg | M96: Moderator Booster Mass | O96: Kg | Q96: 2022 | R96: Material | S96: Naranjo de Candido and Shirvan, 2022 | T96: Naranjo De Candido and Shirvan. (2022). Graphite Life-Cycle Cost Model for HTGRs, International High-Level Radioactive Waste Management Conference | W96: Factory Other | Z96: Lognormal | AA96: =0.9*K96 -> 72 | AB96: =1.3*K96 -> 104 | AC96: Lognormal | AD96: 0.1 | AE96: 1 | AF96: 0 | AG96: Truncated Normal
A97: 221.34 | B97: =IF(ISNUMBER(A97), IF(AND(A97=INT(A97), MOD(A97, 10) = 0), 0, IF(AND(A97=INT(A97), LEN(A97)=2), 1, IF(AND(A97=INT(A97), LEN(A97)=3), 2, LEN(A97) - FIND(".", A97) + 2) ) ), "") -> 4 | C97: Moderator (Booster) | D97: =REPT(" ", B97*2) & C97 -> Moderator (Booster) | E97: standard | F97: Moderator Booster | G97: ZrH | K97: 1520 | L97: $/Kg | M97: Moderator Booster Mass | O97: Kg | Q97: 2017 | R97: Material | S97: the Fuel SA&I Cost Basis Report | T97: Abou-Jaoude, A., C. S. Lohse, L. M. Larsen, N. Guaita, I. Trivedi, F. C. Joseck, E. Hoffman, N. Stauff, K. Shirvan and A. Stein (2024). Meta-Analysis of Advanced Nuclear Reactor Cost Estimations, Idaho National Laboratory (INL), Idaho Falls, ID (United States). | W97: Factory Other | Z97: Lognormal | AA97: =0.9*K97 -> 1368 | AB97: =1.3*K97 -> 1976 | AC97: Lognormal | AD97: 0.1 | AE97: 1 | AF97: 0 | AG97: Truncated Normal
A98: 222 | B98: =IF(ISNUMBER(A98), IF(AND(A98=INT(A98), MOD(A98, 10) = 0), 0, IF(AND(A98=INT(A98), LEN(A98)=2), 1, IF(AND(A98=INT(A98), LEN(A98)=3), 2, LEN(A98) - FIND(".", A98) + 2) ) ), "") -> 2 | C98: Main Heat Transport System | D98: =REPT(" ", B98*2) & C98 -> Main Heat Transport System
A99: 222.1 | B99: =IF(ISNUMBER(A99), IF(AND(A99=INT(A99), MOD(A99, 10) = 0), 0, IF(AND(A99=INT(A99), LEN(A99)=2), 1, IF(AND(A99=INT(A99), LEN(A99)=3), 2, LEN(A99) - FIND(".", A99) + 2) ) ), "") -> 3 | C99: Fluid Circulation Drive System | D99: =REPT(" ", B99*2) & C99 -> Fluid Circulation Drive System
A100: 222.11 | B100: =IF(ISNUMBER(A100), IF(AND(A100=INT(A100), MOD(A100, 10) = 0), 0, IF(AND(A100=INT(A100), LEN(A100)=2), 1, IF(AND(A100=INT(A100), LEN(A100)=3), 2, LEN(A100) - FIND(".", A100) + 2) ) ), "") -> 4 | C100: Primary Pump | D100: =REPT(" ", B100*2) & C100 -> Primary Pump | E100: nonstandard | F100: Primary Pump | G100: Yes | K100: =12.5*705.48 -> 8818.5 | L100: $/(kg.sec) | M100: Primary Pump Mechanical Power | P100: 0.71 | Q100: 2003 | R100: Lab and Mat and Equip | S100: Data from non-nuclear power plant + Ratio of safety grade pump nomalized cost compared to non-safety grade pump is btween 10 and 15 (12.5 ratio was used, from the EEDB (Ganda 2019, Figure 23) | T100: Roosen, P., Uhlenbruck, S., & Lucas, K. (2003). Pareto optimization of a combined cycle power system as a decision support tool for trading off investment vs. operating costs. International Journal of Thermal Sciences, 42(6), 553-560. Ganda, F., Hoffman, E., Taiwo, T. A., Kim, T. K., & Hansen, J. (2019). Report on the ACCERT cost algorithms tool (No. ANL/NSE-19/10). Argonne National Lab.(ANL), Argonne, IL (United States). | U100: https://www.sciencedirect.com/science/article/pii/S1290072903000218 https://publications.anl.gov/anlpubs/2019/06/152862.pdf | W100: Factory Other | X100: =0.9*$J100 -> 0 | Y100: =1.5*J100 -> 0 | Z100: Lognormal | AA100: =0.9*K100 -> 7936.65 | AB100: =1.3*K100 -> 11464.05 | AC100: Lognormal | AD100: 0.1 | AE100: 1 | AF100: 0 | AG100: Truncated Normal
...

Sheet MARVEL_Cost
A1: Account ID | B1: Account Title | C1: TOTAL COST (2024 USD)
A3: 10 | B3: Capitalized Pre-Construction Costs | C3: =C4 -> 5210451
A4: 15 | B4: Plant Studies | C4: 5210451
A5: 20 | B5: Capitalized Direct Costs | C5: =C6+C13+C45+C48+C52+C54 -> 30295715
A6: 21 | B6: Structures and Improvements | C6: =C7+C8+C9+C10 -> 2799006.7
A7: 211 | B7: Site Preparation/Yard Work
A8: 212 | B8: Reactor Island Civil Structures | C8: 2573469.9
A9: 213 | B9: Main Function Buildings
A10: 214 | B10: Buildings to Support Main Function | C10: =SUM(C11:C11) -> 225536.86
A11: 214.7 | B11: Emergency and Start-up Power Systems | C11: 225536.86
A12: 217 | B12: Miscellaneous Other Structures
A13: 22 | B13: Reactor System | C13: =C14+C32+C41+C42+C43+C44 -> 17586713
A14: 221 | B14: Reactor Components | C14: =C15+C19+C25 -> 8937296.6
A15: 221.1 | B15: Reactor vessel and accessories | C15: =C16+C17+C18 -> 2004852
A16: 221.11 | B16: Reactor support | C16: 762382.4
A17: 221.12 | B17: Outer vessel structure | C17: 1201688.6
A18: 221.13 | B18: Inner vessel structure | C18: 40781
A19: 221.2 | B19: Reactor control devices | C19: =C20 -> 2114223
A20: 221.21 | B20: Reactivity control system | C20: =SUM(C21:C23) -> 2114223
A21: 221.211 | B21: Reactivity Control System Fabrication | C21: 1391560
A22: 221.212 | B22: Installation | C22: 322663
A23: 221.213 | B23: Control Drums Materials (Absorber) | C23: 400000
A24: 221.214 | B24: Control Drums Materials (Reflector)
A25: 221.3 | B25: Non-fuel core internals | C25: =C26+C30+C31 -> 4818221.6
A26: 221.31 | B26: Reflector | C26: 4170231
A27: 221.311 | B27: Reflector (Materials: BeO) | C27: 3200000
A28: 221.312 | B28: Reflector (Materials: Be Metal) | C28: 850000
A29: 221.313 | B29: Reflector (installation | C29: 120231
A30: 221.32 | B30: Shield | C30: 647990.6
A31: 221.33 | B31: Moderator | C31: 0
A32: 222 | B32: Main Heat Transport System | C32: =C33+C34+C38+C39+C40 -> 5908950.6
A33: 222.1 | B33: Fluid circulation drive system | C33: 0
A34: 222.2 | B34: Reactor Heat Hransfer Piping System | C34: 4890230.6
A35: 222.21 | B35: Reactor Heat Hransfer Piping System (Mat) | C35: 1520786
A36: 222.22 | B36: Reactor Heat Hransfer Piping System (Fabrication) | C36: 3341486
A37: 222.23 | B37: Reactor Heat Hransfer Piping System (Installation) | C37: 27958.6
A38: 222.3 | B38: Heat Exchangers | C38: 0
A39: 222.4 | B39: Pressurizer System | C39: 0
A40: 222.5 | B40: Initial Heat Transfer Fluid Inventory | C40: 1018720
A41: 224 | B41: Radioactive Byproduct Processing Systems
A42: 226 | B42: Other Reactor Plant Equipment | C42: 456297
A43: 227 | B43: Reactor Instrumentation and Control (I&C) | C43: 2253208.4
A44: 228 | B44: Reactor Plant Miscellaneous Items | C44: 30960
A45: 23 | B45: Energy Conversion System | C45: =C46 -> 0
A46: 232 | B46: Energy Applications | C46: =C47 -> 0
A47: 232.1 | B47: Electricity Generation Systems | C47: 0
A48: 24 | B48: Electrical Equipment | C48: =C49+C50+C51 -> 73415.62
A49: 244 | B49: Protective Systems Equipment | C49: 1627.02
A50: 245 | B50: Electrical Raceway Systems | C50: 0
A51: 246 | B51: Power and Control Cables and Wiring | C51: 71788.6
A52: 25 | B52: Initial Fuel Inventory | C52: =C53 -> 9836580.5
A53: 254 | B53: First Core Fuel Assembly Fabrication | C53: 9836580.5
A54: 26 | B54: Miscellaneous Equipment
A55: 30 | B55: Capitalized Indirect Services Cost | C55: =C56+C58+C62+C65+C68 -> 6442742.5
A56: 31 | B56: Factory & Field Indirect Costs | C56: =C57 -> 1333020.8
A57: 317 | B57: Field Shops | C57: 1333020.8
A58: 33 | B58: Startup Costs | C58: =C59 -> 2407166.4
A59: 331 | B59: Commissioning and Trial Test Runs | C59: =C60+C61 -> 2407166.4
A60: 331.3 | B60: Initial Fuel Loading Operations | C60: 215000
A61: 331.5 | B61: Test Runs | C61: 2192166.4
A62: 34 | B62: Shipping and Transportation Costs | C62: =C63+C64 -> 1665282.8
A63: 341 | B63: Fuel Shipping and Transportation | C63: 1635355.8
A64: 345 | B64: Other Shipping and Transportation Costs | C64: 29927
A65: 35 | B65: Engineering Services | C65: =C66+C67 -> 620313.59
A66: 351 | B66: Off-Site | C66: 257261.4
A67: 352 | B67: On-Site | C67: 363052.19
A68: 36 | B68: PM/CM Services | C68: =C69+C70 -> 416958.94
A69: 361 | B69: Off-Site
A70: 362 | B70: On-Site | C70: 416958.94
A71: 40 | B71: Capitalized Training Costs | C71: =C72 -> 4169765
A72: 41 | B72: Staff Recruitment and Training | C72: 4169765
A73: 50 | B73: Capitalized Supplementary Costs | C73: =C74 -> 16408782
A74: 54 | B74: Decommissioning | C74: 16408782
A75: 60 | B75: Capitalized Financial Costs | C75: =C76 -> 6160606
A76: 61 | B76: Escalation | C76: 6160606
A77: 70 | B77: Annualized O&M Cost | C77: =C78 -> 2456659.2
A78: 71 | B78: O&M Staff | C78: 2456659.2
A79: Non-Recurrung Costs | B79: Non-Recurrung Costs | C79: 33779050

Sheet Design Variables
A1: Variable | B1: Value | C1: Units | D1: Description
A2: Overall System
A3: Thermal power | B3: 83 | C3: kWth | D3: —
A4: Electric Power | B4: 20 | C4: kWe
A5: Core outer radius | B5: 5.5 | C5: inches | D5: —
A6: Reflector outer radius | B6: 16.5 | C6: inches | D6: —
A7: Fuel
A8: Fuel mass | B8: 145.3 | C8: kg | D8: UZrH
A9: U Weight fraction | B9: 30 | C9: wt% | D9: U/UZrH
A10: U enrichment | B10: 19.75 | C10: wt% | D10: High-assay low-enriched uranium (HALEU)
A11: Pins | B11: 36 | C11: # | D11: —
A12: Reflector
A13: Outer reflector material | B13: BeO | C13: — | D13: 99% theoretical density
A14: Elements | B14: 124 | C14: # | D14: Quarter plates
A15: Reflector plate thickness | B15: 1 | C15: inches | D15: —
A16: Reflector plate volume | B16: 818.4 | C16: cm3/plate | D16: —
A17: Mass of BeO reflector | B17: 318 | C17: Kg
A18: Insert volume | B18: 570 | C18: cm3/plate | D18: —
A19: Mass of Be-metal reflector | B19: 0.019 | C19: MT | D19: —
A20: Control Elements
A21: Control drums | B21: 4 | C21: # | D21: —
A22: Shutdown rods | B22: 1 | C22: # | D22: —
A23: Control drum elements | B23: 124 | C23: # | D23: Discs
A24: Drum disc thickness | B24: 1 | C24: inches | D24: —
A25: Drum reflector volume | B25: 880.8 | C25: cm3/plate | D25: BeO 99%
A26: Mass of drum reflector | B26: 309 | C26: Kg | D26: —
A27: Drum poison volume | B27: 49.2 | C27: cm3/plate | D27: B4C
A28: Mass of drum poison | B28: 14 | C28: Kg | D28: —
A29: Mass of rod poison | B29: 14 | C29: Kg | D29: B4C
A30: Instruments and Controls
A31: Control cabinet | B31: 5 | D31: —
A32: Instrument cabinet | B32: 2 | D32: —
A33: Nuclear input/output (IO) | B33: 9 | D33: —
A34: Non-nuclear IO | B34: 213 | D34: —
A35: Stirling engine IO | B35: 48 | C35: — | D35: These should be excluded if there no stirling engine?
A36: TOTAL | B36: 277
A37: Shielding in Vessel
A38: Stainless Steel cans | B38: 54.2 | C38: Kg | D38: Stainless Steel cans of the boron carbide shielding material (SS316H)
A39: Gamma shield material | B39: 56.3 | C39: Kg | D39: Gamma shield material inside the guard vessel (of Tungsten)
A40: Neutron shield material in the guard vessel | B40: 39.7 | C40: Kg | D40: made of natural B4C powder and is located above the core (a donut around the core barrel)—
A41: Boron Carbine shielding | B41: 95.3 | C41: Kg | D41: made of natural B4C (called base shield) below the core
A42: Radial (lead) | B42: 2571.9 | C42: Kg | D42: lead
A43: Radial (WEP) | B43: 925.3 | C43: Kg | D43: made of Water Extended Polyster (WEP)
A44: Shielding in Pit
A45: Mass of the pit neutron shielding | B45: 8.3 | C45: MT | D45: Approximated 6-in.-thick covering whole pit and made of Water-extruded poly (WEP)
A46: Heat Transfer
A47: Mass of coolant | B47: 156 | C47: Kg | D47: —
A48: Number of loops | B48: 4 | C48: # | D48: —
A49: Mass of PCSs | B49: 0.86 | C49: MT | D49: SS316H
A50: Subassembly Structure Masses
A51: Reactor support frame | B51: 1.11 | C51: MT | D51: —
A52: Guard vessel | B52: 1.587 | C52: MT | D52: —

Sheet Inflation Adjustment
A1: Year | B1: General | C1: Labor | D1: Material | E1: Equipment | F1: Lab and Mat and Equip | G1: Lab and Equip
A2: 1985 | B2: 2.4640874 | C2: 3.1848907 | D2: 3.0544914 | E2: 3.8305631 | F2: =(C2+D2+E2)/3 -> 3.3566484 | G2: =AVERAGE(C2,E2) -> 3.5077269
A3: =+A2+1 -> 1986 | B3: 2.4153374 | C3: 3.0852191 | D3: 3.0606568 | E3: 3.7330963 | F3: =(C3+D3+E3)/3 -> 3.2929907 | G3: =AVERAGE(C3,E3) -> 3.4091577
A4: =+A3+1 -> 1987 | B4: 2.3571109 | C4: 2.9915966 | D4: 2.9991875 | E4: 3.6990765 | F4: =(C4+D4+E4)/3 -> 3.2299536 | G4: =AVERAGE(C4,E4) -> 3.3453366
A5: =+A4+1 -> 1988 | B5: 2.2768417 | C5: 2.8748318 | D5: 2.8405735 | E5: 3.5245615 | F5: =(C5+D5+E5)/3 -> 3.0799889 | G5: =AVERAGE(C5,E5) -> 3.1996966
A6: =+A5+1 -> 1989 | B6: 2.1907944 | C6: 2.78125 | D6: 2.7498305 | E6: 3.3126659 | F6: =(C6+D6+E6)/3 -> 2.9479155 | G6: =AVERAGE(C6,E6) -> 3.046958
A7: =+A6+1 -> 1990 | B7: 2.1115837 | C7: 2.6589212 | D7: 2.7465738 | E7: 3.2240826 | F7: =(C7+D7+E7)/3 -> 2.8765258 | G7: =AVERAGE(C7,E7) -> 2.9415019
A8: =+A7+1 -> 1991 | B8: 2.0426379 | C8: 2.5540056 | D8: 2.7290821 | E8: 3.1182024 | F8: =(C8+D8+E8)/3 -> 2.80043 | G8: =AVERAGE(C8,E8) -> 2.836104
A9: =+A8+1 -> 1992 | B9: 1.9971771 | C9: 2.4750869 | D9: 2.6817441 | E9: 2.9899601 | F9: =(C9+D9+E9)/3 -> 2.715597 | G9: =AVERAGE(C9,E9) -> 2.7325235
A10: =+A9+1 -> 1993 | B10: 1.9508958 | C10: 2.3964099 | D10: 2.5547123 | E10: 2.8240631 | F10: =(C10+D10+E10)/3 -> 2.5917284 | G10: =AVERAGE(C10,E10) -> 2.6102365
A11: =+A10+1 -> 1994 | B11: 1.9101281 | C11: 2.3108547 | D11: 2.4545088 | E11: 2.7417224 | F11: =(C11+D11+E11)/3 -> 2.5023619 | G11: =AVERAGE(C11,E11) -> 2.5262885
A12: =+A11+1 -> 1995 | B12: 1.8708477 | C12: 2.27073 | D12: 2.3662637 | E12: 2.6948515 | F12: =(C12+D12+E12)/3 -> 2.4439484 | G12: =AVERAGE(C12,E12) -> 2.4827907
A13: =+A12+1 -> 1996 | B13: 1.8372585 | C13: 2.2150017 | D13: 2.3528479 | E13: 2.6375049 | F13: =(C13+D13+E13)/3 -> 2.4017848 | G13: =AVERAGE(C13,E13) -> 2.4262533
A14: =+A13+1 -> 1997 | B14: 1.8060906 | C14: 2.1583025 | D14: 2.3124125 | E14: 2.5759924 | F14: =(C14+D14+E14)/3 -> 2.3489024 | G14: =AVERAGE(C14,E14) -> 2.3671474
... A39: =+A38+1 -> 2022 | B39: 1.0615669 | C39: 1.0737265 | D39: 0.96194441 | E39: 1.0847449 | F39: =(C39+D39+E39)/3 -> 1.0401386 | G39: =AVERAGE(C39,E39) -> 1.0792357
A40: 2023 | B40: 1.0242342 | C40: 1.029563 | D40: 0.9902105 | E40: 1.0049167 | F40: =(C40+D40+E40)/3 -> 1.0082301 | G40: =AVERAGE(C40,E40) -> 1.0172399
A41: 2024 | B41: 1 | C41: 1 | D41: 1 | E41: 1 | F41: =(C41+D41+E41)/3 -> 1 | G41: =AVERAGE(C41,E41) -> 1

Sheet Economics Parameters
A1: Parameter | B1: Value | C1: Note | D1: Reference | E1: Notes
A2: indirect to direct field-related cost | B2: 0.065389932
A3: FTEs Per Onsite Operator (24/7) | B3: 5
A4: FTEs Per Offsite Operator (24/7) | B4: 5
A5: FTEs Per Security Staff (24/7) | B5: 5
A6: Hours Per FTE | B6: 1800
A7: Work Hours Per Shift | B7: 10
A8: Maintenance to Direct Cost Ratio | B8: 0.01
A9: Onsite Learning | B9: 0.08 | C9: FOAK to NOAK Learning Rates | D9: Assessment of Factory Fabrication Considerations for Nuclear Microreactors 10.1080/00295450.2023.2206779 | E9: Calculated based on Refernce Paper + Gyutae's work. Refer to TEM Slides for rationale and methodology
A10: No Learning | B10: 0
A11: Licensing Learning | B11: 0
A12: Factory Primary Structure | B12: 0.1844317
A13: Factory Drums | B13: 0.24138
A14: Factory Other | B14: 0.22962848
A15: Factory Be | B15: 0.41505378
A16: Factory BeO | B16: 0.39914906
A17: Non-nuclear off-the-shelf | B17: 0.05 | D17: Park, et al., Bottom-up levelized cost estimation of low-enriched and low-pressure nuclear batteries. Nuclear Engineering and Design. 2025. | E17: For off-the-shelf commercial components that are not produced in the FB Factory
